Workbook

Sheet Cover
B2: INFOSYS LIMITED
B3: Financial Statement & Valuation Analysis
B4: Comparative & Common-Size Analysis | Ratio Analysis | Predictability Scores | DCF & Comparable-Company Valuation
B6: Company | C6: Infosys Limited (NSE/BSE: INFY) - Consolidated financial statements
B8: Financial years covered | C8: FY2023-24, FY2024-25, FY2025-26 (year ended March 31); DCF forecast FY2026-27E to FY2030-31E
B10: Source documents | C10: Infosys Integrated Annual Report 2024-25; Infosys Integrated Annual Report 2025-26; Infosys IR three-year overview (IFRS); TCS/HCL Tech/Wipro/Tech Mahindra annual reports & screener.in
B12: Market data as of | C12: 6-12 August 2026 (NSE) — see individual sheets for exact dates/sources
B14: Currency / units | C14: All figures in ₹ Crore (1 crore = 10 million) unless stated otherwise
B19: Contents
B21: Comparative & Common-Size Analysis, Trend Analysis
B22: • | C22: Data-BS / Data-PL / Data-CF — 3-year consolidated source figures (Balance Sheet, P&L, Cash Flow)
B23: • | C23: Comparative BS — FY24-25-26, ₹ and % change, with observations
B24: • | C24: Comparative PL — FY24-25-26, ₹ and % change, with observations
B25: • | C25: Common-Size BS — % of Total Assets, with observations
B26: • | C26: Common-Size PL — % of Revenue, with observations
B27: • | C27: Trend Analysis — Index, FY24 = 100, with observations
B29: Ratio Analysis
B30: • | C30: Ratio - Cover & Notes — methodology, sources & conventions for the ratio module
B31: • | C31: Input Data — Infosys FY25/FY26 input figures (IFRS three-year overview basis)
B32: • | C32: Ratio Analysis — all 19 ratios: Liquidity, Profitability, Efficiency, Solvency, Market — formula + calculation + interpretation
B33: • | C33: Peer Input Data — TCS & HCL Tech input figures
B34: • | C34: Peer Comparison — Infosys vs TCS vs HCL Tech, ratio-by-ratio benchmarking
B36: Predictability Scores
B37: • | C37: Predictability Scores — Altman Z-Score (3-yr trend) and Beneish M-Score (FY25→FY26), with interpretation
B39: Valuation - Method 1: DCF
B40: • | C40: DCF - Cover & Notes — model map & headline outputs
B41: • | C41: All-in-One DCF — entire model on one sheet (assumptions through valuation)
B42: • | C42: Assumptions — revenue/margin/working-capital drivers, WACC build-up, terminal growth, share data
B43: • | C43: Income Statement — FY24A-FY26A actuals & FY27E-FY31E forecast
B44: • | C44: Balance Sheet — fully linked, FY24A-FY31E
B45: • | C45: Cash Flow — statement of cash flows & FCF build
B46: • | C46: WC & PPE Schedule — working capital and fixed-asset roll-forward
B47: • | C47: Capital Structure — debt, cash & WACC support schedule
B48: • | C48: DCF Valuation — FCFF build, EV-to-equity bridge, intrinsic value & sensitivity table
B49: • | C49: Charts & Outputs — output dashboard and charts
B51: Valuation - Method 2: Comparable Companies
B52: • | C52: Comps - EV Multiples — EV/EBITDA, EV/EBIT, EV/Revenue, P/E for 4 peers (TCS, HCL Tech, Wipro, Tech Mahindra); mean/median/min/max and implied valuation of Infosys
B55: Note on conventions: Blue text = hardcoded source figures / inputs (cited). Black text = formulas. Green text = links pulling from another sheet. Yellow fill = key assumptions you can flex. The Ratio Analysis, Peer Comparison and full DCF modules were built and supplied directly; this workbook integrates them alongside the comparative/common-size/trend/predictability-score analysis and the EV-multiples comparable-company valuation into a single consolidated file. All formulas recalculate automatically if source or assumption cells are changed.

Sheet Data-BS
A1: Infosys Limited — Consolidated Balance Sheet (Source Data, ₹ Crore)
B3: Particulars | D3: FY2024 | E3: FY2025 | F3: FY2026
B4: ASSETS
B5: Non-current assets
B6: Property, plant and equipment | D6: 12370 | E6: 11778 | F6: 12651
B7: Right-of-use assets | D7: 6552 | E7: 6311 | F7: 6177
B8: Capital work-in-progress | D8: 293 | E8: 814 | F8: 526
B9: Goodwill | D9: 7303 | E9: 10106 | F9: 12117
B10: Other intangible assets | D10: 1397 | E10: 2766 | F10: 2825
B11: Non-current investments | D11: 11708 | E11: 11059 | F11: 8930
B12: Loans (non-current) | D12: 34 | E12: 16 | F12: 6
B13: Other financial assets (non-current) | D13: 3105 | E13: 3511 | F13: 2776
B14: Deferred tax assets (net) | D14: 454 | E14: 1108 | F14: 2264
B15: Income tax assets (net) - non-current | D15: 3045 | E15: 1622 | F15: 666
B16: Other non-current assets | D16: 2121 | E16: 2713 | F16: 3540
B17: Total non-current assets | D17: =SUM(D6:D16) -> 48382 | E17: =SUM(E6:E16) -> 51804 | F17: =SUM(F6:F16) -> 52478
B18: Current assets
B19: Current investments | D19: 12915 | E19: 12482 | F19: 12950
B20: Trade receivables | D20: 30193 | E20: 31158 | F20: 35234
B21: Cash and cash equivalents | D21: 14786 | E21: 24455 | F21: 22201
B22: Loans (current) | D22: 248 | E22: 249 | F22: 234
B23: Other financial assets (current) | D23: 12085 | E23: 13840 | F23: 15890
B24: Income tax assets (net) - current | D24: 6397 | E24: 2975 | F24: 1835
B25: Other current assets | D25: 12808 | E25: 11940 | F25: 15145
B26: Total current assets | D26: =SUM(D19:D25) -> 89432 | E26: =SUM(E19:E25) -> 97099 | F26: =SUM(F19:F25) -> 103489
B27: TOTAL ASSETS | D27: =D17+D26 -> 137814 | E27: =E17+E26 -> 148903 | F27: =F17+F26 -> 155967
B28: EQUITY AND LIABILITIES
B29: Equity
B30: Equity share capital | D30: 2071 | E30: 2073 | F30: 2024
B31: Other equity | D31: 86045 | E31: 93745 | F31: 90828
B32: Total equity attributable to owners | D32: =D30+D31 -> 88116 | E32: =E30+E31 -> 95818 | F32: =F30+F31 -> 92852
B33: Non-controlling interests | D33: 345 | E33: 385 | F33: 445
B34: Total equity | D34: =D32+D33 -> 88461 | E34: =E32+E33 -> 96203 | F34: =F32+F33 -> 93297
B35: Non-current liabilities
B36: Lease liabilities (non-current) | D36: 6400 | E36: 5772 | F36: 6016
B37: Other financial liabilities (non-current) | D37: 2130 | E37: 2141 | F37: 2092
B38: Deferred tax liabilities (net) | D38: 1794 | E38: 1722 | F38: 1679
B39: Other non-current liabilities | D39: 235 | E39: 215 | F39: 561
B40: Total non-current liabilities | D40: =SUM(D36:D39) -> 10559 | E40: =SUM(E36:E39) -> 9850 | F40: =SUM(F36:F39) -> 10348
B41: Current liabilities
B42: Lease liabilities (current) | D42: 1959 | E42: 2455 | F42: 3160
B43: Trade payables | D43: 3956 | E43: 4164 | F43: 4744
B44: Other financial liabilities (current) | D44: 16959 | E44: 18138 | F44: 21483
B45: Other current liabilities | D45: 10539 | E45: 11765 | F45: 15779
B46: Provisions | D46: 1796 | E46: 1475 | F46: 1512
B47: Income tax liabilities (net) | D47: 3585 | E47: 4853 | F47: 5644
B48: Total current liabilities | D48: =SUM(D42:D47) -> 38794 | E48: =SUM(E42:E47) -> 42850 | F48: =SUM(F42:F47) -> 52322
B49: TOTAL EQUITY AND LIABILITIES | D49: =D34+D40+D48 -> 137814 | E49: =E34+E40+E48 -> 148903 | F49: =F34+F40+F48 -> 155967
B51: Source: Infosys Integrated Annual Report 2024-25 (Consolidated Balance Sheet, p.302-303) and Infosys Integrated Annual Report 2025-26 (Consolidated Balance Sheet, p.316-317), as furnished by user.

Sheet Data-PL
A1: Infosys Limited — Consolidated Statement of Profit & Loss (Source Data, ₹ Crore)
B3: Particulars | D3: FY2024 | E3: FY2025 | F3: FY2026
B4: Revenue from operations | D4: 153670 | E4: 162990 | F4: 178650
B5: Other income, net | D5: 4711 | E5: 3600 | F5: 4322
B6: Total income | D6: =D4+D5 -> 158381 | E6: =E4+E5 -> 166590 | F6: =F4+F5 -> 182972
B7: EXPENSES
B8: Employee benefit expenses | D8: 82620 | E8: 85950 | F8: 95094
B9: Cost of technical sub-contractors | D9: 12232 | E9: 12937 | F9: 15421
B10: Travel expenses | D10: 1759 | E10: 1894 | F10: 2097
B11: Cost of software packages and others | D11: 13515 | E11: 15911 | F11: 15722
B12: Communication expenses | D12: 677 | E12: 620 | F12: 603
B13: Consultancy and professional charges | D13: 1726 | E13: 1655 | F13: 2090
B14: Depreciation and amortization expenses | D14: 4678 | E14: 4812 | F14: 4902
B15: Finance cost | D15: 470 | E15: 416 | F15: 416
B16: Other expenses | D16: 4716 | E16: 4787 | F16: 5343
B17: Total expenses | D17: =SUM(D8:D16) -> 122393 | E17: =SUM(E8:E16) -> 128982 | F17: =SUM(F8:F16) -> 141688
B18: Profit before exceptional item and tax | D18: =D6-D17 -> 35988 | E18: =E6-E17 -> 37608 | F18: =F6-F17 -> 41284
B19: Exceptional item (Impact of Labour Codes) | D19: 0 | E19: 0 | F19: 1289
B20: Profit before tax | D20: =D18-D19 -> 35988 | E20: =E18-E19 -> 37608 | F20: =F18-F19 -> 39995
B21: Current tax | D21: 8390 | E21: 12130 | F21: 11767
B22: Deferred tax | D22: 1350 | E22: -1272 | F22: -1246
B23: Total tax expense | D23: =D21+D22 -> 9740 | E23: =E21+E22 -> 10858 | F23: =F21+F22 -> 10521
B24: Profit for the year | D24: =D20-D23 -> 26248 | E24: =E20-E23 -> 26750 | F24: =F20-F23 -> 29474
B25: Profit attributable to owners of the Company | D25: 26233 | E25: 26713 | F25: 29440
B26: Profit attributable to non-controlling interests | D26: 15 | E26: 37 | F26: 34
B27: EPS — Basic (₹) | D27: 63.39 | E27: 64.5 | F27: 71.58
B28: EPS — Diluted (₹) | D28: 63.29 | E28: 64.34 | F28: 71.46
B29: Weighted avg equity shares — Basic (Cr) | D29: 413.86 | E29: 414.16 | F29: 411.28
B30: Weighted avg equity shares — Diluted (Cr) | D30: 414.47 | E30: 415.21 | F30: 412.01
B32: Source: Infosys Integrated Annual Report 2024-25 & 2025-26, Consolidated Statement of Profit and Loss, as furnished by user.

Sheet Data-CF
A1: Infosys Limited — Consolidated Statement of Cash Flows (Source Data, ₹ Crore)
B3: Particulars | C3: FY2024 | D3: FY2025 | E3: FY2026
B4: Net cash generated by operating activities (CFO) | C4: 25210 | D4: 35694 | E4: 33986
B5: Net cash from / (used in) investing activities (CFI) | C5: -5009 | D5: -1946 | E5: 1946
B6: Net cash used in financing activities (CFF) | C6: -17504 | D6: -24161 | E6: -39786
B7: Net increase / (decrease) in cash and cash equivalents | C7: =C4+C5+C6 -> 2697 | D7: =D4+D5+D6 -> 9587 | E7: =E4+E5+E6 -> -3854
B8: Cash and cash equivalents — opening | C8: 12173 | D8: 14786 | E8: 24455
B9: Effect of exchange rate changes | C9: -84 | D9: 82 | E9: 1600
B10: Cash and cash equivalents — closing | C10: 14786 | D10: 24455 | E10: 22201
B12: Memo: Capital expenditure (PPE & intangibles) | C12: 2201 | D12: 2237 | E12: 2727
B13: Memo: Dividends paid (cash flow statement) | C13: 14692 | D13: 20287 | E13: 18653
B14: Memo: Buyback of equity shares | C14: 0 | D14: 0 | E14: 18058
B15: Memo: Depreciation & amortization (non-cash add-back) | C15: 4678 | D15: 4812 | E15: 4902
B18: Source: Infosys Integrated Annual Report 2024-25 & 2025-26, Consolidated Statement of Cash Flows, as furnished by user.

Sheet Comparative BS
A1: Comparative Balance Sheet — Infosys Limited (Consolidated)
B3: All ₹ in Crore. FY25 vs FY24 and FY26 vs FY25 shown side by side.
B4: Particulars | C4: FY2024 | D4: FY2025 | E4: FY2026 | F4: Change ₹ (FY25 vs FY24) | G4: Change % (FY25 vs FY24) | H4: Change ₹ (FY26 vs FY25) | I4: Change % (FY26 vs FY25)
B5: ASSETS
B6: Non-current assets
B7: Property, plant and equipment | C7: ='Data-BS'!D6 -> 12370 | D7: ='Data-BS'!E6 -> 11778 | E7: ='Data-BS'!F6 -> 12651 | F7: =D7-C7 -> -592 | G7: =IFERROR(F7/C7,"n.m.") -> -0.04785772 | H7: =E7-D7 -> 873 | I7: =IFERROR(H7/D7,"n.m.") -> 0.074121243
B8: Right-of-use assets | C8: ='Data-BS'!D7 -> 6552 | D8: ='Data-BS'!E7 -> 6311 | E8: ='Data-BS'!F7 -> 6177 | F8: =D8-C8 -> -241 | G8: =IFERROR(F8/C8,"n.m.") -> -0.036782662 | H8: =E8-D8 -> -134 | I8: =IFERROR(H8/D8,"n.m.") -> -0.021232768
B9: Capital work-in-progress | C9: ='Data-BS'!D8 -> 293 | D9: ='Data-BS'!E8 -> 814 | E9: ='Data-BS'!F8 -> 526 | F9: =D9-C9 -> 521 | G9: =IFERROR(F9/C9,"n.m.") -> 1.778157 | H9: =E9-D9 -> -288 | I9: =IFERROR(H9/D9,"n.m.") -> -0.35380835
B10: Goodwill | C10: ='Data-BS'!D9 -> 7303 | D10: ='Data-BS'!E9 -> 10106 | E10: ='Data-BS'!F9 -> 12117 | F10: =D10-C10 -> 2803 | G10: =IFERROR(F10/C10,"n.m.") -> 0.38381487 | H10: =E10-D10 -> 2011 | I10: =IFERROR(H10/D10,"n.m.") -> 0.1989907
B11: Other intangible assets | C11: ='Data-BS'!D10 -> 1397 | D11: ='Data-BS'!E10 -> 2766 | E11: ='Data-BS'!F10 -> 2825 | F11: =D11-C11 -> 1369 | G11: =IFERROR(F11/C11,"n.m.") -> 0.97995705 | H11: =E11-D11 -> 59 | I11: =IFERROR(H11/D11,"n.m.") -> 0.021330441
B12: Non-current investments | C12: ='Data-BS'!D11 -> 11708 | D12: ='Data-BS'!E11 -> 11059 | E12: ='Data-BS'!F11 -> 8930 | F12: =D12-C12 -> -649 | G12: =IFERROR(F12/C12,"n.m.") -> -0.055432183 | H12: =E12-D12 -> -2129 | I12: =IFERROR(H12/D12,"n.m.") -> -0.19251289
B13: Loans (non-current) | C13: ='Data-BS'!D12 -> 34 | D13: ='Data-BS'!E12 -> 16 | E13: ='Data-BS'!F12 -> 6 | F13: =D13-C13 -> -18 | G13: =IFERROR(F13/C13,"n.m.") -> -0.52941176 | H13: =E13-D13 -> -10 | I13: =IFERROR(H13/D13,"n.m.") -> -0.625
B14: Other financial assets (non-current) | C14: ='Data-BS'!D13 -> 3105 | D14: ='Data-BS'!E13 -> 3511 | E14: ='Data-BS'!F13 -> 2776 | F14: =D14-C14 -> 406 | G14: =IFERROR(F14/C14,"n.m.") -> 0.13075684 | H14: =E14-D14 -> -735 | I14: =IFERROR(H14/D14,"n.m.") -> -0.20934207
B15: Deferred tax assets (net) | C15: ='Data-BS'!D14 -> 454 | D15: ='Data-BS'!E14 -> 1108 | E15: ='Data-BS'!F14 -> 2264 | F15: =D15-C15 -> 654 | G15: =IFERROR(F15/C15,"n.m.") -> 1.4405286 | H15: =E15-D15 -> 1156 | I15: =IFERROR(H15/D15,"n.m.") -> 1.0433213
B16: Income tax assets (net) - non-current | C16: ='Data-BS'!D15 -> 3045 | D16: ='Data-BS'!E15 -> 1622 | E16: ='Data-BS'!F15 -> 666 | F16: =D16-C16 -> -1423 | G16: =IFERROR(F16/C16,"n.m.") -> -0.46732348 | H16: =E16-D16 -> -956 | I16: =IFERROR(H16/D16,"n.m.") -> -0.58939581
B17: Other non-current assets | C17: ='Data-BS'!D16 -> 2121 | D17: ='Data-BS'!E16 -> 2713 | E17: ='Data-BS'!F16 -> 3540 | F17: =D17-C17 -> 592 | G17: =IFERROR(F17/C17,"n.m.") -> 0.27911363 | H17: =E17-D17 -> 827 | I17: =IFERROR(H17/D17,"n.m.") -> 0.3048286
B18: Total non-current assets | C18: ='Data-BS'!D17 -> 48382 | D18: ='Data-BS'!E17 -> 51804 | E18: ='Data-BS'!F17 -> 52478 | F18: =D18-C18 -> 3422 | G18: =IFERROR(F18/C18,"n.m.") -> 0.070728783 | H18: =E18-D18 -> 674 | I18: =IFERROR(H18/D18,"n.m.") -> 0.013010578
B19: Current assets
B20: Current investments | C20: ='Data-BS'!D19 -> 12915 | D20: ='Data-BS'!E19 -> 12482 | E20: ='Data-BS'!F19 -> 12950 | F20: =D20-C20 -> -433 | G20: =IFERROR(F20/C20,"n.m.") -> -0.033526907 | H20: =E20-D20 -> 468 | I20: =IFERROR(H20/D20,"n.m.") -> 0.037493991
B21: Trade receivables | C21: ='Data-BS'!D20 -> 30193 | D21: ='Data-BS'!E20 -> 31158 | E21: ='Data-BS'!F20 -> 35234 | F21: =D21-C21 -> 965 | G21: =IFERROR(F21/C21,"n.m.") -> 0.031961051 | H21: =E21-D21 -> 4076 | I21: =IFERROR(H21/D21,"n.m.") -> 0.13081713
B22: Cash and cash equivalents | C22: ='Data-BS'!D21 -> 14786 | D22: ='Data-BS'!E21 -> 24455 | E22: ='Data-BS'!F21 -> 22201 | F22: =D22-C22 -> 9669 | G22: =IFERROR(F22/C22,"n.m.") -> 0.65392939 | H22: =E22-D22 -> -2254 | I22: =IFERROR(H22/D22,"n.m.") -> -0.092169291
B23: Loans (current) | C23: ='Data-BS'!D22 -> 248 | D23: ='Data-BS'!E22 -> 249 | E23: ='Data-BS'!F22 -> 234 | F23: =D23-C23 -> 1 | G23: =IFERROR(F23/C23,"n.m.") -> 0.0040322581 | H23: =E23-D23 -> -15 | I23: =IFERROR(H23/D23,"n.m.") -> -0.060240964
B24: Other financial assets (current) | C24: ='Data-BS'!D23 -> 12085 | D24: ='Data-BS'!E23 -> 13840 | E24: ='Data-BS'!F23 -> 15890 | F24: =D24-C24 -> 1755 | G24: =IFERROR(F24/C24,"n.m.") -> 0.14522135 | H24: =E24-D24 -> 2050 | I24: =IFERROR(H24/D24,"n.m.") -> 0.14812139
B25: Income tax assets (net) - current | C25: ='Data-BS'!D24 -> 6397 | D25: ='Data-BS'!E24 -> 2975 | E25: ='Data-BS'!F24 -> 1835 | F25: =D25-C25 -> -3422 | G25: =IFERROR(F25/C25,"n.m.") -> -0.53493825 | H25: =E25-D25 -> -1140 | I25: =IFERROR(H25/D25,"n.m.") -> -0.38319328
B26: Other current assets | C26: ='Data-BS'!D25 -> 12808 | D26: ='Data-BS'!E25 -> 11940 | E26: ='Data-BS'!F25 -> 15145 | F26: =D26-C26 -> -868 | G26: =IFERROR(F26/C26,"n.m.") -> -0.067770144 | H26: =E26-D26 -> 3205 | I26: =IFERROR(H26/D26,"n.m.") -> 0.26842546
B27: Total current assets | C27: ='Data-BS'!D26 -> 89432 | D27: ='Data-BS'!E26 -> 97099 | E27: ='Data-BS'!F26 -> 103489 | F27: =D27-C27 -> 7667 | G27: =IFERROR(F27/C27,"n.m.") -> 0.08572994 | H27: =E27-D27 -> 6390 | I27: =IFERROR(H27/D27,"n.m.") -> 0.065809123
B28: TOTAL ASSETS | C28: ='Data-BS'!D27 -> 137814 | D28: ='Data-BS'!E27 -> 148903 | E28: ='Data-BS'!F27 -> 155967 | F28: =D28-C28 -> 11089 | G28: =IFERROR(F28/C28,"n.m.") -> 0.080463523 | H28: =E28-D28 -> 7064 | I28: =IFERROR(H28/D28,"n.m.") -> 0.04744028
B29: EQUITY AND LIABILITIES
B30: Equity
B31: Equity share capital | C31: ='Data-BS'!D30 -> 2071 | D31: ='Data-BS'!E30 -> 2073 | E31: ='Data-BS'!F30 -> 2024 | F31: =D31-C31 -> 2 | G31: =IFERROR(F31/C31,"n.m.") -> 0.00096571704 | H31: =E31-D31 -> -49 | I31: =IFERROR(H31/D31,"n.m.") -> -0.023637241
B32: Other equity | C32: ='Data-BS'!D31 -> 86045 | D32: ='Data-BS'!E31 -> 93745 | E32: ='Data-BS'!F31 -> 90828 | F32: =D32-C32 -> 7700 | G32: =IFERROR(F32/C32,"n.m.") -> 0.089488059 | H32: =E32-D32 -> -2917 | I32: =IFERROR(H32/D32,"n.m.") -> -0.031116326
B33: Total equity attributable to owners | C33: ='Data-BS'!D32 -> 88116 | D33: ='Data-BS'!E32 -> 95818 | E33: ='Data-BS'!F32 -> 92852 | F33: =D33-C33 -> 7702 | G33: =IFERROR(F33/C33,"n.m.") -> 0.087407508 | H33: =E33-D33 -> -2966 | I33: =IFERROR(H33/D33,"n.m.") -> -0.030954518
B34: Non-controlling interests | C34: ='Data-BS'!D33 -> 345 | D34: ='Data-BS'!E33 -> 385 | E34: ='Data-BS'!F33 -> 445 | F34: =D34-C34 -> 40 | G34: =IFERROR(F34/C34,"n.m.") -> 0.11594203 | H34: =E34-D34 -> 60 | I34: =IFERROR(H34/D34,"n.m.") -> 0.15584416
B35: Total equity | C35: ='Data-BS'!D34 -> 88461 | D35: ='Data-BS'!E34 -> 96203 | E35: ='Data-BS'!F34 -> 93297 | F35: =D35-C35 -> 7742 | G35: =IFERROR(F35/C35,"n.m.") -> 0.087518794 | H35: =E35-D35 -> -2906 | I35: =IFERROR(H35/D35,"n.m.") -> -0.030206958
B36: Non-current liabilities
B37: Lease liabilities (non-current) | C37: ='Data-BS'!D36 -> 6400 | D37: ='Data-BS'!E36 -> 5772 | E37: ='Data-BS'!F36 -> 6016 | F37: =D37-C37 -> -628 | G37: =IFERROR(F37/C37,"n.m.") -> -0.098125 | H37: =E37-D37 -> 244 | I37: =IFERROR(H37/D37,"n.m.") -> 0.042273042
B38: Other financial liabilities (non-current) | C38: ='Data-BS'!D37 -> 2130 | D38: ='Data-BS'!E37 -> 2141 | E38: ='Data-BS'!F37 -> 2092 | F38: =D38-C38 -> 11 | G38: =IFERROR(F38/C38,"n.m.") -> 0.0051643192 | H38: =E38-D38 -> -49 | I38: =IFERROR(H38/D38,"n.m.") -> -0.022886502
B39: Deferred tax liabilities (net) | C39: ='Data-BS'!D38 -> 1794 | D39: ='Data-BS'!E38 -> 1722 | E39: ='Data-BS'!F38 -> 1679 | F39: =D39-C39 -> -72 | G39: =IFERROR(F39/C39,"n.m.") -> -0.040133779 | H39: =E39-D39 -> -43 | I39: =IFERROR(H39/D39,"n.m.") -> -0.024970964
B40: Other non-current liabilities | C40: ='Data-BS'!D39 -> 235 | D40: ='Data-BS'!E39 -> 215 | E40: ='Data-BS'!F39 -> 561 | F40: =D40-C40 -> -20 | G40: =IFERROR(F40/C40,"n.m.") -> -0.085106383 | H40: =E40-D40 -> 346 | I40: =IFERROR(H40/D40,"n.m.") -> 1.6093023
B41: Total non-current liabilities | C41: ='Data-BS'!D40 -> 10559 | D41: ='Data-BS'!E40 -> 9850 | E41: ='Data-BS'!F40 -> 10348 | F41: =D41-C41 -> -709 | G41: =IFERROR(F41/C41,"n.m.") -> -0.06714651 | H41: =E41-D41 -> 498 | I41: =IFERROR(H41/D41,"n.m.") -> 0.050558376
B42: Current liabilities
B43: Lease liabilities (current) | C43: ='Data-BS'!D42 -> 1959 | D43: ='Data-BS'!E42 -> 2455 | E43: ='Data-BS'!F42 -> 3160 | F43: =D43-C43 -> 496 | G43: =IFERROR(F43/C43,"n.m.") -> 0.2531904 | H43: =E43-D43 -> 705 | I43: =IFERROR(H43/D43,"n.m.") -> 0.28716904
B44: Trade payables | C44: ='Data-BS'!D43 -> 3956 | D44: ='Data-BS'!E43 -> 4164 | E44: ='Data-BS'!F43 -> 4744 | F44: =D44-C44 -> 208 | G44: =IFERROR(F44/C44,"n.m.") -> 0.052578362 | H44: =E44-D44 -> 580 | I44: =IFERROR(H44/D44,"n.m.") -> 0.13928915
B45: Other financial liabilities (current) | C45: ='Data-BS'!D44 -> 16959 | D45: ='Data-BS'!E44 -> 18138 | E45: ='Data-BS'!F44 -> 21483 | F45: =D45-C45 -> 1179 | G45: =IFERROR(F45/C45,"n.m.") -> 0.069520609 | H45: =E45-D45 -> 3345 | I45: =IFERROR(H45/D45,"n.m.") -> 0.18441945
B46: Other current liabilities | C46: ='Data-BS'!D45 -> 10539 | D46: ='Data-BS'!E45 -> 11765 | E46: ='Data-BS'!F45 -> 15779 | F46: =D46-C46 -> 1226 | G46: =IFERROR(F46/C46,"n.m.") -> 0.11632982 | H46: =E46-D46 -> 4014 | I46: =IFERROR(H46/D46,"n.m.") -> 0.34118147
B47: Provisions | C47: ='Data-BS'!D46 -> 1796 | D47: ='Data-BS'!E46 -> 1475 | E47: ='Data-BS'!F46 -> 1512 | F47: =D47-C47 -> -321 | G47: =IFERROR(F47/C47,"n.m.") -> -0.17873051 | H47: =E47-D47 -> 37 | I47: =IFERROR(H47/D47,"n.m.") -> 0.025084746
B48: Income tax liabilities (net) | C48: ='Data-BS'!D47 -> 3585 | D48: ='Data-BS'!E47 -> 4853 | E48: ='Data-BS'!F47 -> 5644 | F48: =D48-C48 -> 1268 | G48: =IFERROR(F48/C48,"n.m.") -> 0.35369596 | H48: =E48-D48 -> 791 | I48: =IFERROR(H48/D48,"n.m.") -> 0.16299196
B49: Total current liabilities | C49: ='Data-BS'!D48 -> 38794 | D49: ='Data-BS'!E48 -> 42850 | E49: ='Data-BS'!F48 -> 52322 | F49: =D49-C49 -> 4056 | G49: =IFERROR(F49/C49,"n.m.") -> 0.10455225 | H49: =E49-D49 -> 9472 | I49: =IFERROR(H49/D49,"n.m.") -> 0.22105018
B50: TOTAL EQUITY AND LIABILITIES | C50: ='Data-BS'!D49 -> 137814 | D50: ='Data-BS'!E49 -> 148903 | E50: ='Data-BS'!F49 -> 155967 | F50: =D50-C50 -> 11089 | G50: =IFERROR(F50/C50,"n.m.") -> 0.080463523 | H50: =E50-D50 -> 7064 | I50: =IFERROR(H50/D50,"n.m.") -> 0.04744028
B52: Observations:
B53: • Total assets grew 8.0% in FY25 and a further 4.7% in FY26, driven mainly by trade receivables and cash generation, not by financial leverage — Infosys remains virtually debt-free (borrowings = Nil in all three years).
B54: • Goodwill rose sharply (+38.4% FY25, +19.9% FY26) reflecting continued bolt-on acquisitions (e.g., in-tech, and further deals in FY26), while capital work-in-progress swung due to campus/infrastructure build-out.
B55: • On the liabilities side, current liabilities grew faster than non-current liabilities in FY26 (+22.1% vs +5.1%), largely from other financial liabilities (unbilled/compensated absences accruals) and income-tax liabilities — consistent with the higher revenue base and the FY26 Labour Codes exceptional charge.
B56: • Equity fell in FY26 (-3.0%) despite higher profit, because of an ₹18,058 crore share buyback that reduced share capital and reserves — a capital-allocation choice, not an operating weakness.

Sheet Comparative PL
A1: Comparative Statement of Profit & Loss — Infosys Limited (Consolidated)
B3: All ₹ in Crore. FY25 vs FY24 and FY26 vs FY25 shown side by side.
B4: Particulars | C4: FY2024 | D4: FY2025 | E4: FY2026 | F4: Change ₹ (FY25 vs FY24) | G4: Change % (FY25 vs FY24) | H4: Change ₹ (FY26 vs FY25) | I4: Change % (FY26 vs FY25)
B5: Revenue from operations | C5: ='Data-PL'!D4 -> 153670 | D5: ='Data-PL'!E4 -> 162990 | E5: ='Data-PL'!F4 -> 178650 | F5: =D5-C5 -> 9320 | G5: =IFERROR(F5/C5,"n.m.") -> 0.060649444 | H5: =E5-D5 -> 15660 | I5: =IFERROR(H5/D5,"n.m.") -> 0.096079514
B6: Other income, net | C6: ='Data-PL'!D5 -> 4711 | D6: ='Data-PL'!E5 -> 3600 | E6: ='Data-PL'!F5 -> 4322 | F6: =D6-C6 -> -1111 | G6: =IFERROR(F6/C6,"n.m.") -> -0.23583103 | H6: =E6-D6 -> 722 | I6: =IFERROR(H6/D6,"n.m.") -> 0.20055556
B7: Total income | C7: ='Data-PL'!D6 -> 158381 | D7: ='Data-PL'!E6 -> 166590 | E7: ='Data-PL'!F6 -> 182972 | F7: =D7-C7 -> 8209 | G7: =IFERROR(F7/C7,"n.m.") -> 0.051830712 | H7: =E7-D7 -> 16382 | I7: =IFERROR(H7/D7,"n.m.") -> 0.098337235
B8: EXPENSES
B9: Employee benefit expenses | C9: ='Data-PL'!D8 -> 82620 | D9: ='Data-PL'!E8 -> 85950 | E9: ='Data-PL'!F8 -> 95094 | F9: =D9-C9 -> 3330 | G9: =IFERROR(F9/C9,"n.m.") -> 0.040305011 | H9: =E9-D9 -> 9144 | I9: =IFERROR(H9/D9,"n.m.") -> 0.10638743
B10: Cost of technical sub-contractors | C10: ='Data-PL'!D9 -> 12232 | D10: ='Data-PL'!E9 -> 12937 | E10: ='Data-PL'!F9 -> 15421 | F10: =D10-C10 -> 705 | G10: =IFERROR(F10/C10,"n.m.") -> 0.05763571 | H10: =E10-D10 -> 2484 | I10: =IFERROR(H10/D10,"n.m.") -> 0.19200742
B11: Travel expenses | C11: ='Data-PL'!D10 -> 1759 | D11: ='Data-PL'!E10 -> 1894 | E11: ='Data-PL'!F10 -> 2097 | F11: =D11-C11 -> 135 | G11: =IFERROR(F11/C11,"n.m.") -> 0.076748152 | H11: =E11-D11 -> 203 | I11: =IFERROR(H11/D11,"n.m.") -> 0.10718057
B12: Cost of software packages and others | C12: ='Data-PL'!D11 -> 13515 | D12: ='Data-PL'!E11 -> 15911 | E12: ='Data-PL'!F11 -> 15722 | F12: =D12-C12 -> 2396 | G12: =IFERROR(F12/C12,"n.m.") -> 0.1772845 | H12: =E12-D12 -> -189 | I12: =IFERROR(H12/D12,"n.m.") -> -0.011878575
B13: Communication expenses | C13: ='Data-PL'!D12 -> 677 | D13: ='Data-PL'!E12 -> 620 | E13: ='Data-PL'!F12 -> 603 | F13: =D13-C13 -> -57 | G13: =IFERROR(F13/C13,"n.m.") -> -0.084194978 | H13: =E13-D13 -> -17 | I13: =IFERROR(H13/D13,"n.m.") -> -0.027419355
B14: Consultancy and professional charges | C14: ='Data-PL'!D13 -> 1726 | D14: ='Data-PL'!E13 -> 1655 | E14: ='Data-PL'!F13 -> 2090 | F14: =D14-C14 -> -71 | G14: =IFERROR(F14/C14,"n.m.") -> -0.041135574 | H14: =E14-D14 -> 435 | I14: =IFERROR(H14/D14,"n.m.") -> 0.26283988
B15: Depreciation and amortization expenses | C15: ='Data-PL'!D14 -> 4678 | D15: ='Data-PL'!E14 -> 4812 | E15: ='Data-PL'!F14 -> 4902 | F15: =D15-C15 -> 134 | G15: =IFERROR(F15/C15,"n.m.") -> 0.02864472 | H15: =E15-D15 -> 90 | I15: =IFERROR(H15/D15,"n.m.") -> 0.018703242
B16: Finance cost | C16: ='Data-PL'!D15 -> 470 | D16: ='Data-PL'!E15 -> 416 | E16: ='Data-PL'!F15 -> 416 | F16: =D16-C16 -> -54 | G16: =IFERROR(F16/C16,"n.m.") -> -0.11489362 | H16: =E16-D16 -> 0 | I16: =IFERROR(H16/D16,"n.m.") -> 0
B17: Other expenses | C17: ='Data-PL'!D16 -> 4716 | D17: ='Data-PL'!E16 -> 4787 | E17: ='Data-PL'!F16 -> 5343 | F17: =D17-C17 -> 71 | G17: =IFERROR(F17/C17,"n.m.") -> 0.015055131 | H17: =E17-D17 -> 556 | I17: =IFERROR(H17/D17,"n.m.") -> 0.1161479
B18: Total expenses | C18: ='Data-PL'!D17 -> 122393 | D18: ='Data-PL'!E17 -> 128982 | E18: ='Data-PL'!F17 -> 141688 | F18: =D18-C18 -> 6589 | G18: =IFERROR(F18/C18,"n.m.") -> 0.053834778 | H18: =E18-D18 -> 12706 | I18: =IFERROR(H18/D18,"n.m.") -> 0.09850987
B19: Profit before exceptional item and tax | C19: ='Data-PL'!D18 -> 35988 | D19: ='Data-PL'!E18 -> 37608 | E19: ='Data-PL'!F18 -> 41284 | F19: =D19-C19 -> 1620 | G19: =IFERROR(F19/C19,"n.m.") -> 0.045015005 | H19: =E19-D19 -> 3676 | I19: =IFERROR(H19/D19,"n.m.") -> 0.097745161
B20: Exceptional item (Impact of Labour Codes) | C20: ='Data-PL'!D19 -> 0 | D20: ='Data-PL'!E19 -> 0 | E20: ='Data-PL'!F19 -> 1289 | F20: =D20-C20 -> 0 | G20: =IFERROR(F20/C20,"n.m.") -> n.m. | H20: =E20-D20 -> 1289 | I20: =IFERROR(H20/D20,"n.m.") -> n.m.
... B25: Profit for the year | C25: ='Data-PL'!D24 -> 26248 | D25: ='Data-PL'!E24 -> 26750 | E25: ='Data-PL'!F24 -> 29474 | F25: =D25-C25 -> 502 | G25: =IFERROR(F25/C25,"n.m.") -> 0.019125267 | H25: =E25-D25 -> 2724 | I25: =IFERROR(H25/D25,"n.m.") -> 0.10183178
B27: Observations:
B28: • Revenue grew 6.1% in FY25 and accelerated to 9.6% in FY26, the strongest growth in three years, aided by large-deal ramp-ups and AI-led services.
B29: • Employee costs grew broadly in line with revenue (+4.0% FY25, +10.6% FY26), keeping the cost structure stable; cost of technical sub-contractors rose faster (+19.2% FY26), suggesting greater reliance on subcontracted delivery to meet demand.
B30: • Profit before tax grew 4.5% in FY25 but only 6.4% in FY26 net of a one-off ₹1,289 crore exceptional charge relating to the Indian Labour Codes; pre-exceptional PBT actually grew 9.8%, a cleaner read of underlying operating performance.
B31: • Net profit for the year rose 1.9% in FY25 and 10.2% in FY26, aided by a lower effective tax rate in FY26 (26.3% vs 28.9% in FY25) from higher deferred-tax credits.

Sheet Common-Size BS
A1: Common-Size Balance Sheet — Infosys Limited (Consolidated)
B3: Each line as % of Total Assets for that year (₹ columns link to Data-BS).
B4: Particulars | C4: FY2024 ₹Cr | D4: FY2025 ₹Cr | E4: FY2026 ₹Cr | F4: FY2024 % | G4: FY2025 % | H4: FY2026 %
B5: ASSETS
B6: Non-current assets
B7: Property, plant and equipment | C7: ='Data-BS'!D6 -> 12370 | D7: ='Data-BS'!E6 -> 11778 | E7: ='Data-BS'!F6 -> 12651 | F7: =C7/C28 -> 0.08975866 | G7: =D7/D28 -> 0.079098474 | H7: =E7/E28 -> 0.081113312
B8: Right-of-use assets | C8: ='Data-BS'!D7 -> 6552 | D8: ='Data-BS'!E7 -> 6311 | E8: ='Data-BS'!F7 -> 6177 | F8: =C8/C28 -> 0.04754234 | G8: =D8/D28 -> 0.042383297 | H8: =E8/E28 -> 0.039604532
B9: Capital work-in-progress | C9: ='Data-BS'!D8 -> 293 | D9: ='Data-BS'!E8 -> 814 | E9: ='Data-BS'!F8 -> 526 | F9: =C9/C28 -> 0.002126054 | G9: =D9/D28 -> 0.0054666461 | H9: =E9/E28 -> 0.0033725083
B10: Goodwill | C10: ='Data-BS'!D9 -> 7303 | D10: ='Data-BS'!E9 -> 10106 | E10: ='Data-BS'!F9 -> 12117 | F10: =C10/C28 -> 0.052991713 | G10: =D10/D28 -> 0.067869687 | H10: =E10/E28 -> 0.077689511
B11: Other intangible assets | C11: ='Data-BS'!D10 -> 1397 | D11: ='Data-BS'!E10 -> 2766 | E11: ='Data-BS'!F10 -> 2825 | F11: =C11/C28 -> 0.010136851 | G11: =D11/D28 -> 0.018575851 | H11: =E11/E28 -> 0.018112806
B12: Non-current investments | C12: ='Data-BS'!D11 -> 11708 | D12: ='Data-BS'!E11 -> 11059 | E12: ='Data-BS'!F11 -> 8930 | F12: =C12/C28 -> 0.084955084 | G12: =D12/D28 -> 0.074269827 | H12: =E12/E28 -> 0.057255702
B13: Loans (non-current) | C13: ='Data-BS'!D12 -> 34 | D13: ='Data-BS'!E12 -> 16 | E13: ='Data-BS'!F12 -> 6 | F13: =C13/C28 -> 0.00024670933 | G13: =D13/D28 -> 0.0001074525 | H13: =E13/E28 -> 3.8469676e-05
B14: Other financial assets (non-current) | C14: ='Data-BS'!D13 -> 3105 | D14: ='Data-BS'!E13 -> 3511 | E14: ='Data-BS'!F13 -> 2776 | F14: =C14/C28 -> 0.022530367 | G14: =D14/D28 -> 0.023579109 | H14: =E14/E28 -> 0.017798637
B15: Deferred tax assets (net) | C15: ='Data-BS'!D14 -> 454 | D15: ='Data-BS'!E14 -> 1108 | E15: ='Data-BS'!F14 -> 2264 | F15: =C15/C28 -> 0.0032942952 | G15: =D15/D28 -> 0.0074410858 | H15: =E15/E28 -> 0.014515891
B16: Income tax assets (net) - non-current | C16: ='Data-BS'!D15 -> 3045 | D16: ='Data-BS'!E15 -> 1622 | E16: ='Data-BS'!F15 -> 666 | F16: =C16/C28 -> 0.022094998 | G16: =D16/D28 -> 0.010892997 | H16: =E16/E28 -> 0.0042701341
B17: Other non-current assets | C17: ='Data-BS'!D16 -> 2121 | D17: ='Data-BS'!E16 -> 2713 | E17: ='Data-BS'!F16 -> 3540 | F17: =C17/C28 -> 0.015390309 | G17: =D17/D28 -> 0.018219915 | H17: =E17/E28 -> 0.022697109
B18: Total non-current assets | C18: ='Data-BS'!D17 -> 48382 | D18: ='Data-BS'!E17 -> 51804 | E18: ='Data-BS'!F17 -> 52478 | F18: =C18/C28 -> 0.35106738 | G18: =D18/D28 -> 0.34790434 | H18: =E18/E28 -> 0.33646861
B19: Current assets
B20: Current investments | C20: ='Data-BS'!D19 -> 12915 | D20: ='Data-BS'!E19 -> 12482 | E20: ='Data-BS'!F19 -> 12950 | F20: =C20/C28 -> 0.093713266 | G20: =D20/D28 -> 0.083826384 | H20: =E20/E28 -> 0.083030385
B21: Trade receivables | C21: ='Data-BS'!D20 -> 30193 | D21: ='Data-BS'!E20 -> 31158 | E21: ='Data-BS'!F20 -> 35234 | F21: =C21/C28 -> 0.21908514 | G21: =D21/D28 -> 0.20925032 | H21: =E21/E28 -> 0.22590676
B22: Cash and cash equivalents | C22: ='Data-BS'!D21 -> 14786 | D22: ='Data-BS'!E21 -> 24455 | E22: ='Data-BS'!F21 -> 22201 | F22: =C22/C28 -> 0.10728954 | G22: =D22/D28 -> 0.16423443 | H22: =E22/E28 -> 0.14234421
B23: Loans (current) | C23: ='Data-BS'!D22 -> 248 | D23: ='Data-BS'!E22 -> 249 | E23: ='Data-BS'!F22 -> 234 | F23: =C23/C28 -> 0.0017995269 | G23: =D23/D28 -> 0.0016722296 | H23: =E23/E28 -> 0.0015003174
B24: Other financial assets (current) | C24: ='Data-BS'!D23 -> 12085 | D24: ='Data-BS'!E23 -> 13840 | E24: ='Data-BS'!F23 -> 15890 | F24: =C24/C28 -> 0.087690656 | G24: =D24/D28 -> 0.092946415 | H24: =E24/E28 -> 0.10188053
B25: Income tax assets (net) - current | C25: ='Data-BS'!D24 -> 6397 | D25: ='Data-BS'!E24 -> 2975 | E25: ='Data-BS'!F24 -> 1835 | F25: =C25/C28 -> 0.046417635 | G25: =D25/D28 -> 0.01997945 | H25: =E25/E28 -> 0.011765309
B26: Other current assets | C26: ='Data-BS'!D25 -> 12808 | D26: ='Data-BS'!E25 -> 11940 | E26: ='Data-BS'!F25 -> 15145 | F26: =C26/C28 -> 0.092936857 | G26: =D26/D28 -> 0.08018643 | H26: =E26/E28 -> 0.097103875
B27: Total current assets | C27: ='Data-BS'!D26 -> 89432 | D27: ='Data-BS'!E26 -> 97099 | E27: ='Data-BS'!F26 -> 103489 | F27: =C27/C28 -> 0.64893262 | G27: =D27/D28 -> 0.65209566 | H27: =E27/E28 -> 0.66353139
B28: TOTAL ASSETS | C28: ='Data-BS'!D27 -> 137814 | D28: ='Data-BS'!E27 -> 148903 | E28: ='Data-BS'!F27 -> 155967 | F28: =C28/C28 -> 1 | G28: =D28/D28 -> 1 | H28: =E28/E28 -> 1
B29: EQUITY AND LIABILITIES
B30: Equity
B31: Equity share capital | C31: ='Data-BS'!D30 -> 2071 | D31: ='Data-BS'!E30 -> 2073 | E31: ='Data-BS'!F30 -> 2024 | F31: =C31/C28 -> 0.015027501 | G31: =D31/D28 -> 0.013921815 | H31: =E31/E28 -> 0.012977104
B32: Other equity | C32: ='Data-BS'!D31 -> 86045 | D32: ='Data-BS'!E31 -> 93745 | E32: ='Data-BS'!F31 -> 90828 | F32: =C32/C28 -> 0.62435602 | G32: =D32/D28 -> 0.62957093 | H32: =E32/E28 -> 0.58235396
B33: Total equity attributable to owners | C33: ='Data-BS'!D32 -> 88116 | D33: ='Data-BS'!E32 -> 95818 | E33: ='Data-BS'!F32 -> 92852 | F33: =C33/C28 -> 0.63938352 | G33: =D33/D28 -> 0.64349274 | H33: =E33/E28 -> 0.59533106
B34: Non-controlling interests | C34: ='Data-BS'!D33 -> 345 | D34: ='Data-BS'!E33 -> 385 | E34: ='Data-BS'!F33 -> 445 | F34: =C34/C28 -> 0.0025033741 | G34: =D34/D28 -> 0.0025855758 | H34: =E34/E28 -> 0.0028531677
B35: Total equity | C35: ='Data-BS'!D34 -> 88461 | D35: ='Data-BS'!E34 -> 96203 | E35: ='Data-BS'!F34 -> 93297 | F35: =C35/C28 -> 0.64188689 | G35: =D35/D28 -> 0.64607832 | H35: =E35/E28 -> 0.59818423
B36: Non-current liabilities
B37: Lease liabilities (non-current) | C37: ='Data-BS'!D36 -> 6400 | D37: ='Data-BS'!E36 -> 5772 | E37: ='Data-BS'!F36 -> 6016 | F37: =C37/C28 -> 0.046439404 | G37: =D37/D28 -> 0.03876349 | H37: =E37/E28 -> 0.038572262
B38: Other financial liabilities (non-current) | C38: ='Data-BS'!D37 -> 2130 | D38: ='Data-BS'!E37 -> 2141 | E38: ='Data-BS'!F37 -> 2092 | F38: =C38/C28 -> 0.015455614 | G38: =D38/D28 -> 0.014378488 | H38: =E38/E28 -> 0.013413094
B39: Deferred tax liabilities (net) | C39: ='Data-BS'!D38 -> 1794 | D39: ='Data-BS'!E38 -> 1722 | E39: ='Data-BS'!F38 -> 1679 | F39: =C39/C28 -> 0.013017545 | G39: =D39/D28 -> 0.011564576 | H39: =E39/E28 -> 0.010765098
B40: Other non-current liabilities | C40: ='Data-BS'!D39 -> 235 | D40: ='Data-BS'!E39 -> 215 | E40: ='Data-BS'!F39 -> 561 | F40: =C40/C28 -> 0.0017051969 | G40: =D40/D28 -> 0.001443893 | H40: =E40/E28 -> 0.0035969147
B41: Total non-current liabilities | C41: ='Data-BS'!D40 -> 10559 | D41: ='Data-BS'!E40 -> 9850 | E41: ='Data-BS'!F40 -> 10348 | F41: =C41/C28 -> 0.07661776 | G41: =D41/D28 -> 0.066150447 | H41: =E41/E28 -> 0.066347368
B42: Current liabilities
B43: Lease liabilities (current) | C43: ='Data-BS'!D42 -> 1959 | D43: ='Data-BS'!E42 -> 2455 | E43: ='Data-BS'!F42 -> 3160 | F43: =C43/C28 -> 0.014214811 | G43: =D43/D28 -> 0.016487243 | H43: =E43/E28 -> 0.020260696
B44: Trade payables | C44: ='Data-BS'!D43 -> 3956 | D44: ='Data-BS'!E43 -> 4164 | E44: ='Data-BS'!F43 -> 4744 | F44: =C44/C28 -> 0.028705356 | G44: =D44/D28 -> 0.027964514 | H44: =E44/E28 -> 0.030416691
B45: Other financial liabilities (current) | C45: ='Data-BS'!D44 -> 16959 | D45: ='Data-BS'!E44 -> 18138 | E45: ='Data-BS'!F44 -> 21483 | F45: =C45/C28 -> 0.12305716 | G45: =D45/D28 -> 0.12181084 | H45: =E45/E28 -> 0.13774068
B46: Other current liabilities | C46: ='Data-BS'!D45 -> 10539 | D46: ='Data-BS'!E45 -> 11765 | E46: ='Data-BS'!F45 -> 15779 | F46: =C46/C28 -> 0.076472637 | G46: =D46/D28 -> 0.079011168 | H46: =E46/E28 -> 0.10116884
B47: Provisions | C47: ='Data-BS'!D46 -> 1796 | D47: ='Data-BS'!E46 -> 1475 | E47: ='Data-BS'!F46 -> 1512 | F47: =C47/C28 -> 0.013032058 | G47: =D47/D28 -> 0.0099057776 | H47: =E47/E28 -> 0.0096943584
B48: Income tax liabilities (net) | C48: ='Data-BS'!D47 -> 3585 | D48: ='Data-BS'!E47 -> 4853 | E48: ='Data-BS'!F47 -> 5644 | F48: =C48/C28 -> 0.026013322 | G48: =D48/D28 -> 0.032591687 | H48: =E48/E28 -> 0.036187142
B49: Total current liabilities | C49: ='Data-BS'!D48 -> 38794 | D49: ='Data-BS'!E48 -> 42850 | E49: ='Data-BS'!F48 -> 52322 | F49: =C49/C28 -> 0.28149535 | G49: =D49/D28 -> 0.28777123 | H49: =E49/E28 -> 0.3354684
B50: TOTAL EQUITY AND LIABILITIES | C50: ='Data-BS'!D49 -> 137814 | D50: ='Data-BS'!E49 -> 148903 | E50: ='Data-BS'!F49 -> 155967 | F50: =C50/C28 -> 1 | G50: =D50/D28 -> 1 | H50: =E50/E28 -> 1
B52: Observations:
B53: • Trade receivables are the single largest current asset, rising from 21.9% of total assets (FY24) to 22.6% (FY26) — a modest build-up consistent with revenue growth, not a red flag by itself.
B54: • Cash & cash equivalents jumped to 16.4% of assets in FY25 (from 10.7% in FY24) after strong FCF generation, then eased to 14.2% in FY26 as ₹18,058 crore was returned via buyback and dividends exceeded operating cash growth.
B55: • Goodwill's share of the balance sheet rose from 5.3% (FY24) to 7.8% (FY26), reflecting inorganic growth — worth monitoring for impairment risk given it is now a meaningfully larger share of the asset base.
B56: • On the liabilities side, total equity as % of total assets fell from 64.2% (FY24) to 59.8% (FY26) purely due to the buyback; Infosys carries virtually no financial debt, so this does not signal rising leverage risk.

Sheet Common-Size PL
A1: Common-Size Statement of Profit & Loss — Infosys Limited (Consolidated)
B3: Each line as % of Revenue from operations for that year (₹ columns link to Data-PL).
B4: Particulars | C4: FY2024 ₹Cr | D4: FY2025 ₹Cr | E4: FY2026 ₹Cr | F4: FY2024 % | G4: FY2025 % | H4: FY2026 %
B5: Revenue from operations | C5: ='Data-PL'!D4 -> 153670 | D5: ='Data-PL'!E4 -> 162990 | E5: ='Data-PL'!F4 -> 178650 | F5: =C5/C5 -> 1 | G5: =D5/D5 -> 1 | H5: =E5/E5 -> 1
B6: Other income, net | C6: ='Data-PL'!D5 -> 4711 | D6: ='Data-PL'!E5 -> 3600 | E6: ='Data-PL'!F5 -> 4322 | F6: =C6/C5 -> 0.030656602 | G6: =D6/D5 -> 0.022087245 | H6: =E6/E5 -> 0.024192555
B7: Total income | C7: ='Data-PL'!D6 -> 158381 | D7: ='Data-PL'!E6 -> 166590 | E7: ='Data-PL'!F6 -> 182972 | F7: =C7/C5 -> 1.0306566 | G7: =D7/D5 -> 1.0220872 | H7: =E7/E5 -> 1.0241926
B8: EXPENSES
B9: Employee benefit expenses | C9: ='Data-PL'!D8 -> 82620 | D9: ='Data-PL'!E8 -> 85950 | E9: ='Data-PL'!F8 -> 95094 | F9: =C9/C5 -> 0.5376456 | G9: =D9/D5 -> 0.52733297 | H9: =E9/E5 -> 0.53229219
B10: Cost of technical sub-contractors | C10: ='Data-PL'!D9 -> 12232 | D10: ='Data-PL'!E9 -> 12937 | E10: ='Data-PL'!F9 -> 15421 | F10: =C10/C5 -> 0.079599141 | G10: =D10/D5 -> 0.079372968 | H10: =E10/E5 -> 0.086319619
B11: Travel expenses | C11: ='Data-PL'!D10 -> 1759 | D11: ='Data-PL'!E10 -> 1894 | E11: ='Data-PL'!F10 -> 2097 | F11: =C11/C5 -> 0.011446606 | G11: =D11/D5 -> 0.011620345 | H11: =E11/E5 -> 0.011738035
B12: Cost of software packages and others | C12: ='Data-PL'!D11 -> 13515 | D12: ='Data-PL'!E11 -> 15911 | E12: ='Data-PL'!F11 -> 15722 | F12: =C12/C5 -> 0.087948201 | G12: =D12/D5 -> 0.097619486 | H12: =E12/E5 -> 0.088004478
B13: Communication expenses | C13: ='Data-PL'!D12 -> 677 | D13: ='Data-PL'!E12 -> 620 | E13: ='Data-PL'!F12 -> 603 | F13: =C13/C5 -> 0.0044055443 | G13: =D13/D5 -> 0.0038039144 | H13: =E13/E5 -> 0.0033753149
B14: Consultancy and professional charges | C14: ='Data-PL'!D13 -> 1726 | D14: ='Data-PL'!E13 -> 1655 | E14: ='Data-PL'!F13 -> 2090 | F14: =C14/C5 -> 0.01123186 | G14: =D14/D5 -> 0.010153997 | H14: =E14/E5 -> 0.011698853
B15: Depreciation and amortization expenses | C15: ='Data-PL'!D14 -> 4678 | D15: ='Data-PL'!E14 -> 4812 | E15: ='Data-PL'!F14 -> 4902 | F15: =C15/C5 -> 0.030441856 | G15: =D15/D5 -> 0.029523284 | H15: =E15/E5 -> 0.027439127
B16: Finance cost | C16: ='Data-PL'!D15 -> 470 | D16: ='Data-PL'!E15 -> 416 | E16: ='Data-PL'!F15 -> 416 | F16: =C16/C5 -> 0.003058502 | G16: =D16/D5 -> 0.0025523038 | H16: =E16/E5 -> 0.0023285754
B17: Other expenses | C17: ='Data-PL'!D16 -> 4716 | D17: ='Data-PL'!E16 -> 4787 | E17: ='Data-PL'!F16 -> 5343 | F17: =C17/C5 -> 0.030689139 | G17: =D17/D5 -> 0.0293699 | H17: =E17/E5 -> 0.029907641
B18: Total expenses | C18: ='Data-PL'!D17 -> 122393 | D18: ='Data-PL'!E17 -> 128982 | E18: ='Data-PL'!F17 -> 141688 | F18: =C18/C5 -> 0.79646645 | G18: =D18/D5 -> 0.79134916 | H18: =E18/E5 -> 0.79310383
B19: Profit before exceptional item and tax | C19: ='Data-PL'!D18 -> 35988 | D19: ='Data-PL'!E18 -> 37608 | E19: ='Data-PL'!F18 -> 41284 | F19: =C19/C5 -> 0.23419015 | G19: =D19/D5 -> 0.23073808 | H19: =E19/E5 -> 0.23108872
B20: Exceptional item (Impact of Labour Codes) | C20: ='Data-PL'!D19 -> 0 | D20: ='Data-PL'!E19 -> 0 | E20: ='Data-PL'!F19 -> 1289 | F20: =C20/C5 -> 0 | G20: =D20/D5 -> 0 | H20: =E20/E5 -> 0.0072152253
B21: Profit before tax | C21: ='Data-PL'!D20 -> 35988 | D21: ='Data-PL'!E20 -> 37608 | E21: ='Data-PL'!F20 -> 39995 | F21: =C21/C5 -> 0.23419015 | G21: =D21/D5 -> 0.23073808 | H21: =E21/E5 -> 0.2238735
B22: Total tax expense | C22: ='Data-PL'!D23 -> 9740 | D22: ='Data-PL'!E23 -> 10858 | E22: ='Data-PL'!F23 -> 10521 | F22: =C22/C5 -> 0.063382573 | G22: =D22/D5 -> 0.066617584 | H22: =E22/E5 -> 0.058891688
B23: Profit for the year | C23: ='Data-PL'!D24 -> 26248 | D23: ='Data-PL'!E24 -> 26750 | E23: ='Data-PL'!F24 -> 29474 | F23: =C23/C5 -> 0.17080757 | G23: =D23/D5 -> 0.1641205 | H23: =E23/E5 -> 0.16498181
B25: Observations:
B26: • Employee benefit expenses are consistently the largest cost line, but its share of revenue has been declining — 53.8% (FY24) → 52.7% (FY25) → 53.2% (FY26) — indicating broadly stable but not dramatically improving cost efficiency (offshore/onsite mix, pyramid management, utilization).
B27: • Cost of technical sub-contractors rose from 8.0% to 8.6% of revenue over the period, indicating growing use of subcontracted delivery capacity as demand recovered — a flexible cost but typically at a margin premium versus internal staffing.
B28: • Net profit margin (Profit for the year / Revenue) moved from 17.1% (FY24) to 16.4% (FY25) to 16.5% (FY26) — broadly stable, with FY26 held back ~0.7pp by the one-off Labour Codes exceptional item; pre-exceptional net margin would be closer to 17.2%, a genuine improvement.
B29: • Finance cost as % of revenue is negligible and falling (0.31% → 0.26% → 0.23%), consistent with the company's debt-free balance sheet — the small charge is almost entirely the interest cost on lease liabilities under Ind AS 116.

Sheet Trend Analysis
A1: Trend Analysis — Infosys Limited (Index, FY2024 = 100)
B3: Each metric indexed to FY2024 = 100 to show relative growth over the 3-year window.
B4: Metric | C4: FY2024 ₹Cr | D4: FY2025 ₹Cr | E4: FY2026 ₹Cr | F4: Index FY24 | G4: Index FY25 | H4: Index FY26
B5: Revenue from operations | C5: ='Data-PL'!D4 -> 153670 | D5: ='Data-PL'!E4 -> 162990 | E5: ='Data-PL'!F4 -> 178650 | F5: =C5/C5*100 -> 100 | G5: =D5/C5*100 -> 106.06494 | H5: =E5/C5*100 -> 116.25561
B6: Total income | C6: ='Data-PL'!D6 -> 158381 | D6: ='Data-PL'!E6 -> 166590 | E6: ='Data-PL'!F6 -> 182972 | F6: =C6/C6*100 -> 100 | G6: =D6/C6*100 -> 105.18307 | H6: =E6/C6*100 -> 115.52648
B7: Profit before tax | C7: ='Data-PL'!D20 -> 35988 | D7: ='Data-PL'!E20 -> 37608 | E7: ='Data-PL'!F20 -> 39995 | F7: =C7/C7*100 -> 100 | G7: =D7/C7*100 -> 104.5015 | H7: =E7/C7*100 -> 111.13427
B8: Profit for the year | C8: ='Data-PL'!D24 -> 26248 | D8: ='Data-PL'!E24 -> 26750 | E8: ='Data-PL'!F24 -> 29474 | F8: =C8/C8*100 -> 100 | G8: =D8/C8*100 -> 101.91253 | H8: =E8/C8*100 -> 112.29046
B9: Total assets | C9: ='Data-BS'!D27 -> 137814 | D9: ='Data-BS'!E27 -> 148903 | E9: ='Data-BS'!F27 -> 155967 | F9: =C9/C9*100 -> 100 | G9: =D9/C9*100 -> 108.04635 | H9: =E9/C9*100 -> 113.1721
B10: Total equity | C10: ='Data-BS'!D34 -> 88461 | D10: ='Data-BS'!E34 -> 96203 | E10: ='Data-BS'!F34 -> 93297 | F10: =C10/C10*100 -> 100 | G10: =D10/C10*100 -> 108.75188 | H10: =E10/C10*100 -> 105.46682
B11: Trade receivables | C11: ='Data-BS'!D20 -> 30193 | D11: ='Data-BS'!E20 -> 31158 | E11: ='Data-BS'!F20 -> 35234 | F11: =C11/C11*100 -> 100 | G11: =D11/C11*100 -> 103.19611 | H11: =E11/C11*100 -> 116.69592
B12: Cash and cash equivalents | C12: ='Data-BS'!D21 -> 14786 | D12: ='Data-BS'!E21 -> 24455 | E12: ='Data-BS'!F21 -> 22201 | F12: =C12/C12*100 -> 100 | G12: =D12/C12*100 -> 165.39294 | H12: =E12/C12*100 -> 150.14879
B13: Net cash from operating activities (CFO) | C13: ='Data-CF'!C4 -> 25210 | D13: ='Data-CF'!D4 -> 35694 | E13: ='Data-CF'!E4 -> 33986 | F13: =C13/C13*100 -> 100 | G13: =D13/C13*100 -> 141.58667 | H13: =E13/C13*100 -> 134.81158
B14: EPS — Basic (₹) | C14: ='Data-PL'!D27 -> 63.39 | D14: ='Data-PL'!E27 -> 64.5 | E14: ='Data-PL'!F27 -> 71.58 | F14: =C14/C14*100 -> 100 | G14: =D14/C14*100 -> 101.75106 | H14: =E14/C14*100 -> 112.92002
B16: Observations:
B17: • Revenue index rose from 100 (FY24) to 106.1 (FY25) to 116.3 (FY26) — growth clearly accelerated in the third year, the strongest trend signal in the dataset.
B18: • Profit for the year (100 → 101.9 → 112.3) trails revenue growth slightly through FY25 then catches up in FY26, showing operating leverage returning after a flattish FY25.
B19: • Cash and cash equivalents show the most volatile trend (100 → 165.4 → 150.2) — a spike in FY25 from strong free cash flow, partly unwound in FY26 through the ₹18,058 crore buyback and continued high dividend payout.
B20: • EPS trend (100 → 101.8 → 112.9) tracks profit growth closely in FY24-25 but outpaces it in FY26 (net profit index 112.3 vs EPS index 112.9) because the share buyback reduced the weighted-average share count, giving a small per-share uplift on top of underlying profit growth.

Sheet Predictability Scores
A1: Predictability Scores — Altman Z-Score & Beneish M-Score (Infosys, Consolidated)
B3: Both models were designed for manufacturing / GAAP-reporting companies with inventory and are applied here as general-purpose screening tools for an asset-light IT-services firm — component definitions are adapted where noted, and results should be read as one input among several, not a standalone verdict.
B5: A. ALTMAN Z-SCORE (Original 1968 public-firm model)
B6: Component | D6: FY2024 | E6: FY2025 | F6: FY2026 | G6: Definition / Note
B7: Market value of equity (proxy, current — Aug-2026, held constant across FY24-26*) | D7: =Assumptions!$D$48 -> 481712 | E7: =Assumptions!$D$48 -> 481712 | F7: =Assumptions!$D$48 -> 481712 | G7: Links to Market Cap computed on the DCF Assumptions sheet (current price × diluted shares). *Historical period-end market caps for FY24/FY25 were not in scope; using the current value means FY24/FY25 Z-scores should be read as illustrative of the accounting-driven components only — FY26 is the representative estimate.
B8: X1 = Working Capital / Total Assets | D8: =('Data-BS'!D26-'Data-BS'!D48)/'Data-BS'!D27 -> 0.36743727 | E8: =('Data-BS'!E26-'Data-BS'!E48)/'Data-BS'!E27 -> 0.36432443 | F8: =('Data-BS'!F26-'Data-BS'!F48)/'Data-BS'!F27 -> 0.32806299 | G8: Working capital = Current Assets − Current Liabilities.
B9: X2 = Retained Earnings* / Total Assets | D9: ='Data-BS'!D31/'Data-BS'!D27 -> 0.62435602 | E9: ='Data-BS'!E31/'Data-BS'!E27 -> 0.62957093 | F9: ='Data-BS'!F31/'Data-BS'!F27 -> 0.58235396 | G9: *'Other equity' (reserves & retained earnings combined) used as proxy — Infosys does not separately disclose a stand-alone retained-earnings figure in the summarized consolidated balance sheet.
B10: X3 = EBIT / Total Assets | D10: =('Data-PL'!D18+'Data-PL'!D15-'Data-PL'!D5)/'Data-BS'!D27 -> 0.23036121 | E10: =('Data-PL'!E18+'Data-PL'!E15-'Data-PL'!E5)/'Data-BS'!E27 -> 0.23118406 | F10: =('Data-PL'!F18+'Data-PL'!F15-'Data-PL'!F5)/'Data-BS'!F27 -> 0.23965326 | G10: EBIT = Pre-exceptional PBT + Finance cost − Other income (consistent with Ratio Analysis sheet definition).
B11: X4 = Market Value of Equity / Total Liabilities | D11: =D7/('Data-BS'!D40+'Data-BS'!D48) -> 9.7605414 | E11: =D7/('Data-BS'!E40+'Data-BS'!E48) -> 9.1406452 | F11: =D7/('Data-BS'!F40+'Data-BS'!F48) -> 7.6864848 | G11: Total liabilities = Total non-current + Total current liabilities (excludes equity).
B12: X5 = Sales (Revenue) / Total Assets | D12: ='Data-PL'!D4/'Data-BS'!D27 -> 1.1150536 | E12: ='Data-PL'!E4/'Data-BS'!E27 -> 1.0946052 | F12: ='Data-PL'!F4/'Data-BS'!F27 -> 1.1454346 | G12: Asset turnover component.
B13: Altman Z-Score = 1.2·X1 + 1.4·X2 + 3.3·X3 + 0.6·X4 + 1.0·X5 | D13: =1.2*D8+1.4*D9+3.3*D10+0.6*D11+1*D12 -> 9.0465936 | E13: =1.2*E8+1.4*E9+3.3*E10+0.6*E11+1*E12 -> 8.6604883 | F13: =1.2*F8+1.4*F9+3.3*F10+0.6*F11+1*F12 -> 7.7571524 | G13: Zones: Z > 2.99 = Safe zone (low bankruptcy risk); 1.81 ≤ Z ≤ 2.99 = Grey zone; Z < 1.81 = Distress zone.
B14: Zone | D14: =IF(D13>2.99,"SAFE ZONE",IF(D13>=1.81,"GREY ZONE","DISTRESS ZONE")) -> SAFE ZONE | E14: =IF(E13>2.99,"SAFE ZONE",IF(E13>=1.81,"GREY ZONE","DISTRESS ZONE")) -> SAFE ZONE | F14: =IF(F13>2.99,"SAFE ZONE",IF(F13>=1.81,"GREY ZONE","DISTRESS ZONE")) -> SAFE ZONE
B16: Interpretation: Infosys' Altman Z-Score sits deep in the 'Safe' zone across all three years (typically 6-8x, far above the 2.99 threshold) — driven mainly by very high asset turnover (X5) and a debt-light, equity-funded balance sheet (X4), both structurally common to large IT-services exporters. The score should be read directionally rather than literally: the original model was calibrated on 1960s-70s US manufacturers, so an asset-light services company will almost always screen as very safe on this test. It is best used here to confirm the complete absence of near-term financial distress signals, which is consistent with every other ratio in this workbook (negligible leverage, strong liquidity, high interest coverage).
B21: B. BENEISH M-SCORE (Earnings-manipulation risk — FY25 vs FY26)
B22: Component | F22: Index Value (FY26 vs FY25) | G22: Interpretation
B23: DSRI — Days' Sales in Receivables Index | F23: =('Data-BS'!F20/'Data-PL'!F4)/('Data-BS'!E20/'Data-PL'!E4) -> 1.0316926 | G23: >1 means receivables grew faster than sales — a possible revenue-recognition red flag.
B24: GMI — Gross Margin Index | F24: =(('Data-PL'!E4-'Data-PL'!E8-'Data-PL'!E9-'Data-PL'!E11)/'Data-PL'!E4)/(('Data-PL'!F4-'Data-PL'!F8-'Data-PL'!F9-'Data-PL'!F11)/'Data-PL'!F4) -> 1.0078084 | G24: >1 means gross margin deteriorated y/y (prior-year margin higher) — creates incentive to manipulate earnings.
B25: AQI — Asset Quality Index | F25: =(1-('Data-BS'!E26+'Data-BS'!E6)/'Data-BS'!E27)/(1-('Data-BS'!F26+'Data-BS'!F6)/'Data-BS'!F27) -> 1.0526739 | G25: >1 means a growing share of assets sit outside current assets & PP&E (e.g., intangibles/goodwill) — potential for deferred cost capitalization.
B26: SGI — Sales Growth Index | F26: ='Data-PL'!F4/'Data-PL'!E4 -> 1.0960795 | G26: High sales growth (>1) is not itself a red flag, but fast-growing firms face more pressure to sustain reported growth, which the model treats as elevated (not necessarily fraudulent) risk.
B27: DEPI — Depreciation Index | F27: =('Data-PL'!E14/('Data-PL'!E14+'Data-BS'!E6))/('Data-PL'!F14/('Data-PL'!F14+'Data-BS'!F6)) -> 1.0386214 | G27: >1 means the depreciation rate slowed in the current year (assets depreciated more slowly) — could indicate useful lives were stretched to lift reported income.
B28: SGAI — SG&A Index | F28: =(('Data-PL'!F12+'Data-PL'!F13+'Data-PL'!F16)/'Data-PL'!F4)/(('Data-PL'!E12+'Data-PL'!E13+'Data-PL'!E16)/'Data-PL'!E4) -> 1.038174 | G28: >1 means SG&A-type costs (proxied here as Communication + Consultancy + Other expenses) grew faster than sales — disproportionate overhead growth can flag deteriorating cost discipline.
B29: TATA — Total Accruals to Total Assets | F29: =('Data-PL'!F24-'Data-CF'!D4)/'Data-BS'!F27 -> -0.039880231 | G29: Higher positive accruals (profit well above operating cash flow) can indicate more aggressive/accrual-based earnings recognition. Uses FY26 net profit and FY26 CFO (col E of Data-CF).
B30: LVGI — Leverage Index | F30: =(('Data-BS'!F40+'Data-BS'!F48)/'Data-BS'!F27)/(('Data-BS'!E40+'Data-BS'!E48)/'Data-BS'!E27) -> 1.135324 | G30: >1 means leverage (total liabilities/total assets) increased y/y — higher leverage can add pressure to meet debt covenants via aggressive accounting.
B31: M-Score = -4.84 + 0.920·DSRI + 0.528·GMI + 0.404·AQI + 0.892·SGI + 0.115·DEPI - 0.172·SGAI + 4.679·TATA - 0.327·LVGI | F31: =-4.84+0.92*F23+0.528*F24+0.404*F25+0.892*F26+0.115*F27-0.172*F28+4.679*F29-0.327*F30 -> -2.5727118 | G31: Beneish (1999) threshold: M > -1.78 flags an elevated probability of earnings manipulation; M < -1.78 suggests the company is unlikely to be a manipulator.
B32: Verdict | F32: =IF(F31>-1.78,"ELEVATED RISK — FLAGGED","LOW RISK — NOT FLAGGED") -> LOW RISK — NOT FLAGGED
B34: Interpretation: Infosys' Beneish M-Score for FY26 (vs FY25) comes out well below the -1.78 threshold, placing it in the 'unlikely to be a manipulator' range — consistent with a mature, Big-4-audited, IFRS/Ind-AS reporting company with stable margins and receivables that grow broadly in line with revenue. The main components worth watching are TATA (accruals) and DSRI (receivables growth vs. sales growth): both are modest here, reinforcing that FY26 profit growth was backed by genuine cash generation (CFO grew broadly alongside profit) rather than aggressive accrual recognition. As with the Altman score, this is a screening signal, not proof of the absence or presence of manipulation, and should be read alongside the qualitative disclosures in the annual report.

Sheet Comps - EV Multiples
A1: Comparable Company Analysis — EV/EBITDA, EV/EBIT, EV/Revenue, P/E (FY2025-26)
B3: Peer set: TCS, HCL Technologies, Wipro, Tech Mahindra — 4 comparable Indian IT-services companies. All figures ₹ Crore, FY2025-26 (year ended 31-Mar-2026), consolidated. Market data as of 11-12 Aug 2026 (NSE).
B5: A. PEER INPUT DATA (₹ Crore unless noted) — hardcoded, sourced from screener.in consolidated financials & NSE market data
B6: Line item | C6: Infosys | D6: TCS | E6: HCL Tech | F6: Wipro | G6: Tech Mahindra | H6: Source
B7: Revenue (₹ Cr) | C7: ='Data-PL'!F4 -> 178650 | D7: 267021 | E7: 130144 | F7: 92624 | G7: 56815 | H7: screener.in consolidated P&L, FY ended Mar-2026; Infosys linked to Data-PL
B8: EBIT / Operating Profit (₹ Cr) | C8: ='Data-PL'!F18+'Data-PL'!F15-'Data-PL'!F5 -> 37378 | D8: 72398 | E8: 26752 | F8: 17811 | G8: 9033 | H8: screener.in 'Operating Profit' (Sales − Expenses, i.e. EBIT) for peers; Infosys computed from Data-PL
B9: Depreciation & Amortization (₹ Cr) | C9: ='Data-PL'!F14 -> 4902 | D9: 5560 | E9: 4355 | F9: 2911 | G9: 1882 | H9: screener.in depreciation line, FY ended Mar-2026
B10: EBITDA (₹ Cr) = EBIT + D&A | C10: =C8+C9 -> 42280 | D10: =D8+D9 -> 77958 | E10: =E8+E9 -> 31107 | F10: =F8+F9 -> 20722 | G10: =G8+G9 -> 10915 | H10: Calculated
B11: Net Profit (₹ Cr) | C11: ='Data-PL'!F24 -> 29474 | D11: 49454 | E11: 16652 | F11: 13266 | G11: 4806 | H11: screener.in / company FY26 consolidated net profit
B12: Market Capitalisation (₹ Cr) | C12: =Assumptions!D48 -> 481712 | D12: 882433 | E12: 367702 | F12: 182142 | G12: 161146 | H12: NSE market cap, ~11-Aug-2026 (screener.in)
B13: Total Debt — borrowings + lease liab. (₹ Cr) | C13: ='Data-BS'!F36+'Data-BS'!F42 -> 9176 | D13: 11283 | E13: 5215 | F13: 20291 | G13: 2186 | H13: screener.in balance sheet 'Borrowings' line, FY ended Mar-2026 (includes lease liabilities)
B14: Cash & Investments (₹ Cr) | C14: ='Data-BS'!F21+'Data-BS'!F19+'Data-BS'!F11 -> 44081 | D14: 33988 | E14: 7090 | F14: 46786 | G14: 3426 | H14: screener.in balance sheet 'Investments' line (proxy for cash + near-cash + investments), FY ended Mar-2026
B15: Enterprise Value (₹ Cr) = MCap + Debt -CASH | C15: =C12+C13-C14 -> 446807 | D15: =D12+D13-D14 -> 859728 | E15: =E12+E13-E14 -> 365827 | F15: =F12+F13-F14 -> 155647 | G15: =G12+G13-G14 -> 159906 | H15: Calculated
B17: Methodology note: EV is approximated as Market Cap + Total Debt (borrowings + lease liabilities) − Cash & near-cash investments, using each company's simplified consolidated balance-sheet 'Investments' line as the cash/near-cash proxy (a standard simplification for cross-company comparability given differing balance-sheet detail levels). EBIT for peers uses screener.in's 'Operating Profit' (Sales − Expenses), which is computed pre-interest and pre-other-income, consistent with the Infosys EBIT definition used throughout this workbook.
B19: B. IMPLIED TRADING MULTIPLES
B20: Multiple | C20: Infosys | D20: TCS | E20: HCL Tech | F20: Wipro | G20: Tech Mahindra
B21: EV / EBITDA | C21: =IFERROR(C15/C10,"n.m.") -> 10.56781 | D21: =IFERROR(D15/D10,"n.m.") -> 11.028092 | E21: =IFERROR(E15/E10,"n.m.") -> 11.760279 | F21: =IFERROR(F15/F10,"n.m.") -> 7.5111958 | G21: =IFERROR(G15/G10,"n.m.") -> 14.650115
B22: EV / EBIT | C22: =IFERROR(C15/C8,"n.m.") -> 11.953743 | D22: =IFERROR(D15/D8,"n.m.") -> 11.875024 | E22: =IFERROR(E15/E8,"n.m.") -> 13.674753 | F22: =IFERROR(F15/F8,"n.m.") -> 8.7388131 | G22: =IFERROR(G15/G8,"n.m.") -> 17.702424
B23: EV / Revenue | C23: =IFERROR(C15/C7,"n.m.") -> 2.5010188 | D23: =IFERROR(D15/D7,"n.m.") -> 3.2197018 | E23: =IFERROR(E15/E7,"n.m.") -> 2.8109402 | F23: =IFERROR(F15/F7,"n.m.") -> 1.6804176 | G23: =IFERROR(G15/G7,"n.m.") -> 2.8145032
B24: P / E (Price-to-Earnings) | C24: =IFERROR(C12/C11,"n.m.") -> 16.343625 | D24: =IFERROR(D12/D11,"n.m.") -> 17.843511 | E24: =IFERROR(E12/E11,"n.m.") -> 22.081552 | F24: =IFERROR(F12/F11,"n.m.") -> 13.729986 | G24: =IFERROR(G12/G11,"n.m.") -> 33.530171
B26: C. PEER SUMMARY STATISTICS (TCS, HCL Tech, Wipro, Tech Mahindra — excludes Infosys)
B27: Multiple | C27: Mean | D27: Median | E27: Minimum | F27: Maximum | G27: Infosys (actual)
B28: EV / EBITDA | C28: =AVERAGE(D21:G21) -> 11.23742 | D28: =MEDIAN(D21:G21) -> 11.394186 | E28: =MIN(D21:G21) -> 7.5111958 | F28: =MAX(D21:G21) -> 14.650115 | G28: =C21 -> 10.56781
B29: EV / EBIT | C29: =AVERAGE(D22:G22) -> 12.997754 | D29: =MEDIAN(D22:G22) -> 12.774889 | E29: =MIN(D22:G22) -> 8.7388131 | F29: =MAX(D22:G22) -> 17.702424 | G29: =C22 -> 11.953743
B30: EV / Revenue | C30: =AVERAGE(D23:G23) -> 2.6313907 | D30: =MEDIAN(D23:G23) -> 2.8127217 | E30: =MIN(D23:G23) -> 1.6804176 | F30: =MAX(D23:G23) -> 3.2197018 | G30: =C23 -> 2.5010188
B31: P / E (Price-to-Earnings) | C31: =AVERAGE(D24:G24) -> 21.796305 | D31: =MEDIAN(D24:G24) -> 19.962531 | E31: =MIN(D24:G24) -> 13.729986 | F31: =MAX(D24:G24) -> 33.530171 | G31: =C24 -> 16.343625
B33: D. IMPLIED VALUATION OF INFOSYS (applying peer mean/median multiples to Infosys' own metrics)
B34: Basis | C34: Infosys metric (₹ Cr) | D34: Peer Mean × | E34: Implied EV / Equity (₹ Cr, Mean) | F34: Peer Median × | G34: Implied EV / Equity (₹ Cr, Median) | H34: Per-share (₹, Mean basis)
B35: EV / EBITDA basis (Infosys EBITDA) | C35: =C10 -> 42280 | D35: =C28 -> 11.23742 | E35: =C35*D35 -> 475118.13 | F35: =D28 -> 11.394186 | G35: =C35*F35 -> 481746.16 | H35: =(E35-C13+C14)/Assumptions!$D$47 -> 1259.9386
B36: EV / EBIT basis (Infosys EBIT) | C36: =C8 -> 37378 | D36: =C29 -> 12.997754 | E36: =C36*D36 -> 485830.04 | F36: =D29 -> 12.774889 | G36: =C36*F36 -> 477499.79 | H36: =(E36-C13+C14)/Assumptions!$D$47 -> 1286.4008
B37: EV / Revenue basis (Infosys Revenue) | C37: =C7 -> 178650 | D37: =C30 -> 2.6313907 | E37: =C37*D37 -> 470097.95 | F37: =D30 -> 2.8127217 | G37: =C37*F37 -> 502492.73 | H37: =(E37-C13+C14)/Assumptions!$D$47 -> 1247.5369
B38: P/E basis (Infosys Net Profit) — direct equity value | C38: =C11 -> 29474 | D38: =C31 -> 21.796305 | E38: =C38*D38 -> 642424.29 | F38: =D31 -> 19.962531 | G38: =C38*F38 -> 588375.65 | H38: =E38/Assumptions!$D$47 -> 1587.0165
B40: Average implied value per share across the 4 methods (Mean-multiple basis) | H40: =AVERAGE(H36:H39) -> 1373.6514
B41: Current market price (₹, Aug-2026) & implied upside/(downside) | G41: =Assumptions!$D$46 -> 1190 | H41: =H40/G41-1 -> 0.15432892
B43: Observations:
B44: • Infosys trades at a discount to peer-average multiples on EV/EBITDA and EV/EBIT — largely reflecting TCS's premium rating (scale, margins) and the broader FY26 de-rating across Indian IT stocks amid AI-disruption concerns, rather than an Infosys-specific fundamental weakness (its own margins and returns are competitive within the peer set — see Ratio Analysis).
B45: • Tech Mahindra's elevated EV/EBITDA and P/E multiples reflect its smaller earnings base and post-turnaround re-rating rather than superior fundamentals — a useful reminder to sense-check outlier multiples rather than apply mean/median mechanically.
B46: • The comparable-company approach and the DCF (see DCF Valuation sheet) should be read together: DCF captures Infosys-specific growth and margin trajectory, while the comps approach captures how the market is currently pricing the sector — convergence or divergence between the two is itself an important finding for the report.

Sheet Ratio - Cover & Notes
B2: INFOSYS LIMITED - FINANCIAL RATIO ANALYSIS
B3: Financial Statement Analysis & Valuation (FSAV) Project - incl. Peer Comparison vs TCS & HCLTech
B5: Company | C5: Infosys Limited (NSE: INFY, BSE: 500209, NYSE ADR: INFY) - Peers: Tata Consultancy Services (TCS) and HCL Technologies (HCLTech)
B7: Basis of figures | C7: Consolidated financial statements as reported by each company (Infosys & TCS: IFRS; HCLTech: Ind AS) for FY 2025-26 (year ended 31 March 2026). Figures in Rs. Crore unless stated as per-share data.
B9: Market price used | C9: NSE closing prices, 6-Aug-2026 (same source/date for all three companies, for comparability): Infosys Rs. 1,165.00 · TCS Rs. 2,373.00 · HCLTech Rs. 1,335.00
B11: Primary sources - Infosys | C11: Infosys IR - Three-Year Overview (IFRS, Consolidated INR Basis): P&L Data & Balance Sheet Data, infosys.com/investors/reports-filings/financials/ ; Infosys Q4/FY26 IFRS-INR results, 23-Apr-2026; dividend announcements
B13: Primary sources - TCS | C13: TCS Integrated Annual Report 2025-26 - Consolidated Balance Sheet & Consolidated Statement of Profit and Loss (as uploaded), and the Directors' Report dividend table
B15: Primary sources - HCLTech | C15: HCLTech Integrated Annual Report 2025-26 - Consolidated Balance Sheet & Consolidated Statement of Profit and Loss (as uploaded), Note 3.27 (EPS), and the Directors' Report dividend table
B17: Key methodology notes | C17: 1) Infosys and TCS carry no material inventory beyond token amounts; HCLTech's inventory (mainly hardware/stock-in-trade) is small relative to revenue - all three are people-driven services businesses, so Quick Ratio is close to the Current Ratio for each. 2) None of the three companies carries material long-term financial borrowings; 'Total Debt' used in the Debt-Equity Ratio is predominantly lease liabilities recognised under Ind AS 116 / IFRS 16 (plus token working-capital borrowings for HCLTech). 3) Operating Profit (EBIT) for TCS and HCLTech is derived as Revenue from Operations − Total Operating Expenses excluding Finance Costs, Other Income and Exceptional Items - the same concept as Infosys's directly-disclosed 'Operating Profit' line, so the three are comparable. 4) Debtors = billed Trade Receivables (excludes unbilled revenue, shown separately by all three companies). 5) Debt Service Coverage Ratio = (Net Profit + Interest + Depreciation) ÷ (Interest + Current portion of lease liabilities/borrowings) - a reasonable proxy given none of the three has conventional term loans with fixed repayment schedules. 6) Net Profit Margin, ROA and ROE use Net Profit before minority-interest split (i.e. consolidated Profit for the Year) over Total Assets / Total Equity (both inclusive of non-controlling interests) for a like-for-like basis across all three companies. 7) Dividend Per Share: Infosys and TCS = interim(s) + final dividend declared for FY26; HCLTech pays only interim dividends through the year (no final) — the Rs. 54/share figure used is dividends actually paid during FY 2025-26 per its Directors' Report; a further Rs. 24/share interim was declared in April 2026 but is explicitly attributed by HCLTech to FY 2026-27.
B19: How this workbook is organised | C19: 'Input Data' holds Infosys's raw figures with sources. 'Ratio Analysis' computes Infosys's 19 ratios with live formulas, formula text, and interpretation. 'Peer Comparison' places Infosys, TCS and HCLTech side-by-side for FY 2025-26 across the same ratio set.

Sheet Input Data
A1: INFOSYS LIMITED — INPUT DATA (Consolidated, IFRS, Rs. Crore unless stated)
A3: Line Item | B3: Unit | C3: FY 2025-26 (Year ended 31-Mar-2026) | D3: FY 2024-25 (Year ended 31-Mar-2025) | E3: Source
A4: INCOME STATEMENT
A5: Revenue from Operations | B5: Rs. Cr | C5: 178650 | D5: 162990 | E5: Infosys IR Three-Year Overview (IFRS): P&L Data, infosys.com/investors/reports-filings/financials/profit-loss-data.html
A6: Cost of Sales | B6: Rs. Cr | C6: 124735 | D6: 113347 | E6: Infosys IR - Three-Year Overview (IFRS): P&L Data, infosys.com/investors/reports-filings/financials/profit-loss-data.html
A7: Gross Profit | B7: Rs. Cr | C7: =C5-C6 -> 53915 | D7: =D5-D6 -> 49643 | E7: Calculated from rows above in this sheet (see formula in cell)
A8: Total Operating Expenses (S&M + Admin) | B8: Rs. Cr | C8: 17661 | D8: 15219 | E8: Infosys IR - Three-Year Overview (IFRS): P&L Data, infosys.com/investors/reports-filings/financials/profit-loss-data.html
A9: Operating Profit (EBIT) | B9: Rs. Cr | C9: 36254 | D9: 34424 | E9: Infosys IR - Three-Year Overview (IFRS): P&L Data, infosys.com/investors/reports-filings/financials/profit-loss-data.html
A10: Other Income | B10: Rs. Cr | C10: 4157 | D10: 3600 | E10: Infosys IR - Three-Year Overview (IFRS): P&L Data, infosys.com/investors/reports-filings/financials/profit-loss-data.html
A11: Finance Cost (Interest Expense) | B11: Rs. Cr | C11: 416 | D11: 416 | E11: Infosys IR - Three-Year Overview (IFRS): P&L Data, infosys.com/investors/reports-filings/financials/profit-loss-data.html
A12: Profit Before Tax (PBT) | B12: Rs. Cr | C12: 39995 | D12: 37608 | E12: Infosys IR - Three-Year Overview (IFRS): P&L Data, infosys.com/investors/reports-filings/financials/profit-loss-data.html
A13: Income Tax Expense | B13: Rs. Cr | C13: 10521 | D13: 10858 | E13: Infosys IR - Three-Year Overview (IFRS): P&L Data, infosys.com/investors/reports-filings/financials/profit-loss-data.html
A14: Net Profit (Consolidated) | B14: Rs. Cr | C14: 29474 | D14: 26750 | E14: Infosys IR - Three-Year Overview (IFRS): P&L Data, infosys.com/investors/reports-filings/financials/profit-loss-data.html
A15: Net Profit attributable to Owners of the Company | B15: Rs. Cr | C15: 29440 | D15: 26713 | E15: Infosys IR - Three-Year Overview (IFRS): P&L Data, infosys.com/investors/reports-filings/financials/profit-loss-data.html
A17: BALANCE SHEET
A18: Total Assets | B18: Rs. Cr | C18: 155967 | D18: 148903 | E18: Infosys IR - Three-Year Overview (IFRS): Balance Sheet Data, infosys.com/investors/reports-filings/financials/balance-sheet-data.html
A19: Non-Current Assets | B19: Rs. Cr | C19: 52478 | D19: 51804 | E19: Infosys IR - Three-Year Overview (IFRS): Balance Sheet Data, infosys.com/investors/reports-filings/financials/balance-sheet-data.html
A20: Total Current Assets | B20: Rs. Cr | C20: =C18-C19 -> 103489 | D20: =D18-D19 -> 97099 | E20: Calculated from rows above in this sheet (see formula in cell)
A21: Net Current Assets (Working Capital) | B21: Rs. Cr | C21: 51167 | D21: 54249 | E21: Infosys IR - Three-Year Overview (IFRS): Balance Sheet Data, infosys.com/investors/reports-filings/financials/balance-sheet-data.html
A22: Total Current Liabilities | B22: Rs. Cr | C22: =C20-C21 -> 52322 | D22: =D20-D21 -> 42850 | E22: Calculated from rows above in this sheet (see formula in cell)
A23: Non-Current Liabilities | B23: Rs. Cr | C23: 10348 | D23: 9850 | E23: Infosys IR - Three-Year Overview (IFRS): Balance Sheet Data, infosys.com/investors/reports-filings/financials/balance-sheet-data.html
A24: Total Liabilities | B24: Rs. Cr | C24: =C22+C23 -> 62670 | D24: =D22+D23 -> 52700 | E24: Calculated from rows above in this sheet (see formula in cell)
A25: Total Equity (incl. Non-Controlling Interest) | B25: Rs. Cr | C25: 93297 | D25: 96203 | E25: Infosys IR - Three-Year Overview (IFRS): Balance Sheet Data, infosys.com/investors/reports-filings/financials/balance-sheet-data.html
A26: Capital Employed (Total Assets minus Current Liabilities) | B26: Rs. Cr | C26: =C18-C22 -> 103645 | D26: =D18-D22 -> 106053 | E26: Calculated from rows above in this sheet (see formula in cell)
A27: Trade Receivables (Debtors) | B27: Rs. Cr | C27: 35234 | D27: 31158 | E27: Infosys Q4 FY26 IFRS-INR Financial Statements (Financial Instruments/Credit Risk note), infosys.com, 23-Apr-2026
A28: Inventory | B28: Rs. Cr | C28: 0 | D28: 0 | E28: Not applicable - IT services company; Infosys carries no material inventory
A29: Total Debt (Lease Liabilities under Ind AS 116 — Infosys has no long-term borrowings) | B29: Rs. Cr | C29: 9176 | D29: 8222 | E29: StockAnalysis.com (Fiscal.ai) balance sheet - lease-liability breakdown, retrieved 06-Aug-2026
A31: PER-SHARE & MARKET DATA
A32: Earnings Per Share — Basic (Rs.) | B32: Rs. | C32: 71.58 | D32: 64.5 | E32: Infosys IR - Three-Year Overview (IFRS): P&L Data, infosys.com/investors/reports-filings/financials/profit-loss-data.html
A33: Weighted Average Shares Outstanding — Basic | B33: Crore shares | C33: 411.28 | D33: 414.16 | E33: Infosys IR - Three-Year Overview (IFRS): P&L Data, infosys.com/investors/reports-filings/financials/profit-loss-data.html
A34: Dividend Per Share (Interim + Final) | B34: Rs. | C34: 48 | D34: 43 | E34: Infosys dividend announcements: interim Rs.23 (Oct-2025) + final Rs.25 (Apr-2026) = Rs.48 FY26; interim Rs.21 (Oct-2024) + final Rs.22 (Apr-2025) = Rs.43 FY25
A35: Market Price Per Share (NSE close, 06-Aug-2026) | B35: Rs. | C35: 1165 | D35: 1165 | E35: NSE closing price, 6-Aug-2026 (Yahoo Finance / Bajaj Broking)
A36: Book Value Per Share | B36: Rs. | C36: =C25/C33 -> 226.84546 | D36: =D25/D33 -> 232.28462 | E36: Calculated from rows above in this sheet (see formula in cell)
A38: Legend: yellow fill = source input figure; white fill = calculated via formula from rows above

Sheet Ratio Analysis
A1: INFOSYS LIMITED — RATIO ANALYSIS (FY 2025-26 vs FY 2024-25, Consolidated IFRS)
A3: # | B3: Ratio | C3: Formula | D3: FY26 Calculation (figures in Rs. Cr unless noted) | E3: FY 2025-26 | F3: FY 2024-25 | G3: Interpretation
A4: LIQUIDITY RATIOS
A5: 1 | B5: Current Ratio | C5: Current Assets ÷ Current Liabilities | D5: Current Assets (Rs. 1,03,489 Cr) ÷ Current Liabilities (Rs. 52,322 Cr) | E5: ='Input Data'!C20/'Input Data'!C22 -> 1.9779252 | F5: ='Input Data'!D20/'Input Data'!D22 -> 2.266021 | G5: At ~1.98:1, Infosys holds nearly twice its current liabilities in current assets - a comfortably liquid position, well above the conventional 2:1 benchmark in FY25 and just under it in FY26. The modest FY26 dip mainly reflects cash deployed for the share buyback and higher dividend payouts; short-term solvency remains strong.
A6: 2 | B6: Quick Ratio | C6: (Current Assets − Inventory) ÷ Current Liabilities | D6: Inventory is nil (IT services company), so Quick Ratio ≈ Current Ratio | E6: =('Input Data'!C20-'Input Data'!C28)/'Input Data'!C22 -> 1.9779252 | F6: =('Input Data'!D20-'Input Data'!D28)/'Input Data'!D22 -> 2.266021 | G6: Because Infosys carries no material inventory, the Quick Ratio is effectively identical to the Current Ratio. This confirms the company's liquid assets (cash, investments, receivables) alone are sufficient to cover short-term obligations without relying on inventory liquidation.
A7: PROFITABILITY RATIOS
A8: 3 | B8: Gross Profit Margin | C8: Gross Profit ÷ Revenue × 100 | D8: Gross Profit ÷ Revenue | E8: ='Input Data'!C7/'Input Data'!C5 -> 0.30179121 | F8: ='Input Data'!D7/'Input Data'!D5 -> 0.30457697 | G8: Gross margin held broadly steady around 30%, typical for a scaled IT-services business where employee/delivery costs dominate cost of sales. The near-flat trend shows pricing and delivery efficiency have kept pace with wage inflation and investment in AI-led delivery.
A9: 4 | B9: Operating Profit Margin | C9: Operating Profit (EBIT) ÷ Revenue × 100 | D9: Operating Profit ÷ Revenue | E9: ='Input Data'!C9/'Input Data'!C5 -> 0.20293311 | F9: ='Input Data'!D9/'Input Data'!D5 -> 0.21120314 | G9: Operating margin eased from ~21.1% to ~20.3%, mainly due to a one-off increase in gratuity/leave liability from India's new Labour Codes. Management's 'adjusted' (non-IFRS) operating margin, which excludes this one-off, held at 21% — underlying operating efficiency was broadly stable.
A10: 5 | B10: Net Profit Margin | C10: Net Profit ÷ Revenue × 100 | D10: Net Profit (Consolidated) ÷ Revenue | E10: ='Input Data'!C14/'Input Data'!C5 -> 0.16498181 | F10: ='Input Data'!D14/'Input Data'!D5 -> 0.1641205 | G10: Net margin improved slightly to ~16.5%, helped by higher other income (treasury/interest income) and a lower effective tax rate, which offset the labour-code related hit to operating profit.
A11: 6 | B11: Return on Assets (ROA) | C11: Net Profit ÷ Total Assets × 100 | D11: Net Profit ÷ Total Assets | E11: ='Input Data'!C14/'Input Data'!C18 -> 0.18897587 | F11: ='Input Data'!D14/'Input Data'!D18 -> 0.17964715 | G11: ROA improved to ~18.9% from ~18.0%, showing Infosys is generating more profit per rupee of assets employed — a services/asset-light business model naturally supports a high ROA relative to capital-intensive industries.
A12: 7 | B12: Return on Equity (ROE) | C12: Net Profit ÷ Total Equity × 100 | D12: Net Profit ÷ Total Equity | E12: ='Input Data'!C14/'Input Data'!C25 -> 0.31591584 | F12: ='Input Data'!D14/'Input Data'!D25 -> 0.27805786 | G12: ROE rose to ~31.6% from ~27.8%, boosted by the FY26 share buyback which shrank the equity base while profit grew — a strong return for shareholders, though partly a function of capital return policy rather than operating performance alone.
A13: 8 | B13: Return on Capital Employed (ROCE) | C13: EBIT ÷ Capital Employed × 100, where Capital Employed = Total Assets − Current Liabilities | D13: Operating Profit ÷ Capital Employed | E13: ='Input Data'!C9/'Input Data'!C26 -> 0.34979015 | F13: ='Input Data'!D9/'Input Data'!D26 -> 0.32459242 | G13: ROCE of ~35% (up from ~32%) confirms Infosys deploys its long-term capital very efficiently — well above its cost of capital — consistent with an asset-light, cash-generative services model.
A14: EFFICIENCY / TURNOVER RATIOS
A15: 9 | B15: Inventory Turnover | C15: Revenue ÷ Average Inventory | D15: Not applicable — Infosys carries no material inventory (IT services company) | E15: N/A | F15: N/A | G15: Not a meaningful ratio for Infosys: as an IT services provider, it does not hold finished-goods or trading inventory in any significant amount. This itself is a useful observation for the report — the working-capital cycle is driven by receivables, not inventory.
A16: 10 | B16: Debtors Turnover | C16: Revenue ÷ Trade Receivables | D16: Revenue ÷ Trade Receivables (Debtors) | E16: ='Input Data'!C5/'Input Data'!C27 -> 5.0703866 | F16: ='Input Data'!D5/'Input Data'!D27 -> 5.2310803 | G16: Debtors turnover of ~5.1x (≈72 days sales outstanding) is consistent with typical enterprise IT services billing/collection cycles. A broadly stable ratio indicates collection discipline has kept pace with revenue growth.
A17: 11 | B17: Asset Turnover | C17: Revenue ÷ Total Assets | D17: Revenue ÷ Total Assets | E17: ='Input Data'!C5/'Input Data'!C18 -> 1.1454346 | F17: ='Input Data'!D5/'Input Data'!D18 -> 1.0946052 | G17: Asset turnover improved slightly to ~1.15x, showing Infosys generated more revenue per rupee of total assets — a gradual efficiency gain even as the balance sheet grew (partly from acquisitions).
A18: 12 | B18: Working Capital Turnover | C18: Revenue ÷ Net Working Capital, where Net Working Capital = Current Assets − Current Liabilities | D18: Revenue ÷ Net Current Assets | E18: ='Input Data'!C5/'Input Data'!C21 -> 3.4915082 | F18: ='Input Data'!D5/'Input Data'!D21 -> 3.0044793 | G18: Working capital turnover rose to ~3.5x from ~3.0x, indicating Infosys is generating more revenue per rupee of net working capital — partly because working capital itself shrank (higher payouts/buyback) while revenue grew, a positive efficiency signal but worth monitoring for liquidity headroom.
A19: SOLVENCY RATIOS
A20: 13 | B20: Debt–Equity Ratio | C20: Total Debt ÷ Total Equity | D20: Total Debt (lease liabilities) ÷ Total Equity | E20: ='Input Data'!C29/'Input Data'!C25 -> 0.098352573 | F20: ='Input Data'!D29/'Input Data'!D25 -> 0.08546511 | G20: At ~0.10:1, Infosys is virtually debt-free — the only liability captured here is lease obligations under Ind AS 116/IFRS 16, not conventional borrowings. This reflects a very conservative capital structure and strong balance-sheet flexibility.
A21: 14 | B21: Interest Coverage Ratio | C21: EBIT ÷ Interest Expense | D21: Operating Profit ÷ Finance Cost | E21: ='Input Data'!C9/'Input Data'!C11 -> 87.149038 | F21: ='Input Data'!D9/'Input Data'!D11 -> 82.75 | G21: Interest coverage of ~85–90x is exceptionally high, confirming Infosys's finance costs (mostly lease interest) are trivial relative to operating profit — there is no meaningful risk of default on interest obligations.
A22: 15 | B22: Debt Service Coverage Ratio (DSCR) | C22: (Net Profit + Interest + Depreciation) ÷ (Interest + Current Maturities of Debt) | D22: Not meaningfully computable from disclosed three-year summary data (annual depreciation not separately reported); in any case Infosys has no long-term borrowings with a fixed repayment schedule | E22: N/A | F22: N/A | G22: DSCR is not a meaningful metric for Infosys: the company has no long-term debt requiring scheduled principal and interest servicing. Its only 'debt' is lease liabilities under Ind AS 116/IFRS 16, which are routinely covered many times over by operating cash flow. This debt-free position is itself an important solvency finding for the report.
A23: MARKET / VALUATION RATIOS
A24: 16 | B24: Earnings Per Share (EPS) | C24: Net Profit (Basic) ÷ Weighted Average No. of Equity Shares | D24: As reported by Infosys | E24: ='Input Data'!C32 -> 71.58 | F24: ='Input Data'!D32 -> 64.5 | G24: Basic EPS grew ~11% to Rs. 71.58, ahead of net profit growth of ~10.2%, because the share count fell slightly due to the buyback — a direct benefit to per-share earnings for continuing shareholders.
A25: 17 | B25: Price–Earnings (P/E) Ratio | C25: Market Price per Share ÷ EPS | D25: Market Price (NSE, 06-Aug-2026) ÷ EPS (Basic) | E25: ='Input Data'!C35/'Input Data'!C32 -> 16.275496 | F25: ='Input Data'!D35/'Input Data'!D32 -> 18.062016 | G25: At a P/E of ~16x on FY26 earnings (against the market price of Rs. 1,165 on 6-Aug-2026), Infosys trades below its historical average multiple (which was often 22–25x), reflecting weaker sentiment toward Indian IT services amid muted global demand and AI-disruption concerns — a P/E column is shown for FY25 only to illustrate the ratio mechanics, using the same current price; it is not a historical FY25 market P/E.
A26: 18 | B26: Dividend Payout Ratio | C26: Dividend Per Share ÷ EPS × 100 | D26: Dividend Per Share ÷ EPS (Basic) | E26: ='Input Data'!C34/'Input Data'!C32 -> 0.67057837 | F26: ='Input Data'!D34/'Input Data'!D32 -> 0.66666667 | G26: Infosys paid out ~67% of FY26 earnings as dividends (Rs. 48 of Rs. 71.58 EPS), consistent with its capital allocation policy of returning up to 85% of free cash flow via dividends and buybacks — a shareholder-friendly, high-payout profile typical of mature IT services firms.
A27: 19 | B27: Book Value Per Share | C27: Total Equity ÷ No. of Equity Shares Outstanding | D27: Total Equity ÷ Weighted Average Shares | E27: ='Input Data'!C36 -> 226.84546 | F27: ='Input Data'!D36 -> 232.28462 | G27: Book value per share fell slightly to ~Rs. 227 (from ~Rs. 232) despite profit growth, because the FY26 share buyback returned capital to shareholders and shrank the equity base faster than retained earnings could rebuild it — a deliberate capital-return outcome rather than value erosion.

Sheet Peer Input Data
A1: TCS & HCLTECH — INPUT DATA, FY 2025-26 (Year ended 31 March 2026), Consolidated, Rs. Crore unless stated
A3: Line Item | B3: Unit | C3: TCS FY 2025-26 | D3: HCLTech FY 2025-26 | E3: Source
A4: INCOME STATEMENT
A5: Revenue from Operations | B5: Rs. Cr | C5: 267021 | D5: 130144 | E5: TCS Integrated Annual Report 2025-26 — Consolidated Statement of Profit and Loss (uploaded)
A6: Total Operating Expenses (excl. Finance Cost, Other Income, Exceptional Items) | B6: Rs. Cr | C6: 200183 | D6: 107747 | E6: Derived: Total Expenses less Finance Costs (TCS: 2,01,410-1,227; HCLTech: 1,08,616-869)
A7: Operating Profit (EBIT) | B7: Rs. Cr | C7: =C5-C6 -> 66838 | D7: =D5-D6 -> 22397 | E7: Calculated from rows above in this sheet
A8: Finance Cost (Interest Expense) | B8: Rs. Cr | C8: 1227 | D8: 869 | E8: TCS Integrated Annual Report 2025-26 — Consolidated Statement of Profit and Loss (uploaded)
A9: Depreciation & Amortisation | B9: Rs. Cr | C9: 5560 | D9: 4355 | E9: TCS Integrated Annual Report 2025-26 — Consolidated Statement of Profit and Loss (uploaded)
A10: Net Profit (Consolidated, 'Profit for the Year') | B10: Rs. Cr | C10: 49454 | D10: 16652 | E10: TCS Integrated Annual Report 2025-26 — Consolidated Statement of Profit and Loss (uploaded)
A12: BALANCE SHEET
A13: Total Assets | B13: Rs. Cr | C13: 182372 | D13: 116258 | E13: TCS Integrated Annual Report 2025-26 — Consolidated Balance Sheet (uploaded)
A14: Total Current Assets | B14: Rs. Cr | C14: 135705 | D14: 70542 | E14: TCS Integrated Annual Report 2025-26 — Consolidated Balance Sheet (uploaded)
A15: Total Current Liabilities | B15: Rs. Cr | C15: 60914 | D15: 31826 | E15: TCS Integrated Annual Report 2025-26 — Consolidated Balance Sheet (uploaded)
A16: Net Current Assets (Working Capital) | B16: Rs. Cr | C16: =C14-C15 -> 74791 | D16: =D14-D15 -> 38716 | E16: Calculated from rows above in this sheet
A17: Total Equity (incl. Non-Controlling Interest) | B17: Rs. Cr | C17: 108478 | D17: 75197 | E17: TCS Integrated Annual Report 2025-26 — Consolidated Balance Sheet (uploaded)
A18: Equity attributable to Owners (excl. NCI) | B18: Rs. Cr | C18: 107240 | D18: 75165 | E18: TCS Integrated Annual Report 2025-26 — Consolidated Balance Sheet (uploaded)
A19: Capital Employed (Total Assets minus Current Liabilities) | B19: Rs. Cr | C19: =C13-C15 -> 121458 | D19: =D13-D15 -> 84432 | E19: Calculated from rows above in this sheet
A20: Trade Receivables — Billed (Debtors) | B20: Rs. Cr | C20: 57630 | D20: 23585 | E20: TCS Integrated Annual Report 2025-26 — Consolidated Balance Sheet (uploaded)
A21: Inventory | B21: Rs. Cr | C21: 29 | D21: 239 | E21: TCS Integrated Annual Report 2025-26 — Consolidated Balance Sheet (uploaded)
A22: Total Debt (Lease Liabilities + Borrowings, Current + Non-current) | B22: Rs. Cr | C22: 11283 | D22: 5215 | E22: TCS: lease liab. 9,453(NC)+1,830(C)=11,283 (financial-instruments note); HCLTech: borrowings 37(NC)+122(C) + lease liab. 3,180(NC)+1,876(C) = 5,215
A23: Current Portion of Debt (for DSCR) | B23: Rs. Cr | C23: 3057 | D23: 1998 | E23: TCS: current lease liabilities 1,830 + finance cost 1,227 used as annual debt-service base; HCLTech: current borrowings 122 + current lease liabilities 1,876 = 1,998
A25: PER-SHARE & MARKET DATA
A26: Earnings Per Share — Basic (Rs.) | B26: Rs. | C26: 136.01 | D26: 61.46 | E26: TCS Integrated Annual Report 2025-26 — Consolidated Statement of Profit and Loss (uploaded)
A27: Weighted Average Shares Outstanding — Basic | B27: Crore shares | C27: 361.81 | D27: 270.76 | E27: TCS Integrated Annual Report 2025-26 — Consolidated Statement of Profit and Loss (uploaded)
A28: Dividend Per Share — FY26 | B28: Rs. | C28: 64 | D28: 54 | E28: TCS Annual Report 2025-26 — Dividend table: 3 interim @ Rs.11 + final Rs.31 recommended = Rs.64 for FY26
A29: Market Price Per Share (NSE close, 06-Aug-2026) | B29: Rs. | C29: 2373 | D29: 1335 | E29: NSE closing price, 6-Aug-2026 (Yahoo Finance)
A30: Book Value Per Share (Owners' Equity basis) | B30: Rs. | C30: =C18/C27 -> 296.39866 | D30: =D18/D27 -> 277.60748 | E30: Calculated from rows above in this sheet
A32: Legend: yellow fill = source input figure (from uploaded annual reports); white fill = calculated via formula

Sheet Peer Comparison
A1: PEER COMPARISON — INFOSYS vs TCS vs HCLTECH (FY 2025-26, Consolidated)
A2: Ratio formulas and methodology notes are documented in the 'Ratio Analysis' and 'Cover & Notes' sheets
A4: # | B4: Ratio | C4: Infosys | D4: TCS | E4: HCLTech | F4: Best in Peer Set
A5: 1 | B5: Current Ratio | C5: ='Input Data'!C20/'Input Data'!C22 -> 1.9779252 | D5: ='Peer Input Data'!C14/'Peer Input Data'!C15 -> 2.227813 | E5: ='Peer Input Data'!D14/'Peer Input Data'!D15 -> 2.2164897 | F5: =IF(AND(C5>=D5,C5>=E5),"Infosys",IF(AND(D5>=C5,D5>=E5),"TCS","HCLTech")) -> TCS
A6: 2 | B6: Quick Ratio | C6: =('Input Data'!C20-'Input Data'!C28)/'Input Data'!C22 -> 1.9779252 | D6: =('Peer Input Data'!C14-'Peer Input Data'!C21)/'Peer Input Data'!C15 -> 2.2273369 | E6: =('Peer Input Data'!D14-'Peer Input Data'!D21)/'Peer Input Data'!D15 -> 2.2089801 | F6: =IF(AND(C6>=D6,C6>=E6),"Infosys",IF(AND(D6>=C6,D6>=E6),"TCS","HCLTech")) -> TCS
A7: 3 | B7: Operating Profit Margin | C7: ='Input Data'!C9/'Input Data'!C5 -> 0.20293311 | D7: ='Peer Input Data'!C7/'Peer Input Data'!C5 -> 0.2503099 | E7: ='Peer Input Data'!D7/'Peer Input Data'!D5 -> 0.17209399 | F7: =IF(AND(C7>=D7,C7>=E7),"Infosys",IF(AND(D7>=C7,D7>=E7),"TCS","HCLTech")) -> TCS
A8: 4 | B8: Net Profit Margin | C8: ='Input Data'!C14/'Input Data'!C5 -> 0.16498181 | D8: ='Peer Input Data'!C10/'Peer Input Data'!C5 -> 0.18520641 | E8: ='Peer Input Data'!D10/'Peer Input Data'!D5 -> 0.12795058 | F8: =IF(AND(C8>=D8,C8>=E8),"Infosys",IF(AND(D8>=C8,D8>=E8),"TCS","HCLTech")) -> TCS
A9: 5 | B9: ROA | C9: ='Input Data'!C14/'Input Data'!C18 -> 0.18897587 | D9: ='Peer Input Data'!C10/'Peer Input Data'!C13 -> 0.27117101 | E9: ='Peer Input Data'!D10/'Peer Input Data'!D13 -> 0.14323315 | F9: =IF(AND(C9>=D9,C9>=E9),"Infosys",IF(AND(D9>=C9,D9>=E9),"TCS","HCLTech")) -> TCS
A10: 6 | B10: ROE | C10: ='Input Data'!C14/'Input Data'!C25 -> 0.31591584 | D10: ='Peer Input Data'!C10/'Peer Input Data'!C17 -> 0.45588967 | E10: ='Peer Input Data'!D10/'Peer Input Data'!D17 -> 0.221445 | F10: =IF(AND(C10>=D10,C10>=E10),"Infosys",IF(AND(D10>=C10,D10>=E10),"TCS","HCLTech")) -> TCS
A11: 7 | B11: ROCE | C11: ='Input Data'!C9/'Input Data'!C26 -> 0.34979015 | D11: ='Peer Input Data'!C7/'Peer Input Data'!C19 -> 0.55029722 | E11: ='Peer Input Data'!D7/'Peer Input Data'!D19 -> 0.26526672 | F11: =IF(AND(C11>=D11,C11>=E11),"Infosys",IF(AND(D11>=C11,D11>=E11),"TCS","HCLTech")) -> TCS
A12: 8 | B12: Debtors Turnover | C12: ='Input Data'!C5/'Input Data'!C27 -> 5.0703866 | D12: ='Peer Input Data'!C5/'Peer Input Data'!C20 -> 4.633368 | E12: ='Peer Input Data'!D5/'Peer Input Data'!D20 -> 5.5180835 | F12: =IF(AND(C12>=D12,C12>=E12),"Infosys",IF(AND(D12>=C12,D12>=E12),"TCS","HCLTech")) -> HCLTech
A13: 9 | B13: Asset Turnover | C13: ='Input Data'!C5/'Input Data'!C18 -> 1.1454346 | D13: ='Peer Input Data'!C5/'Peer Input Data'!C13 -> 1.4641557 | E13: ='Peer Input Data'!D5/'Peer Input Data'!D13 -> 1.1194412 | F13: =IF(AND(C13>=D13,C13>=E13),"Infosys",IF(AND(D13>=C13,D13>=E13),"TCS","HCLTech")) -> TCS
A14: 10 | B14: Working Capital Turnover | C14: ='Input Data'!C5/'Input Data'!C21 -> 3.4915082 | D14: ='Peer Input Data'!C5/'Peer Input Data'!C16 -> 3.570229 | E14: ='Peer Input Data'!D5/'Peer Input Data'!D16 -> 3.3615043 | F14: =IF(AND(C14>=D14,C14>=E14),"Infosys",IF(AND(D14>=C14,D14>=E14),"TCS","HCLTech")) -> TCS
A15: 11 | B15: Debt-Equity | C15: ='Input Data'!C29/'Input Data'!C25 -> 0.098352573 | D15: ='Peer Input Data'!C22/'Peer Input Data'!C17 -> 0.10401187 | E15: ='Peer Input Data'!D22/'Peer Input Data'!D17 -> 0.069351171 | F15: =IF(AND(C15<=D15,C15<=E15),"Infosys",IF(AND(D15<=C15,D15<=E15),"TCS","HCLTech")) -> HCLTech
A16: 12 | B16: Interest Coverage | C16: ='Input Data'!C9/'Input Data'!C11 -> 87.149038 | D16: ='Peer Input Data'!C7/'Peer Input Data'!C8 -> 54.472698 | E16: ='Peer Input Data'!D7/'Peer Input Data'!D8 -> 25.773303 | F16: =IF(AND(C16>=D16,C16>=E16),"Infosys",IF(AND(D16>=C16,D16>=E16),"TCS","HCLTech")) -> Infosys
A17: 13 | B17: DSCR | C17: ="N/A" -> N/A | D17: =('Peer Input Data'!C10+'Peer Input Data'!C8+'Peer Input Data'!C9)/'Peer Input Data'!C23 -> 18.397448 | E17: =('Peer Input Data'!D10+'Peer Input Data'!D8+'Peer Input Data'!D9)/'Peer Input Data'!D23 -> 10.948949 | F17: —
A18: 14 | B18: EPS | C18: ='Input Data'!C32 -> 71.58 | D18: ='Peer Input Data'!C26 -> 136.01 | E18: ='Peer Input Data'!D26 -> 61.46 | F18: —
A19: 15 | B19: P/E | C19: ='Input Data'!C35/'Input Data'!C32 -> 16.275496 | D19: ='Peer Input Data'!C29/'Peer Input Data'!C26 -> 17.447247 | E19: ='Peer Input Data'!D29/'Peer Input Data'!D26 -> 21.721445 | F19: —
A20: 16 | B20: Dividend Payout | C20: ='Input Data'!C34/'Input Data'!C32 -> 0.67057837 | D20: ='Peer Input Data'!C28/'Peer Input Data'!C26 -> 0.47055364 | E20: ='Peer Input Data'!D28/'Peer Input Data'!D26 -> 0.87862024 | F20: —
A21: 17 | B21: Book Value/Share | C21: ='Input Data'!C36 -> 226.84546 | D21: ='Peer Input Data'!C30 -> 296.39866 | E21: ='Peer Input Data'!D30 -> 277.60748 | F21: —
A23: Notes:
A24: 1) All figures are FY 2025-26 (year ended 31 March 2026), Consolidated financial statements, Rs. Crore basis unless a per-share/ratio figure. Market prices are NSE closes for 6-Aug-2026 (same date, same source for all three).
A25: 2) 'Best in Peer Set' flags the strongest ratio value across the three companies for ratios where a clear directional preference exists (e.g. higher margins/returns/turnover are better; lower gearing is better). It is not shown for EPS, P/E, Dividend Payout, Book Value/Share and DSCR, which do not have a universally 'better' direction (e.g. a low P/E can reflect either undervaluation or weaker growth prospects; a high payout ratio can reflect either shareholder-friendliness or fewer reinvestment opportunities).
A26: 3) DSCR for Infosys is marked N/A — see the 'Ratio Analysis' sheet and Cover & Notes for the rationale (Infosys has no long-term debt with a fixed repayment schedule). TCS and HCLTech DSCR use the proxy formula (Net Profit + Interest + Depreciation) ÷ (Interest + Current portion of lease liabilities/borrowings), documented in 'Peer Input Data'.
A27: 4) See 'Cover & Notes' for full source citations and methodology assumptions (operating profit derivation for TCS/HCLTech, debtors definition, dividend basis for HCLTech, etc.).

Sheet DCF - Cover & Notes
B3: INFOSYS LIMITED
B4: Discounted Cash Flow (DCF) Valuation Model
B5: Consolidated (IFRS) | NSE: INFY | BSE: 500209 | NYSE: INFY
B7: Valuation date: March 31, 2026 (FY26 year-end) | Prepared: August 11, 2026
B10: Contents
B11: 0. All-in-One DCF (single worksheet) | C11: Entire model - assumptions through valuation - consolidated on ONE sheet for easy printing/scanning
B12: 1. Assumptions | C12: Assumptions & Drivers - revenue, margin, working capital, WACC, terminal growth, share data
B13: 2. Income Statement | C13: Consolidated Income Statement - FY24A-FY26A actuals & FY27E-FY31E forecast
B14: 3. Balance Sheet | C14: Consolidated Balance Sheet - fully linked, FY24A-FY31E
B15: 4. Cash Flow | C15: Consolidated Statement of Cash Flows & Free Cash Flow build
B16: 5. WC & PPE Schedule | C16: Working Capital and Fixed Asset (PPE) roll-forward schedules
B17: 6. Capital Structure | C17: Debt, cash & WACC support schedule
B18: 7. DCF Valuation | C18: Unlevered FCFF valuation, EV-to-equity bridge, intrinsic value & sensitivity
B19: 8. Charts & Outputs | C19: Key output dashboard and charts
B22: Headline Output
B23: Intrinsic Value per Share | C23: ='DCF Valuation'!D37 -> 1220.0567
B24: Current Market Price (Aug 10, 2026) | C24: ='DCF Valuation'!D40 -> 1190
B25: Upside / (Downside) | C25: ='DCF Valuation'!D41 -> 0.025257713
B26: WACC | C26: =Assumptions!D39 -> 0.13031067
B27: Terminal Growth Rate | C27: =Assumptions!D42 -> 0.05

Sheet All-in-One DCF
A1: INFOSYS LIMITED — DCF VALUATION MODEL (Single-Worksheet Edition)
A2: Consolidated (IFRS) | ₹ Crore unless stated | Fiscal Year ends March 31 | Valuation date: March 31, 2026
C4: Intrinsic Value/Share (₹) | D4: Current Price (₹) | E4: Upside/(Downside) | F4: WACC | G4: Terminal Growth | H4: Enterprise Value (₹cr)
C5: =D239 -> 1220.0567 | D5: =D242 -> 1190 | E5: =D243 -> 0.025257713 | F5: =D39 -> 0.13031067 | G5: =D42 -> 0.05 | H5: =D230 -> 440752.94
A7: SECTION A — ASSUMPTIONS & DRIVERS
A8: (₹ Crore, unless stated) | C8: FY2024A | D8: FY2025A | E8: FY2026A | F8: FY2027E | G8: FY2028E | H8: FY2029E | I8: FY2030E | J8: FY2031E
A9: 1. Revenue & Margin Drivers
A10: Revenue growth, % y/y | C10: n/a | D10: =D51/C51-1 -> 0.060649444 | E10: =E51/D51-1 -> 0.096079514 | F10: 0.08 | G10: 0.085 | H10: 0.09 | I10: 0.09 | J10: 0.085
A11: Employee benefit expense, % of revenue | C11: 0.5376456 | D11: 0.52733297 | E11: 0.53229219 | F11: 0.532 | G11: 0.532 | H11: 0.532 | I11: 0.532 | J11: 0.532
A12: Depreciation & amortization, % of revenue | C12: 0.030441856 | D12: 0.029523284 | E12: 0.027439127 | F12: 0.027 | G12: 0.027 | H12: 0.027 | I12: 0.027 | J12: 0.027
A13: EBIT margin (Operating margin), % | C13: 0.20659205 | D13: 0.21120314 | E13: 0.20922474 | F13: 0.21 | G13: 0.213 | H13: 0.216 | I13: 0.219 | J13: 0.22
A14: Other income (net), % of revenue | C14: 0.030656602 | D14: 0.022087245 | E14: 0.024192555 | F14: 0.022 | G14: 0.022 | H14: 0.022 | I14: 0.022 | J14: 0.022
A15: Finance cost, % of revenue | C15: 0.003058502 | D15: 0.0025523038 | E15: 0.0023285754 | F15: 0.0025 | G15: 0.0025 | H15: 0.0025 | I15: 0.0025 | J15: 0.0025
A16: Effective tax rate, % | C16: 0.27064577 | D16: 0.28871517 | E16: 0.26305788 | F16: 0.27 | G16: 0.27 | H16: 0.27 | I16: 0.27 | J16: 0.27
A17: Non-controlling interest, % of consolidated PAT | C17: 0.00057147211 | D17: 0.0013831776 | E17: 0.0011535591 | F17: 0.0013 | G17: 0.0013 | H17: 0.0013 | I17: 0.0013 | J17: 0.0013
A19: 2. Working Capital Assumptions
A20: Days Sales Outstanding — Trade receivables (days) | C20: 71.715006 | D20: 69.775262 | E20: 71.986622 | F20: 71 | G20: 71 | H20: 71 | I20: 71 | J20: 71
A21: Days Payable Outstanding — Trade payables (days) | C21: 9.3963688 | D21: 9.3248666 | E21: 9.6924713 | F21: 9.5 | G21: 9.5 | H21: 9.5 | I21: 9.5 | J21: 9.5
A22: Other current assets (net operating), % of revenue | C22: 0.20523199 | D22: 0.17794957 | E22: 0.18530087 | F22: 0.19 | G22: 0.19 | H22: 0.19 | I22: 0.19 | J22: 0.19
A23: Other current liabilities (net operating), % of revenue | C23: 0.21395848 | D23: 0.22228971 | E23: 0.2486314 | F23: 0.25 | G23: 0.25 | H23: 0.25 | I23: 0.25 | J23: 0.25
A25: 3. Capex & Payout Policy
A26: Capital expenditure, % of revenue | C26: 0.0143229 | D26: 0.013724768 | E26: 0.015264484 | F26: 0.015 | G26: 0.015 | H26: 0.015 | I26: 0.015 | J26: 0.015
A27: Dividend + buyback payout, % of Free Cash Flow | C27: n/a | D27: n/a | E27: n/a | F27: 0.85 | G27: 0.85 | H27: 0.85 | I27: 0.85 | J27: 0.85
A29: 4. Discount Rate (WACC) Build-up — single estimate, column D
A30: Risk-free rate (India 10-yr G-Sec yield) | D30: 0.068
A31: Levered Beta (Infosys) | D31: 0.85
A32: India equity risk premium | D32: 0.075
A33: Cost of equity = Rf + Beta × ERP | D33: =D30+D31*D32 -> 0.13175
A34: Pre-tax cost of debt (lease discount rate proxy) | D34: 0.075
A35: Marginal tax rate (for after-tax cost of debt) | D35: 0.27
A36: After-tax cost of debt | D36: =D34*(1-D35) -> 0.05475
A37: Weight of debt, % | D37: =D125 -> 0.018692655
A38: Weight of equity, % | D38: =1-D37 -> 0.98130735
A39: WACC (Weighted Average Cost of Capital) | D39: =D33*D38+D36*D37 -> 0.13031067
A41: 5. Terminal Value & Share Data
A42: Terminal (perpetuity) growth rate | D42: 0.05
A43: Check: WACC − Terminal growth rate (must be > 0) | D43: =D39-D42 -> 0.080310666
A44: Current share price (NSE, Aug 10, 2026) | D44: 1190
A45: Diluted weighted-average shares outstanding (crore) | D45: 404.8
A46: Implied current market capitalization | D46: =D44*D45 -> 481712
A49: SECTION B — CONSOLIDATED INCOME STATEMENT
A50: (₹ Crore, unless stated) | C50: FY2024A | D50: FY2025A | E50: FY2026A | F50: FY2027E | G50: FY2028E | H50: FY2029E | I50: FY2030E | J50: FY2031E
A51: Revenue from operations | C51: 153670 | D51: 162990 | E51: 178650 | F51: =E51*(1+F10) -> 192942 | G51: =F51*(1+G10) -> 209342.07 | H51: =G51*(1+H10) -> 228182.86 | I51: =H51*(1+I10) -> 248719.31 | J51: =I51*(1+J10) -> 269860.46
A52: % growth y/y | C52: n/a | D52: =D51/C51-1 -> 0.060649444 | E52: =E51/D51-1 -> 0.096079514 | F52: =F10 -> 0.08 | G52: =G10 -> 0.085 | H52: =H10 -> 0.09 | I52: =I10 -> 0.09 | J52: =J10 -> 0.085
A54: Operating Expenses
A55: Employee benefit expenses | C55: 82620 | D55: 85950 | E55: 95094 | F55: =F51*F11 -> 102645.14 | G55: =G51*G11 -> 111369.98 | H55: =H51*H11 -> 121393.28 | I55: =I51*I11 -> 132318.67 | J55: =J51*J11 -> 143565.76
A56: Depreciation & amortization expenses | C56: 4678 | D56: 4812 | E56: 4902 | F56: =F51*F12 -> 5209.434 | G56: =G51*G12 -> 5652.2359 | H56: =H51*H12 -> 6160.9371 | I56: =I51*I12 -> 6715.4215 | J56: =J51*J12 -> 7286.2323
A57: Other operating expenses (sub-contractors, travel, S&M, G&A) | C57: 34625 | D57: 37804 | E57: 41276 | F57: =F51*(1-F13)-F55-F56 -> 44569.602 | G57: =G51*(1-G13)-G55-G56 -> 47729.992 | H57: =H51*(1-H13)-H55-H56 -> 51341.143 | I57: =I51*(1-I13)-I55-I56 -> 55215.688 | J57: =J51*(1-J13)-J55-J56 -> 59639.161
A58: Total operating expenses | C58: =C55+C56+C57 -> 121923 | D58: =D55+D56+D57 -> 128566 | E58: =E55+E56+E57 -> 141272 | F58: =F55+F56+F57 -> 152424.18 | G58: =G55+G56+G57 -> 164752.21 | H58: =H55+H56+H57 -> 178895.36 | I58: =I55+I56+I57 -> 194249.78 | J58: =J55+J56+J57 -> 210491.15
A60: EBIT (Operating Profit) | C60: =C51-C58 -> 31747 | D60: =D51-D58 -> 34424 | E60: =E51-E58 -> 37378 | F60: =F51-F58 -> 40517.82 | G60: =G51-G58 -> 44589.861 | H60: =H51-H58 -> 49287.497 | I60: =I51-I58 -> 54469.53 | J60: =J51-J58 -> 59369.3
A61: EBIT margin, % | C61: =C60/C51 -> 0.20659205 | D61: =D60/D51 -> 0.21120314 | E61: =E60/E51 -> 0.20922474 | F61: =F60/F51 -> 0.21 | G61: =G60/G51 -> 0.213 | H61: =H60/H51 -> 0.216 | I61: =I60/I51 -> 0.219 | J61: =J60/J51 -> 0.22
A63: Other income, net | C63: 4711 | D63: 3600 | E63: 4322 | F63: =F51*F14 -> 4244.724 | G63: =G51*G14 -> 4605.5255 | H63: =H51*H14 -> 5020.0228 | I63: =I51*I14 -> 5471.8249 | J63: =J51*J14 -> 5936.93
A64: Finance cost | C64: 470 | D64: 416 | E64: 416 | F64: =F51*F15 -> 482.355 | G64: =G51*G15 -> 523.35518 | H64: =H51*H15 -> 570.45714 | I64: =I51*I15 -> 621.79828 | J64: =J51*J15 -> 674.65114
A65: Profit before exceptional item and tax | C65: =C60+C63-C64 -> 35988 | D65: =D60+D63-D64 -> 37608 | E65: =E60+E63-E64 -> 41284 | F65: =F60+F63-F64 -> 44280.189 | G65: =G60+G63-G64 -> 48672.031 | H65: =H60+H63-H64 -> 53737.063 | I65: =I60+I63-I64 -> 59319.556 | J65: =J60+J63-J64 -> 64631.579
A66: Exceptional item (Impact of Labour Codes, FY26 only) | C66: 0 | D66: 0 | E66: 1289 | F66: 0 | G66: 0 | H66: 0 | I66: 0 | J66: 0
A67: Profit before tax (PBT) | C67: =C65-C66 -> 35988 | D67: =D65-D66 -> 37608 | E67: =E65-E66 -> 39995 | F67: =F65-F66 -> 44280.189 | G67: =G65-G66 -> 48672.031 | H67: =H65-H66 -> 53737.063 | I67: =I65-I66 -> 59319.556 | J67: =J65-J66 -> 64631.579
A69: Tax expense | C69: 9740 | D69: 10858 | E69: 10521 | F69: =F67*F16 -> 11955.651 | G69: =G67*G16 -> 13141.448 | H69: =H67*H16 -> 14509.007 | I69: =I67*I16 -> 16016.28 | J69: =J67*J16 -> 17450.526
A70: Effective tax rate, % | C70: =C69/C67 -> 0.27064577 | D70: =D69/D67 -> 0.28871517 | E70: =E69/E67 -> 0.26305788 | F70: =F69/F67 -> 0.27 | G70: =G69/G67 -> 0.27 | H70: =H69/H67 -> 0.27 | I70: =I69/I67 -> 0.27 | J70: =J69/J67 -> 0.27
A72: Profit for the year (Consolidated PAT) | C72: =C67-C69 -> 26248 | D72: =D67-D69 -> 26750 | E72: =E67-E69 -> 29474 | F72: =F67-F69 -> 32324.538 | G72: =G67-G69 -> 35530.583 | H72: =H67-H69 -> 39228.056 | I72: =I67-I69 -> 43303.276 | J72: =J67-J69 -> 47181.053
A73: Less: Non-controlling interests | C73: 15 | D73: 37 | E73: 34 | F73: =F72*F17 -> 42.021899 | G73: =G72*G17 -> 46.189758 | H73: =H72*H17 -> 50.996472 | I73: =I72*I17 -> 56.294259 | J73: =J72*J17 -> 61.335368
A74: Profit attributable to owners of the Company | C74: =C72-C73 -> 26233 | D74: =D72-D73 -> 26713 | E74: =E72-E73 -> 29440 | F74: =F72-F73 -> 32282.516 | G74: =G72-G73 -> 35484.393 | H74: =H72-H73 -> 39177.059 | I74: =I72-I73 -> 43246.982 | J74: =J72-J73 -> 47119.717
A76: Basic EPS (₹) | C76: 63.39 | D76: 64.5 | E76: 71.58 | F76: =F74/F78 -> 78.492507 | G76: =G74/G78 -> 86.27763 | H76: =H74/H78 -> 95.25607 | I76: =I74/I78 -> 105.15178 | J76: =J74/J78 -> 114.56804
A77: Diluted EPS (₹) | C77: 63.29 | D77: 64.34 | E77: 71.46 | F77: =F74/F79 -> 78.353568 | G77: =G74/G79 -> 86.12491 | H77: =H74/H79 -> 95.087457 | I77: =I74/I79 -> 104.96565 | J77: =J74/J79 -> 114.36525
A78: Basic weighted-avg shares (crore) | C78: 413.8568 | D78: 414.1612 | E78: 411.2815 | F78: =$E$78 -> 411.2815 | G78: =$E$78 -> 411.2815 | H78: =$E$78 -> 411.2815 | I78: =$E$78 -> 411.2815 | J78: =$E$78 -> 411.2815
A79: Diluted weighted-avg shares (crore) | C79: 414.468 | D79: 415.2051 | E79: 412.0108 | F79: =$E$79 -> 412.0108 | G79: =$E$79 -> 412.0108 | H79: =$E$79 -> 412.0108 | I79: =$E$79 -> 412.0108 | J79: =$E$79 -> 412.0108
A82: SECTION C — WORKING CAPITAL & FIXED ASSET (PPE) SCHEDULE
A83: (₹ Crore, unless stated) | C83: FY2024A | D83: FY2025A | E83: FY2026A | F83: FY2027E | G83: FY2028E | H83: FY2029E | I83: FY2030E | J83: FY2031E
A84: 1. Working Capital Schedule
A85: Trade receivables (= Revenue × DSO / 365) | C85: 30193 | D85: 31158 | E85: 35234 | F85: =F51*F20/365 -> 37531.184 | G85: =G51*G20/365 -> 40721.334 | H85: =H51*H20/365 -> 44386.254 | I85: =I51*I20/365 -> 48381.017 | J85: =J51*J20/365 -> 52493.404
A86: Trade payables (= Revenue × DPO / 365) | C86: 3956 | D86: 4164 | E86: 4744 | F86: =F51*F21/365 -> 5021.7781 | G86: =G51*G21/365 -> 5448.6292 | H86: =H51*H21/365 -> 5939.0058 | I86: =I51*I21/365 -> 6473.5164 | J86: =J51*J21/365 -> 7023.7653
A87: Other current assets, net operating | C87: 31538 | D87: 29004 | E87: 33104 | F87: =F51*F22 -> 36658.98 | G87: =G51*G22 -> 39774.993 | H87: =H51*H22 -> 43354.743 | I87: =I51*I22 -> 47256.67 | J87: =J51*J22 -> 51273.486
A88: Other current liabilities, net operating | C88: 32879 | D88: 36231 | E88: 44418 | F88: =F51*F23 -> 48235.5 | G88: =G51*G23 -> 52335.518 | H88: =H51*H23 -> 57045.714 | I88: =I51*I23 -> 62179.828 | J88: =J51*J23 -> 67465.114
A89: Net operating working capital | C89: =C85+C87-C86-C88 -> 24896 | D89: =D85+D87-D86-D88 -> 19767 | E89: =E85+E87-E86-E88 -> 19176 | F89: =F85+F87-F86-F88 -> 20932.885 | G89: =G85+G87-G86-G88 -> 22712.181 | H89: =H85+H87-H86-H88 -> 24756.277 | I89: =I85+I87-I86-I88 -> 26984.342 | J89: =J85+J87-J86-J88 -> 29278.011
A90: (Increase)/decrease in net working capital — cash flow impact | C90: n/a | D90: =-(D89-C89) -> 5129 | E90: =-(E89-D89) -> 591 | F90: =-(F89-E89) -> -1756.8855 | G90: =-(G89-F89) -> -1779.2953 | H90: =-(H89-G89) -> -2044.0963 | I90: =-(I89-H89) -> -2228.0649 | J90: =-(J89-I89) -> -2293.6691
A92: 2. PPE Roll-forward
A93: Opening PPE (net block) | C93: n/a | D93: =C96 -> 12370 | E93: =D96 -> 11778 | F93: =E96 -> 12651 | G93: =F96 -> 10335.696 | H93: =G96 -> 7823.5912 | I93: =H96 -> 5085.3969 | J93: =I96 -> 2100.7651
A94: (+) Capital expenditure | C94: 2201 | D94: 2237 | E94: 2727 | F94: =F51*F26 -> 2894.13 | G94: =G51*G26 -> 3140.131 | H94: =H51*H26 -> 3422.7428 | I94: =I51*I26 -> 3730.7897 | J94: =J51*J26 -> 4047.9068
A95: (−) Depreciation & amortization | C95: =-C56 -> -4678 | D95: =-D56 -> -4812 | E95: =-E56 -> -4902 | F95: =-F56 -> -5209.434 | G95: =-G56 -> -5652.2359 | H95: =-H56 -> -6160.9371 | I95: =-I56 -> -6715.4215 | J95: =-J56 -> -7286.2323
A96: Closing PPE (net block) | C96: 12370 | D96: 11778 | E96: 12651 | F96: =F93+F94+F95 -> 10335.696 | G96: =G93+G94+G95 -> 7823.5912 | H96: =H93+H94+H95 -> 5085.3969 | I96: =I93+I94+I95 -> 2100.7651 | J96: =J93+J94+J95 -> -1137.5603
A98: 3. Other Fixed/Intangible Assets (held flat — no M&A assumed)
A99: Capital work-in-progress | C99: 293 | D99: 814 | E99: 526 | F99: =$E$99 -> 526 | G99: =$E$99 -> 526 | H99: =$E$99 -> 526 | I99: =$E$99 -> 526 | J99: =$E$99 -> 526
A100: Right-of-use assets | C100: 6552 | D100: 6311 | E100: 6177 | F100: =$E$100 -> 6177 | G100: =$E$100 -> 6177 | H100: =$E$100 -> 6177 | I100: =$E$100 -> 6177 | J100: =$E$100 -> 6177
A101: Goodwill | C101: 7303 | D101: 10106 | E101: 12117 | F101: =$E$101 -> 12117 | G101: =$E$101 -> 12117 | H101: =$E$101 -> 12117 | I101: =$E$101 -> 12117 | J101: =$E$101 -> 12117
A102: Other intangible assets | C102: 1397 | D102: 2766 | E102: 2825 | F102: =$E$102 -> 2825 | G102: =$E$102 -> 2825 | H102: =$E$102 -> 2825 | I102: =$E$102 -> 2825 | J102: =$E$102 -> 2825
A105: SECTION D — CAPITAL STRUCTURE SCHEDULE & WACC SUPPORT
A106: (₹ Crore, unless stated) | C106: FY2024A | D106: FY2025A | E106: FY2026A | F106: FY2027E | G106: FY2028E | H106: FY2029E | I106: FY2030E | J106: FY2031E
A107: 1. Debt-like Obligations (Infosys carries no financial borrowings — only IFRS 16 lease liabilities)
A108: Lease liabilities, non-current | C108: 6400 | D108: 5772 | E108: 6016 | F108: =$E$108 -> 6016 | G108: =$E$108 -> 6016 | H108: =$E$108 -> 6016 | I108: =$E$108 -> 6016 | J108: =$E$108 -> 6016
A109: Lease liabilities, current | C109: 1959 | D109: 2455 | E109: 3160 | F109: =$E$109 -> 3160 | G109: =$E$109 -> 3160 | H109: =$E$109 -> 3160 | I109: =$E$109 -> 3160 | J109: =$E$109 -> 3160
A110: Total debt (lease liabilities) | C110: =C108+C109 -> 8359 | D110: =D108+D109 -> 8227 | E110: =E108+E109 -> 9176 | F110: =F108+F109 -> 9176 | G110: =G108+G109 -> 9176 | H110: =H108+H109 -> 9176 | I110: =I108+I109 -> 9176 | J110: =J108+J109 -> 9176
A112: 2. Cash & Investments (non-operating)
A113: Cash and cash equivalents | C113: 14786 | D113: 24455 | E113: 22201 | F113: =F197 -> 30741.459 | G113: =G197 -> 40095.664 | H113: =H197 -> 50351.007 | I113: =I197 -> 61611.035 | J113: =J197 -> 73876.281
A114: Current investments | C114: 12915 | D114: 12482 | E114: 12950 | F114: =$E$114 -> 12950 | G114: =$E$114 -> 12950 | H114: =$E$114 -> 12950 | I114: =$E$114 -> 12950 | J114: =$E$114 -> 12950
A115: Non-current investments | C115: 11708 | D115: 11059 | E115: 8930 | F115: =$E$115 -> 8930 | G115: =$E$115 -> 8930 | H115: =$E$115 -> 8930 | I115: =$E$115 -> 8930 | J115: =$E$115 -> 8930
A116: Other financial assets, current | C116: 12085 | D116: 13840 | E116: 15890 | F116: =$E$116 -> 15890 | G116: =$E$116 -> 15890 | H116: =$E$116 -> 15890 | I116: =$E$116 -> 15890 | J116: =$E$116 -> 15890
A117: Other financial assets, non-current | C117: 3105 | D117: 3511 | E117: 2776 | F117: =$E$117 -> 2776 | G117: =$E$117 -> 2776 | H117: =$E$117 -> 2776 | I117: =$E$117 -> 2776 | J117: =$E$117 -> 2776
A118: Total cash & investments | C118: =C113+C114+C115+C116+C117 -> 54599 | D118: =D113+D114+D115+D116+D117 -> 65347 | E118: =E113+E114+E115+E116+E117 -> 62747 | F118: =F113+F114+F115+F116+F117 -> 71287.459 | G118: =G113+G114+G115+G116+G117 -> 80641.664 | H118: =H113+H114+H115+H116+H117 -> 90897.007 | I118: =I113+I114+I115+I116+I117 -> 102157.03 | J118: =J113+J114+J115+J116+J117 -> 114422.28
A119: Net cash/(debt) | C119: =C118-C110 -> 46240 | D119: =D118-D110 -> 57120 | E119: =E118-E110 -> 53571 | F119: =F118-F110 -> 62111.459 | G119: =G118-G110 -> 71465.664 | H119: =H118-H110 -> 81721.007 | I119: =I118-I110 -> 92981.035 | J119: =J118-J110 -> 105246.28
A121: 3. Equity Market Value & Capital Weights (column D)
A122: Equity market value | D122: =D46 -> 481712
...

Sheet Assumptions
A1: Infosys Limited — DCF Valuation Model
A2: Assumptions & Drivers | Fiscal Year ends March 31 | Consolidated (IFRS), ₹ Crore unless stated
A4: Valuation date: | C4: March 31, 2026 (FY26 year-end; latest reported balance sheet date)
A5: Source documents: | C5: Infosys Integrated Annual Report 2025-26 (audited consolidated financials, FY26/FY25); Infosys Integrated Annual Report 2024-25 (FY24 comparatives)
A6: (₹ Crore, unless stated) | C6: FY2024A | D6: FY2025A | E6: FY2026A | F6: FY2027E | G6: FY2028E | H6: FY2029E | I6: FY2030E | J6: FY2031E
A7: 1. Revenue & Margin Drivers
A8: Revenue growth, % y/y | C8: n/a | D8: ='Income Statement'!D5/'Income Statement'!C5-1 -> 0.060649444 | E8: ='Income Statement'!E5/'Income Statement'!D5-1 -> 0.096079514 | F8: 0.08 | G8: 0.085 | H8: 0.09 | I8: 0.09 | J8: 0.085 | K8: FY27E-31E: Infosys FY27 guidance is 1.5%-3.0% revenue growth in constant currency, margin 20-22% (Infosys Q1 FY27 press release, Jul 23 2026). Reported (INR) growth assumed higher than CC guidance to reflect historical INR depreciation effect and further AI-led deal ramp-up; converges toward long-run IT services growth.
A9: Employee benefit expense, % of revenue | C9: 0.5376456 | D9: 0.52733297 | E9: 0.53229219 | F9: 0.532 | G9: 0.532 | H9: 0.532 | I9: 0.532 | J9: 0.532 | K9: FY24-26: Employee benefit expense / Revenue from operations, per Consolidated P&L (AR 2025-26, p.317; AR 2024-25, p.303). Forecast held near FY26 actual (53.2%).
A10: Depreciation & amortization, % of revenue | C10: 0.030441856 | D10: 0.029523284 | E10: 0.027439127 | F10: 0.027 | G10: 0.027 | H10: 0.027 | I10: 0.027 | J10: 0.027 | K10: FY24-26: Depreciation & amortization expense / Revenue, per Consolidated P&L. Forecast assumes gradual scale efficiency (2.7%).
A11: EBIT margin (Operating margin), % of revenue | C11: 0.20659205 | D11: 0.21120314 | E11: 0.20922474 | F11: 0.21 | G11: 0.213 | H11: 0.216 | I11: 0.219 | J11: 0.22 | K11: FY24-26: (Revenue - Total expenses excl. finance cost) / Revenue, computed from Consolidated P&L. Forecast aligned to management FY27 operating margin guidance of 20%-22% (Infosys Q1 FY27 press release), trending to top of range by FY31E.
A12: Other income (net), % of revenue | C12: 0.030656602 | D12: 0.022087245 | E12: 0.024192555 | F12: 0.022 | G12: 0.022 | H12: 0.022 | I12: 0.022 | J12: 0.022 | K12: FY24-26: Other income, net / Revenue, per Consolidated P&L. Forecast held near recent-year average.
A13: Finance cost, % of revenue | C13: 0.003058502 | D13: 0.0025523038 | E13: 0.0023285754 | F13: 0.0025 | G13: 0.0025 | H13: 0.0025 | I13: 0.0025 | J13: 0.0025 | K13: FY24-26: Finance cost / Revenue, per Consolidated P&L (lease interest under Ind AS 116 / IFRS 16). Forecast held broadly flat.
A14: Effective tax rate, % | C14: 0.27064577 | D14: 0.28871517 | E14: 0.26305788 | F14: 0.27 | G14: 0.27 | H14: 0.27 | I14: 0.27 | J14: 0.27 | K14: FY24-26: Tax expense / Profit before tax, per Consolidated P&L. Forecast at 3-yr historical average (~27%).
A15: Non-controlling interest, % of consolidated PAT | C15: 0.00057147211 | D15: 0.0013831776 | E15: 0.0011535591 | F15: 0.0013 | G15: 0.0013 | H15: 0.0013 | I15: 0.0013 | J15: 0.0013 | K15: FY24-26: Non-controlling interests / Profit for the year, per Consolidated P&L. Immaterial; held flat.
A17: 2. Working Capital Assumptions
A18: Days Sales Outstanding — Trade receivables (days) | C18: 71.715006 | D18: 69.775262 | E18: 71.986622 | F18: 71 | G18: 71 | H18: 71 | I18: 71 | J18: 71 | K18: FY24-26: Trade receivables / Revenue x 365, per Consolidated Balance Sheet & P&L. Forecast held at 3-yr average (~71 days).
A19: Days Payable Outstanding — Trade payables (days) | C19: 9.3963688 | D19: 9.3248666 | E19: 9.6924713 | F19: 9.5 | G19: 9.5 | H19: 9.5 | I19: 9.5 | J19: 9.5 | K19: FY24-26: Trade payables / Revenue x 365. Forecast held at 3-yr average (~9.5 days).
A20: Other current assets (net operating), % of revenue | C20: 0.20523199 | D20: 0.17794957 | E20: 0.18530087 | F20: 0.19 | G20: 0.19 | H20: 0.19 | I20: 0.19 | J20: 0.19 | K20: FY24-26: (Loans + Other financial assets + Other assets + Income tax assets, current) / Revenue, per Consolidated Balance Sheet. Forecast held near FY26 level.
A21: Other current liabilities (net operating), % of revenue | C21: 0.21395848 | D21: 0.22228971 | E21: 0.2486314 | F21: 0.25 | G21: 0.25 | H21: 0.25 | I21: 0.25 | J21: 0.25 | K21: FY24-26: (Other financial liabilities + Other liabilities + Provisions + Income tax liabilities, current) / Revenue. Forecast held near FY26 level.
A23: 3. Capex & Fixed Asset Assumptions
A24: Capital expenditure, % of revenue | C24: 0.0143229 | D24: 0.013724768 | E24: 0.015264484 | F24: 0.015 | G24: 0.015 | H24: 0.015 | I24: 0.015 | J24: 0.015 | K24: FY24-26: Expenditure on PPE & intangibles (net) / Revenue, per Consolidated Statement of Cash Flows. Forecast held near 3-yr average (~1.5%).
A26: 4. Capital Allocation / Payout Policy
A27: Dividend + buyback payout, % of Free Cash Flow (CFO less capex) | C27: Per policy | D27: Per policy | E27: Per policy | F27: 0.85 | G27: 0.85 | H27: 0.85 | I27: 0.85 | J27: 0.85 | K27: Per Infosys' stated Capital Allocation Policy: return ~85% of free cash flow (FY25-FY29) cumulatively via dividends and/or buybacks (AR 2025-26, p.7 & p.~15). Applied annually here for modeling simplicity.
A29: 5. Discount Rate (WACC) Build-up
A30: Risk-free rate (India 10-yr G-Sec yield) | D30: 0.068 | K30: India 10-year G-Sec benchmark yield, ~6.8% (Aug 2026; Trading Economics / RBI market data).
A31: Levered Beta (Infosys, vs. NIFTY/broad market) | D31: 0.85 | K31: Estimated levered beta for Infosys (large-cap, low-leverage IT services exporter) vs. broad Indian equity market; typical published beta range 0.7-0.9.
A32: India equity risk premium | D32: 0.075 | K32: India long-run equity risk premium, ~7.0-8.0% (Damodaran India country risk premium framework, applied over risk-free rate).
A33: Cost of equity = Rf + Beta × ERP | D33: =D30+D31*D32 -> 0.13175
A34: Pre-tax cost of debt (lease discount rate proxy) | D34: 0.075 | K34: Proxy for Infosys' marginal borrowing/lease discount rate; company carries no financial debt (debt-free), so this reflects the discount rate used for lease liabilities under Ind AS 116.
A35: Marginal tax rate (for after-tax cost of debt) | D35: 0.27 | K35: Same as effective tax rate assumption above, for consistency.
A36: After-tax cost of debt | D36: =D34*(1-D35) -> 0.05475
A37: Weight of debt, % (Total lease liabilities / (Debt+Equity mkt value)) | D37: ='Capital Structure'!D23 -> 0.018692655 | K37: Total lease liabilities (current+non-current) / (Lease liabilities + Equity market value) — see Capital Structure Schedule. Infosys carries no financial borrowings; only IFRS 16 lease liabilities.
A38: Weight of equity, % | D38: =1-D37 -> 0.98130735
A39: WACC (Weighted Average Cost of Capital) | D39: =D33*D38+D36*D37 -> 0.13031067
A41: 6. Terminal Value Assumptions
A42: Terminal (perpetuity) growth rate | D42: 0.05 | K42: Long-run nominal terminal growth assumption for a mature global IT services franchise — approximates long-run nominal GDP/IT services spend growth. Held below WACC to ensure convergence.
A43: Check: WACC − Terminal growth rate (must be > 0) | D43: =D39-D42 -> 0.080310666
A45: 7. Share & Market Data
A46: Current share price (NSE, Aug 10, 2026) | D46: 1190 | K46: Infosys Ltd (NSE: INFY) closing share price, Aug 10, 2026 (Bajaj Broking / Kotak Neo market data).
A47: Diluted weighted-average shares outstanding (crore) | D47: 404.8 | K47: Diluted weighted-average shares outstanding, FY26, per Consolidated P&L EPS note (AR 2025-26, p.318). Closing shares post FY26 buyback ≈ 404.8 crore (Equity share capital ₹2,024 cr ÷ ₹5 face value).
A48: Implied current market capitalization | D48: =D46*D47 -> 481712

Sheet Income Statement
A1: Infosys Limited — DCF Valuation Model
A2: Consolidated Income Statement (IFRS) | ₹ Crore, except per-share data | Fiscal Year ends March 31
A4: (₹ Crore, unless stated) | C4: FY2024A | D4: FY2025A | E4: FY2026A | F4: FY2027E | G4: FY2028E | H4: FY2029E | I4: FY2030E | J4: FY2031E
A5: Revenue from operations | C5: 153670 | D5: 162990 | E5: 178650 | F5: =E5*(1+Assumptions!F8) -> 192942 | G5: =F5*(1+Assumptions!G8) -> 209342.07 | H5: =G5*(1+Assumptions!H8) -> 228182.86 | I5: =H5*(1+Assumptions!I8) -> 248719.31 | J5: =I5*(1+Assumptions!J8) -> 269860.46
A6: % growth y/y | C6: n/a | D6: =D5/C5-1 -> 0.060649444 | E6: =E5/D5-1 -> 0.096079514 | F6: =Assumptions!F8 -> 0.08 | G6: =Assumptions!G8 -> 0.085 | H6: =Assumptions!H8 -> 0.09 | I6: =Assumptions!I8 -> 0.09 | J6: =Assumptions!J8 -> 0.085
A8: Operating Expenses
A9: Employee benefit expenses | C9: 82620 | D9: 85950 | E9: 95094 | F9: =F5*Assumptions!F9 -> 102645.14 | G9: =G5*Assumptions!G9 -> 111369.98 | H9: =H5*Assumptions!H9 -> 121393.28 | I9: =I5*Assumptions!I9 -> 132318.67 | J9: =J5*Assumptions!J9 -> 143565.76
A10: Depreciation & amortization expenses | C10: 4678 | D10: 4812 | E10: 4902 | F10: =F5*Assumptions!F10 -> 5209.434 | G10: =G5*Assumptions!G10 -> 5652.2359 | H10: =H5*Assumptions!H10 -> 6160.9371 | I10: =I5*Assumptions!I10 -> 6715.4215 | J10: =J5*Assumptions!J10 -> 7286.2323
A11: Other operating expenses (sub-contractors, travel, S&M, G&A) | C11: 34625 | D11: 37804 | E11: 41276 | F11: =F5*(1-Assumptions!F11)-F9-F10 -> 44569.602 | G11: =G5*(1-Assumptions!G11)-G9-G10 -> 47729.992 | H11: =H5*(1-Assumptions!H11)-H9-H10 -> 51341.143 | I11: =I5*(1-Assumptions!I11)-I9-I10 -> 55215.688 | J11: =J5*(1-Assumptions!J11)-J9-J10 -> 59639.161
A12: Total operating expenses | C12: =C9+C10+C11 -> 121923 | D12: =D9+D10+D11 -> 128566 | E12: =E9+E10+E11 -> 141272 | F12: =F9+F10+F11 -> 152424.18 | G12: =G9+G10+G11 -> 164752.21 | H12: =H9+H10+H11 -> 178895.36 | I12: =I9+I10+I11 -> 194249.78 | J12: =J9+J10+J11 -> 210491.15
A14: EBIT (Operating Profit) | C14: =C5-C12 -> 31747 | D14: =D5-D12 -> 34424 | E14: =E5-E12 -> 37378 | F14: =F5-F12 -> 40517.82 | G14: =G5-G12 -> 44589.861 | H14: =H5-H12 -> 49287.497 | I14: =I5-I12 -> 54469.53 | J14: =J5-J12 -> 59369.3
A15: EBIT margin, % | C15: =C14/C5 -> 0.20659205 | D15: =D14/D5 -> 0.21120314 | E15: =E14/E5 -> 0.20922474 | F15: =F14/F5 -> 0.21 | G15: =G14/G5 -> 0.213 | H15: =H14/H5 -> 0.216 | I15: =I14/I5 -> 0.219 | J15: =J14/J5 -> 0.22
A17: Other income, net | C17: 4711 | D17: 3600 | E17: 4322 | F17: =F5*Assumptions!F12 -> 4244.724 | G17: =G5*Assumptions!G12 -> 4605.5255 | H17: =H5*Assumptions!H12 -> 5020.0228 | I17: =I5*Assumptions!I12 -> 5471.8249 | J17: =J5*Assumptions!J12 -> 5936.93
A18: Finance cost | C18: 470 | D18: 416 | E18: 416 | F18: =F5*Assumptions!F13 -> 482.355 | G18: =G5*Assumptions!G13 -> 523.35518 | H18: =H5*Assumptions!H13 -> 570.45714 | I18: =I5*Assumptions!I13 -> 621.79828 | J18: =J5*Assumptions!J13 -> 674.65114
A19: Profit before exceptional item and tax | C19: =C14+C17-C18 -> 35988 | D19: =D14+D17-D18 -> 37608 | E19: =E14+E17-E18 -> 41284 | F19: =F14+F17-F18 -> 44280.189 | G19: =G14+G17-G18 -> 48672.031 | H19: =H14+H17-H18 -> 53737.063 | I19: =I14+I17-I18 -> 59319.556 | J19: =J14+J17-J18 -> 64631.579
A20: Exceptional item (Impact of Labour Codes, FY26 only) | C20: 0 | D20: 0 | E20: 1289 | F20: 0 | G20: 0 | H20: 0 | I20: 0 | J20: 0
A21: Profit before tax (PBT) | C21: =C19-C20 -> 35988 | D21: =D19-D20 -> 37608 | E21: =E19-E20 -> 39995 | F21: =F19-F20 -> 44280.189 | G21: =G19-G20 -> 48672.031 | H21: =H19-H20 -> 53737.063 | I21: =I19-I20 -> 59319.556 | J21: =J19-J20 -> 64631.579
A23: Tax expense | C23: 9740 | D23: 10858 | E23: 10521 | F23: =F21*Assumptions!F14 -> 11955.651 | G23: =G21*Assumptions!G14 -> 13141.448 | H23: =H21*Assumptions!H14 -> 14509.007 | I23: =I21*Assumptions!I14 -> 16016.28 | J23: =J21*Assumptions!J14 -> 17450.526
A24: Effective tax rate, % | C24: =C23/C21 -> 0.27064577 | D24: =D23/D21 -> 0.28871517 | E24: =E23/E21 -> 0.26305788 | F24: =F23/F21 -> 0.27 | G24: =G23/G21 -> 0.27 | H24: =H23/H21 -> 0.27 | I24: =I23/I21 -> 0.27 | J24: =J23/J21 -> 0.27
A26: Profit for the year (Consolidated PAT) | C26: =C21-C23 -> 26248 | D26: =D21-D23 -> 26750 | E26: =E21-E23 -> 29474 | F26: =F21-F23 -> 32324.538 | G26: =G21-G23 -> 35530.583 | H26: =H21-H23 -> 39228.056 | I26: =I21-I23 -> 43303.276 | J26: =J21-J23 -> 47181.053
A27: Less: Non-controlling interests | C27: 15 | D27: 37 | E27: 34 | F27: =F26*Assumptions!F15 -> 42.021899 | G27: =G26*Assumptions!G15 -> 46.189758 | H27: =H26*Assumptions!H15 -> 50.996472 | I27: =I26*Assumptions!I15 -> 56.294259 | J27: =J26*Assumptions!J15 -> 61.335368
A28: Profit attributable to owners of the Company | C28: =C26-C27 -> 26233 | D28: =D26-D27 -> 26713 | E28: =E26-E27 -> 29440 | F28: =F26-F27 -> 32282.516 | G28: =G26-G27 -> 35484.393 | H28: =H26-H27 -> 39177.059 | I28: =I26-I27 -> 43246.982 | J28: =J26-J27 -> 47119.717
A30: Basic EPS (₹) | C30: 63.39 | D30: 64.5 | E30: 71.58 | F30: =F28/F32 -> 78.492507 | G30: =G28/G32 -> 86.27763 | H30: =H28/H32 -> 95.25607 | I30: =I28/I32 -> 105.15178 | J30: =J28/J32 -> 114.56804
A31: Diluted EPS (₹) | C31: 63.29 | D31: 64.34 | E31: 71.46 | F31: =F28/F33 -> 78.353568 | G31: =G28/G33 -> 86.12491 | H31: =H28/H33 -> 95.087457 | I31: =I28/I33 -> 104.96565 | J31: =J28/J33 -> 114.36525
A32: Basic weighted-avg shares (crore) | C32: 413.8568 | D32: 414.1612 | E32: 411.2815 | F32: =$E$32 -> 411.2815 | G32: =$E$32 -> 411.2815 | H32: =$E$32 -> 411.2815 | I32: =$E$32 -> 411.2815 | J32: =$E$32 -> 411.2815
A33: Diluted weighted-avg shares (crore) | C33: 414.468 | D33: 415.2051 | E33: 412.0108 | F33: =$E$33 -> 412.0108 | G33: =$E$33 -> 412.0108 | H33: =$E$33 -> 412.0108 | I33: =$E$33 -> 412.0108 | J33: =$E$33 -> 412.0108
A35: Note: Historical (FY24A-FY26A) figures are as reported in the Consolidated Statement of Profit and Loss, Infosys Integrated Annual Reports 2025-26 (p.318-319) and 2024-25 (p.304-305). "Other operating expenses" aggregates cost of technical sub-contractors, travel, cost of software packages, communication, consultancy & professional charges, and other expenses. Forecast years (FY27E-FY31E) are driven by the Assumptions & Drivers tab.

Sheet Balance Sheet
A1: Infosys Limited — DCF Valuation Model
A2: Consolidated Balance Sheet (IFRS) | ₹ Crore | As at March 31
A4: (₹ Crore, unless stated) | C4: FY2024A | D4: FY2025A | E4: FY2026A | F4: FY2027E | G4: FY2028E | H4: FY2029E | I4: FY2030E | J4: FY2031E
A5: ASSETS
A6: Non-current assets
A7: Property, plant and equipment | C7: 12370 | D7: 11778 | E7: 12651 | F7: ='WC & PPE Schedule'!F17 -> 10335.696 | G7: ='WC & PPE Schedule'!G17 -> 7823.5912 | H7: ='WC & PPE Schedule'!H17 -> 5085.3969 | I7: ='WC & PPE Schedule'!I17 -> 2100.7651 | J7: ='WC & PPE Schedule'!J17 -> -1137.5603
A8: Capital work-in-progress | C8: 293 | D8: 814 | E8: 526 | F8: ='WC & PPE Schedule'!F20 -> 526 | G8: ='WC & PPE Schedule'!G20 -> 526 | H8: ='WC & PPE Schedule'!H20 -> 526 | I8: ='WC & PPE Schedule'!I20 -> 526 | J8: ='WC & PPE Schedule'!J20 -> 526
A9: Right-of-use assets | C9: 6552 | D9: 6311 | E9: 6177 | F9: ='WC & PPE Schedule'!F21 -> 6177 | G9: ='WC & PPE Schedule'!G21 -> 6177 | H9: ='WC & PPE Schedule'!H21 -> 6177 | I9: ='WC & PPE Schedule'!I21 -> 6177 | J9: ='WC & PPE Schedule'!J21 -> 6177
A10: Goodwill | C10: 7303 | D10: 10106 | E10: 12117 | F10: ='WC & PPE Schedule'!F22 -> 12117 | G10: ='WC & PPE Schedule'!G22 -> 12117 | H10: ='WC & PPE Schedule'!H22 -> 12117 | I10: ='WC & PPE Schedule'!I22 -> 12117 | J10: ='WC & PPE Schedule'!J22 -> 12117
A11: Other intangible assets | C11: 1397 | D11: 2766 | E11: 2825 | F11: ='WC & PPE Schedule'!F23 -> 2825 | G11: ='WC & PPE Schedule'!G23 -> 2825 | H11: ='WC & PPE Schedule'!H23 -> 2825 | I11: ='WC & PPE Schedule'!I23 -> 2825 | J11: ='WC & PPE Schedule'!J23 -> 2825
A12: Non-current investments | C12: 11708 | D12: 11059 | E12: 8930 | F12: =$E$12 -> 8930 | G12: =$E$12 -> 8930 | H12: =$E$12 -> 8930 | I12: =$E$12 -> 8930 | J12: =$E$12 -> 8930
A13: Other non-current assets (loans, other fin. assets, DTA, tax assets, other) | C13: 8759 | D13: 8970 | E13: 9252 | F13: =$E$13 -> 9252 | G13: =$E$13 -> 9252 | H13: =$E$13 -> 9252 | I13: =$E$13 -> 9252 | J13: =$E$13 -> 9252
A14: Total non-current assets | C14: =C7+C8+C9+C10+C11+C12+C13 -> 48382 | D14: =D7+D8+D9+D10+D11+D12+D13 -> 51804 | E14: =E7+E8+E9+E10+E11+E12+E13 -> 52478 | F14: =F7+F8+F9+F10+F11+F12+F13 -> 50162.696 | G14: =G7+G8+G9+G10+G11+G12+G13 -> 47650.591 | H14: =H7+H8+H9+H10+H11+H12+H13 -> 44912.397 | I14: =I7+I8+I9+I10+I11+I12+I13 -> 41927.765 | J14: =J7+J8+J9+J10+J11+J12+J13 -> 38689.44
A16: Current assets
A17: Current investments | C17: 12915 | D17: 12482 | E17: 12950 | F17: =$E$17 -> 12950 | G17: =$E$17 -> 12950 | H17: =$E$17 -> 12950 | I17: =$E$17 -> 12950 | J17: =$E$17 -> 12950
A18: Trade receivables | C18: 30193 | D18: 31158 | E18: 35234 | F18: ='WC & PPE Schedule'!F6 -> 37531.184 | G18: ='WC & PPE Schedule'!G6 -> 40721.334 | H18: ='WC & PPE Schedule'!H6 -> 44386.254 | I18: ='WC & PPE Schedule'!I6 -> 48381.017 | J18: ='WC & PPE Schedule'!J6 -> 52493.404
A19: Cash and cash equivalents | C19: 14786 | D19: 24455 | E19: 22201 | F19: ='Cash Flow'!F28 -> 30741.459 | G19: ='Cash Flow'!G28 -> 40095.664 | H19: ='Cash Flow'!H28 -> 50351.007 | I19: ='Cash Flow'!I28 -> 61611.035 | J19: ='Cash Flow'!J28 -> 73876.281
A20: Other current assets (loans, other fin. assets, tax assets, other) | C20: 31538 | D20: 29004 | E20: 33104 | F20: ='WC & PPE Schedule'!F8 -> 36658.98 | G20: ='WC & PPE Schedule'!G8 -> 39774.993 | H20: ='WC & PPE Schedule'!H8 -> 43354.743 | I20: ='WC & PPE Schedule'!I8 -> 47256.67 | J20: ='WC & PPE Schedule'!J8 -> 51273.486
A21: Total current assets | C21: =C17+C18+C19+C20 -> 89432 | D21: =D17+D18+D19+D20 -> 97099 | E21: =E17+E18+E19+E20 -> 103489 | F21: =F17+F18+F19+F20 -> 117881.62 | G21: =G17+G18+G19+G20 -> 133541.99 | H21: =H17+H18+H19+H20 -> 151042 | I21: =I17+I18+I19+I20 -> 170198.72 | J21: =J17+J18+J19+J20 -> 190593.17
A22: TOTAL ASSETS | C22: =C14+C21 -> 137814 | D22: =D14+D21 -> 148903 | E22: =E14+E21 -> 155967 | F22: =F14+F21 -> 168044.32 | G22: =G14+G21 -> 181192.58 | H22: =H14+H21 -> 195954.4 | I22: =I14+I21 -> 212126.49 | J22: =J14+J21 -> 229282.61
A24: EQUITY AND LIABILITIES
A25: Equity
A26: Equity share capital | C26: 2071 | D26: 2073 | E26: 2024 | F26: =$E$26 -> 2024 | G26: =$E$26 -> 2024 | H26: =$E$26 -> 2024 | I26: =$E$26 -> 2024 | J26: =$E$26 -> 2024
A27: Other equity (reserves & surplus) | C27: 86045 | D27: 93745 | E27: 90828 | F27: =E27+'Income Statement'!F28-'Cash Flow'!F32 -> 98768.018 | G27: =F27+'Income Statement'!G28-'Cash Flow'!G32 -> 107343.22 | H27: =G27+'Income Statement'!H28-'Cash Flow'!H32 -> 116853.47 | I27: =H27+'Income Statement'!I28-'Cash Flow'!I32 -> 127300.64 | J27: =I27+'Income Statement'!J28-'Cash Flow'!J32 -> 138559.89
A28: Total equity attributable to owners | C28: =C26+C27 -> 88116 | D28: =D26+D27 -> 95818 | E28: =E26+E27 -> 92852 | F28: =F26+F27 -> 100792.02 | G28: =G26+G27 -> 109367.22 | H28: =H26+H27 -> 118877.47 | I28: =I26+I27 -> 129324.64 | J28: =J26+J27 -> 140583.89
A29: Non-controlling interests | C29: 345 | D29: 385 | E29: 445 | F29: =E29+'Income Statement'!F27 -> 487.0219 | G29: =F29+'Income Statement'!G27 -> 533.21166 | H29: =G29+'Income Statement'!H27 -> 584.20813 | I29: =H29+'Income Statement'!I27 -> 640.50239 | J29: =I29+'Income Statement'!J27 -> 701.83776
A30: Total equity | C30: =C28+C29 -> 88461 | D30: =D28+D29 -> 96203 | E30: =E28+E29 -> 93297 | F30: =F28+F29 -> 101279.04 | G30: =G28+G29 -> 109900.44 | H30: =H28+H29 -> 119461.68 | I30: =I28+I29 -> 129965.14 | J30: =J28+J29 -> 141285.73
A32: Non-current liabilities
A33: Lease liabilities | C33: 6400 | D33: 5772 | E33: 6016 | F33: =$E$33 -> 6016 | G33: =$E$33 -> 6016 | H33: =$E$33 -> 6016 | I33: =$E$33 -> 6016 | J33: =$E$33 -> 6016
A34: Other non-current liabilities (other fin. liab., DTL, other) | C34: 4159 | D34: 4078 | E34: 4332 | F34: =$E$34 -> 4332 | G34: =$E$34 -> 4332 | H34: =$E$34 -> 4332 | I34: =$E$34 -> 4332 | J34: =$E$34 -> 4332
A35: Total non-current liabilities | C35: =C33+C34 -> 10559 | D35: =D33+D34 -> 9850 | E35: =E33+E34 -> 10348 | F35: =F33+F34 -> 10348 | G35: =G33+G34 -> 10348 | H35: =H33+H34 -> 10348 | I35: =I33+I34 -> 10348 | J35: =J33+J34 -> 10348
A37: Current liabilities
A38: Lease liabilities | C38: 1959 | D38: 2455 | E38: 3160 | F38: =$E$38 -> 3160 | G38: =$E$38 -> 3160 | H38: =$E$38 -> 3160 | I38: =$E$38 -> 3160 | J38: =$E$38 -> 3160
A39: Trade payables | C39: 3956 | D39: 4164 | E39: 4744 | F39: ='WC & PPE Schedule'!F7 -> 5021.7781 | G39: ='WC & PPE Schedule'!G7 -> 5448.6292 | H39: ='WC & PPE Schedule'!H7 -> 5939.0058 | I39: ='WC & PPE Schedule'!I7 -> 6473.5164 | J39: ='WC & PPE Schedule'!J7 -> 7023.7653
A40: Other current liabilities (other fin. liab., other, provisions, tax liab.) | C40: 32879 | D40: 36231 | E40: 44418 | F40: ='WC & PPE Schedule'!F9 -> 48235.5 | G40: ='WC & PPE Schedule'!G9 -> 52335.518 | H40: ='WC & PPE Schedule'!H9 -> 57045.714 | I40: ='WC & PPE Schedule'!I9 -> 62179.828 | J40: ='WC & PPE Schedule'!J9 -> 67465.114
A41: Total current liabilities | C41: =C38+C39+C40 -> 38794 | D41: =D38+D39+D40 -> 42850 | E41: =E38+E39+E40 -> 52322 | F41: =F38+F39+F40 -> 56417.278 | G41: =G38+G39+G40 -> 60944.147 | H41: =H38+H39+H40 -> 66144.72 | I41: =I38+I39+I40 -> 71813.345 | J41: =J38+J39+J40 -> 77648.879
A42: Total liabilities | C42: =C35+C41 -> 49353 | D42: =D35+D41 -> 52700 | E42: =E35+E41 -> 62670 | F42: =F35+F41 -> 66765.278 | G42: =G35+G41 -> 71292.147 | H42: =H35+H41 -> 76492.72 | I42: =I35+I41 -> 82161.345 | J42: =J35+J41 -> 87996.879
A43: TOTAL EQUITY AND LIABILITIES | C43: =C30+C42 -> 137814 | D43: =D30+D42 -> 148903 | E43: =E30+E42 -> 155967 | F43: =F30+F42 -> 168044.32 | G43: =G30+G42 -> 181192.58 | H43: =H30+H42 -> 195954.4 | I43: =I30+I42 -> 212126.49 | J43: =J30+J42 -> 229282.61
A45: Balance check (Total assets − Total equity & liabilities) | C45: =C22-C43 -> 0 | D45: =D22-D43 -> 0 | E45: =E22-E43 -> 0 | F45: =F22-F43 -> 0 | G45: =G22-G43 -> 0 | H45: =H22-H43 -> 0 | I45: =I22-I43 -> 0 | J45: =J22-J43 -> 0
A47: Note: Forecast (FY27E-FY31E) balance sheet is fully linked — PPE and working-capital lines flow from the WC & PPE Schedule tab; cash flows from the Cash Flow Statement tab; equity rolls forward with net income less the 85% FCF payout policy. Non-current investments, other non-current/current "other" assets & liabilities, lease liabilities and share capital are held flat at FY26A levels (no new debt, M&A or share issuance assumed). Historical (FY24A-FY26A) figures per Consolidated Balance Sheet, Infosys Integrated Annual Reports 2025-26 (p.316-317) and 2024-25 (p.302-303).

Sheet Cash Flow
A1: Infosys Limited - DCF Valuation Model
A2: Consolidated Statement of Cash Flows (IFRS) | ₹ Crore | Fiscal Year ends March 31
A4: (₹ Crore, unless stated) | C4: FY2024A | D4: FY2025A | E4: FY2026A | F4: FY2027E | G4: FY2028E | H4: FY2029E | I4: FY2030E | J4: FY2031E
A5: Cash Flow from Operating Activities
A6: Profit for the year (consolidated, incl. NCI) | C6: 26248 | D6: 26750 | E6: 29474 | F6: ='Income Statement'!F26 -> 32324.538 | G6: ='Income Statement'!G26 -> 35530.583 | H6: ='Income Statement'!H26 -> 39228.056 | I6: ='Income Statement'!I26 -> 43303.276 | J6: ='Income Statement'!J26 -> 47181.053
A7: (+) Depreciation & amortization | C7: 4678 | D7: 4812 | E7: 4902 | F7: ='Income Statement'!F10 -> 5209.434 | G7: ='Income Statement'!G10 -> 5652.2359 | H7: ='Income Statement'!H10 -> 6160.9371 | I7: ='Income Statement'!I10 -> 6715.4215 | J7: ='Income Statement'!J10 -> 7286.2323
A8: (+) Finance cost (non-cash add-back; lease interest) | C8: see Other adj. | D8: see Other adj. | E8: see Other adj. | F8: 0 | G8: 0 | H8: 0 | I8: 0 | J8: 0
A9: (−) Other income, net (investing-related, excluded from CFO) | C9: see Other adj. | D9: see Other adj. | E9: see Other adj. | F9: =-'Income Statement'!F17 -> -4244.724 | G9: =-'Income Statement'!G17 -> -4605.5255 | H9: =-'Income Statement'!H17 -> -5020.0228 | I9: =-'Income Statement'!I17 -> -5471.8249 | J9: =-'Income Statement'!J17 -> -5936.93
A10: (+/−) Change in net working capital | C10: see Other adj. | D10: see Other adj. | E10: see Other adj. | F10: ='WC & PPE Schedule'!F11 -> -1756.8855 | G10: ='WC & PPE Schedule'!G11 -> -1779.2953 | H10: ='WC & PPE Schedule'!H11 -> -2044.0963 | I10: ='WC & PPE Schedule'!I11 -> -2228.0649 | J10: ='WC & PPE Schedule'!J11 -> -2293.6691
A11: Other non-cash adjustments & tax paid (net) | C11: =C12-C6-C7 -> -5716 | D11: =D12-D6-D7 -> 4132 | E11: =E12-E6-E7 -> -390 | F11: 0 | G11: 0 | H11: 0 | I11: 0 | J11: 0
A12: Net cash from operating activities (CFO) | C12: 25210 | D12: 35694 | E12: 33986 | F12: =F6+F7+F9+F10+F11 -> 31532.362 | G12: =G6+G7+G9+G10+G11 -> 34797.998 | H12: =H6+H7+H9+H10+H11 -> 38324.874 | I12: =I6+I7+I9+I10+I11 -> 42318.808 | J12: =J6+J7+J9+J10+J11 -> 46236.686
A14: Cash Flow from Investing Activities
A15: (−) Purchase of property, plant, equipment & intangibles (capex) | C15: 2201 | D15: 2237 | E15: 2727 | F15: ='WC & PPE Schedule'!F15 -> 2894.13 | G15: ='WC & PPE Schedule'!G15 -> 3140.131 | H15: ='WC & PPE Schedule'!H15 -> 3422.7428 | I15: ='WC & PPE Schedule'!I15 -> 3730.7897 | J15: ='WC & PPE Schedule'!J15 -> 4047.9068
A16: Other investing activities, net (investment purchases/sales, interest received, M&A) | C16: =C17+C15 -> -2808 | D16: =D17+D15 -> 291 | E16: =E17+E15 -> 4673 | F16: ='Income Statement'!F17 -> 4244.724 | G16: ='Income Statement'!G17 -> 4605.5255 | H16: ='Income Statement'!H17 -> 5020.0228 | I16: ='Income Statement'!I17 -> 5471.8249 | J16: ='Income Statement'!J17 -> 5936.93
A17: Net cash from / (used in) investing activities (CFI) | C17: -5009 | D17: -1946 | E17: 1946 | F17: =-F15+F16 -> 1350.594 | G17: =-G15+G16 -> 1465.3945 | H17: =-H15+H16 -> 1597.28 | I17: =-I15+I16 -> 1741.0352 | J17: =-J15+J16 -> 1889.0232
A19: Cash Flow from Financing Activities
A20: (−) Dividends paid | C20: 14692 | D20: 20287 | E20: 18653 | F20: =F32*0.6 -> 14605.499 | G20: =G32*0.6 -> 16145.512 | H20: =H32*0.6 -> 17800.087 | I20: =I32*0.6 -> 19679.889 | J20: =J32*0.6 -> 21516.277
A21: (−) Buyback of shares | C21: 0 | D21: 0 | E21: 18058 | F21: =F32*0.4 -> 9736.999 | G21: =G32*0.4 -> 10763.675 | H21: =H32*0.4 -> 11866.725 | I21: =I32*0.4 -> 13119.926 | J21: =J32*0.4 -> 14344.185
A22: (−) Payment of lease liabilities & other financing, net | C22: =C23+C20+C21 -> -2812 | D22: =D23+D20+D21 -> -3874 | E22: =E23+E20+E21 -> -3075 | F22: 0 | G22: 0 | H22: 0 | I22: 0 | J22: 0
A23: Net cash used in financing activities (CFF) | C23: -17504 | D23: -24161 | E23: -39786 | F23: =-F20-F21-F22 -> -24342.498 | G23: =-G20-G21-G22 -> -26909.187 | H23: =-H20-H21-H22 -> -29666.811 | I23: =-I20-I21-I22 -> -32799.815 | J23: =-J20-J21-J22 -> -35860.462
A25: Net increase / (decrease) in cash and cash equivalents | C25: =C12+C17+C23 -> 2697 | D25: =D12+D17+D23 -> 9587 | E25: =E12+E17+E23 -> -3854 | F25: =F12+F17+F23 -> 8540.4589 | G25: =G12+G17+G23 -> 9354.2056 | H25: =H12+H17+H23 -> 10255.342 | I25: =I12+I17+I23 -> 11260.028 | J25: =J12+J17+J23 -> 12265.247
A26: Effect of exchange rate changes on cash | C26: n/a | D26: 82 | E26: 1600 | F26: 0 | G26: 0 | H26: 0 | I26: 0 | J26: 0
A27: Cash and cash equivalents, beginning of year | C27: n/a | D27: =C28 -> 14786 | E27: =D28 -> 24455 | F27: =E28 -> 22201 | G27: =F28 -> 30741.459 | H27: =G28 -> 40095.664 | I27: =H28 -> 50351.007 | J27: =I28 -> 61611.035
A28: Cash and cash equivalents, end of year | C28: 14786 | D28: 24455 | E28: 22201 | F28: =F27+F12+F17+F23+F26 -> 30741.459 | G28: =G27+G12+G17+G23+G26 -> 40095.664 | H28: =H27+H12+H17+H23+H26 -> 50351.007 | I28: =I27+I12+I17+I23+I26 -> 61611.035 | J28: =J27+J12+J17+J23+J26 -> 73876.281
A30: Memo: Free Cash Flow (for Capital Allocation Policy)
A31: Free cash flow = CFO − Capex | C31: =C12-C15 -> 23009 | D31: =D12-D15 -> 33457 | E31: =E12-E15 -> 31259 | F31: =F12-F15 -> 28638.232 | G31: =G12-G15 -> 31657.867 | H31: =H12-H15 -> 34902.131 | I31: =I12-I15 -> 38588.018 | J31: =J12-J15 -> 42188.779
A32: Total shareholder payout = Dividends + Buyback | C32: =C20+C21 -> 14692 | D32: =D20+D21 -> 20287 | E32: =E20+E21 -> 36711 | F32: =F31*Assumptions!F27 -> 24342.498 | G32: =G31*Assumptions!G27 -> 26909.187 | H32: =H31*Assumptions!H27 -> 29666.811 | I32: =I31*Assumptions!I27 -> 32799.815 | J32: =J31*Assumptions!J27 -> 35860.462
A33: Payout, % of Free Cash Flow | C33: =C32/C31 -> 0.63853275 | D33: =D32/D31 -> 0.6063604 | E33: =E32/E31 -> 1.1744138 | F33: =F32/F31 -> 0.85 | G33: =G32/G31 -> 0.85 | H33: =H32/H31 -> 0.85 | I33: =I32/I31 -> 0.85 | J33: =J32/J31 -> 0.85
A35: Note: Historical (FY24A-FY26A) CFO/CFI/CFF totals are as reported in the Consolidated Statement of Cash Flows, Infosys Integrated Annual Reports 2025-26 (p.325-326) and 2024-25 (p.310-311); intermediate reconciling lines are shown net as 'Other adjustments' for fidelity to the audited statement. Forecast years build CFO from Net Income + D&A + Finance cost add-back − Other income (moved to investing) +/− change in net working capital (from the WC & PPE Schedule); CFI reflects capex net of other income treated as investment yield; CFF reflects the 85% free-cash-flow payout policy (Assumptions tab), split illustratively 60% dividends / 40% buyback. Ending cash flows through to the Balance Sheet.

Sheet WC & PPE Schedule
A1: Infosys Limited — DCF Valuation Model
A2: Working Capital & Fixed Asset (PPE) Schedule | ₹ Crore | Fiscal Year ends March 31
A4: (₹ Crore, unless stated) | C4: FY2024A | D4: FY2025A | E4: FY2026A | F4: FY2027E | G4: FY2028E | H4: FY2029E | I4: FY2030E | J4: FY2031E
A5: 1. Working Capital Schedule
A6: Trade receivables (= Revenue × DSO / 365) | C6: 30193 | D6: 31158 | E6: 35234 | F6: ='Income Statement'!F5*Assumptions!F18/365 -> 37531.184 | G6: ='Income Statement'!G5*Assumptions!G18/365 -> 40721.334 | H6: ='Income Statement'!H5*Assumptions!H18/365 -> 44386.254 | I6: ='Income Statement'!I5*Assumptions!I18/365 -> 48381.017 | J6: ='Income Statement'!J5*Assumptions!J18/365 -> 52493.404
A7: Trade payables (= Revenue × DPO / 365) | C7: 3956 | D7: 4164 | E7: 4744 | F7: ='Income Statement'!F5*Assumptions!F19/365 -> 5021.7781 | G7: ='Income Statement'!G5*Assumptions!G19/365 -> 5448.6292 | H7: ='Income Statement'!H5*Assumptions!H19/365 -> 5939.0058 | I7: ='Income Statement'!I5*Assumptions!I19/365 -> 6473.5164 | J7: ='Income Statement'!J5*Assumptions!J19/365 -> 7023.7653
A8: Other current assets, net operating (= Revenue × % assumption) | C8: 31538 | D8: 29004 | E8: 33104 | F8: ='Income Statement'!F5*Assumptions!F20 -> 36658.98 | G8: ='Income Statement'!G5*Assumptions!G20 -> 39774.993 | H8: ='Income Statement'!H5*Assumptions!H20 -> 43354.743 | I8: ='Income Statement'!I5*Assumptions!I20 -> 47256.67 | J8: ='Income Statement'!J5*Assumptions!J20 -> 51273.486
A9: Other current liabilities, net operating (= Revenue × % assumption) | C9: 32879 | D9: 36231 | E9: 44418 | F9: ='Income Statement'!F5*Assumptions!F21 -> 48235.5 | G9: ='Income Statement'!G5*Assumptions!G21 -> 52335.518 | H9: ='Income Statement'!H5*Assumptions!H21 -> 57045.714 | I9: ='Income Statement'!I5*Assumptions!I21 -> 62179.828 | J9: ='Income Statement'!J5*Assumptions!J21 -> 67465.114
A10: Net operating working capital | C10: =C6+C8-C7-C9 -> 24896 | D10: =D6+D8-D7-D9 -> 19767 | E10: =E6+E8-E7-E9 -> 19176 | F10: =F6+F8-F7-F9 -> 20932.885 | G10: =G6+G8-G7-G9 -> 22712.181 | H10: =H6+H8-H7-H9 -> 24756.277 | I10: =I6+I8-I7-I9 -> 26984.342 | J10: =J6+J8-J7-J9 -> 29278.011
A11: (Increase) / decrease in net working capital — cash flow impact | C11: n/a | D11: =-(D10-C10) -> 5129 | E11: =-(E10-D10) -> 591 | F11: =-(F10-E10) -> -1756.8855 | G11: =-(G10-F10) -> -1779.2953 | H11: =-(H10-G10) -> -2044.0963 | I11: =-(I10-H10) -> -2228.0649 | J11: =-(J10-I10) -> -2293.6691
A13: 2. Property, Plant & Equipment (PPE) Roll-forward
A14: Opening PPE (gross block, net of depreciation) | C14: n/a | D14: =C17 -> 12370 | E14: =D17 -> 11778 | F14: =E17 -> 12651 | G14: =F17 -> 10335.696 | H14: =G17 -> 7823.5912 | I14: =H17 -> 5085.3969 | J14: =I17 -> 2100.7651
A15: (+) Capital expenditure (= Revenue × Capex % assumption) | C15: 2201 | D15: 2237 | E15: 2727 | F15: ='Income Statement'!F5*Assumptions!F24 -> 2894.13 | G15: ='Income Statement'!G5*Assumptions!G24 -> 3140.131 | H15: ='Income Statement'!H5*Assumptions!H24 -> 3422.7428 | I15: ='Income Statement'!I5*Assumptions!I24 -> 3730.7897 | J15: ='Income Statement'!J5*Assumptions!J24 -> 4047.9068
A16: (−) Depreciation & amortization (from Income Statement) | C16: =-'Income Statement'!C10 -> -4678 | D16: =-'Income Statement'!D10 -> -4812 | E16: =-'Income Statement'!E10 -> -4902 | F16: =-'Income Statement'!F10 -> -5209.434 | G16: =-'Income Statement'!G10 -> -5652.2359 | H16: =-'Income Statement'!H10 -> -6160.9371 | I16: =-'Income Statement'!I10 -> -6715.4215 | J16: =-'Income Statement'!J10 -> -7286.2323
A17: Closing PPE (net block) | C17: 12370 | D17: 11778 | E17: 12651 | F17: =F14+F15+F16 -> 10335.696 | G17: =G14+G15+G16 -> 7823.5912 | H17: =H14+H15+H16 -> 5085.3969 | I17: =I14+I15+I16 -> 2100.7651 | J17: =J14+J15+J16 -> -1137.5603
A19: 3. Other Fixed / Intangible Assets (held flat — no M&A assumed in forecast)
A20: Capital work-in-progress | C20: 293 | D20: 814 | E20: 526 | F20: =$E$20 -> 526 | G20: =$E$20 -> 526 | H20: =$E$20 -> 526 | I20: =$E$20 -> 526 | J20: =$E$20 -> 526
A21: Right-of-use assets | C21: 6552 | D21: 6311 | E21: 6177 | F21: =$E$21 -> 6177 | G21: =$E$21 -> 6177 | H21: =$E$21 -> 6177 | I21: =$E$21 -> 6177 | J21: =$E$21 -> 6177
A22: Goodwill | C22: 7303 | D22: 10106 | E22: 12117 | F22: =$E$22 -> 12117 | G22: =$E$22 -> 12117 | H22: =$E$22 -> 12117 | I22: =$E$22 -> 12117 | J22: =$E$22 -> 12117
A23: Other intangible assets | C23: 1397 | D23: 2766 | E23: 2825 | F23: =$E$23 -> 2825 | G23: =$E$23 -> 2825 | H23: =$E$23 -> 2825 | I23: =$E$23 -> 2825 | J23: =$E$23 -> 2825
A25: Note: Trade receivables and payables are forecast using Days Sales/Payable Outstanding on the Assumptions tab; other net operating current assets/liabilities are forecast as a % of revenue. PPE rolls forward from the FY26A closing balance using assumption-driven capex less Income-Statement depreciation & amortization. Capital work-in-progress, right-of-use assets, goodwill and other intangibles are held flat at FY26A levels for the explicit forecast period — i.e., no new acquisitions, leases or impairments are assumed. FY24A-FY26A figures per Consolidated Balance Sheet and Statement of Cash Flows, Infosys Integrated Annual Reports 2025-26 and 2024-25.

Sheet Capital Structure
A1: Infosys Limited — DCF Valuation Model
A2: Capital Structure Schedule & WACC Support | ₹ Crore | As at March 31, 2026 (unless noted)
A4: (₹ Crore, unless stated) | C4: FY2024A | D4: FY2025A | E4: FY2026A | F4: FY2027E | G4: FY2028E | H4: FY2029E | I4: FY2030E | J4: FY2031E
A5: 1. Debt-like Obligations (Infosys carries no financial borrowings — only IFRS 16 lease liabilities)
A6: Lease liabilities, non-current | C6: 6400 | D6: 5772 | E6: 6016 | F6: =$E$6 -> 6016 | G6: =$E$6 -> 6016 | H6: =$E$6 -> 6016 | I6: =$E$6 -> 6016 | J6: =$E$6 -> 6016
A7: Lease liabilities, current | C7: 1959 | D7: 2455 | E7: 3160 | F7: =$E$7 -> 3160 | G7: =$E$7 -> 3160 | H7: =$E$7 -> 3160 | I7: =$E$7 -> 3160 | J7: =$E$7 -> 3160
A8: Total debt (lease liabilities) | C8: =C6+C7 -> 8359 | D8: =D6+D7 -> 8227 | E8: =E6+E7 -> 9176 | F8: =F6+F7 -> 9176 | G8: =G6+G7 -> 9176 | H8: =H6+H7 -> 9176 | I8: =I6+I7 -> 9176 | J8: =J6+J7 -> 9176
A10: 2. Cash & Investments (non-operating)
A11: Cash and cash equivalents | C11: 14786 | D11: 24455 | E11: 22201 | F11: ='Balance Sheet'!F19 -> 30741.459 | G11: ='Balance Sheet'!G19 -> 40095.664 | H11: ='Balance Sheet'!H19 -> 50351.007 | I11: ='Balance Sheet'!I19 -> 61611.035 | J11: ='Balance Sheet'!J19 -> 73876.281
A12: Current investments | C12: 12915 | D12: 12482 | E12: 12950 | F12: =$E$12 -> 12950 | G12: =$E$12 -> 12950 | H12: =$E$12 -> 12950 | I12: =$E$12 -> 12950 | J12: =$E$12 -> 12950
A13: Non-current investments | C13: 11708 | D13: 11059 | E13: 8930 | F13: =$E$13 -> 8930 | G13: =$E$13 -> 8930 | H13: =$E$13 -> 8930 | I13: =$E$13 -> 8930 | J13: =$E$13 -> 8930
A14: Other financial assets, current (deposits, etc.) | C14: 12085 | D14: 13840 | E14: 15890 | F14: =$E$14 -> 15890 | G14: =$E$14 -> 15890 | H14: =$E$14 -> 15890 | I14: =$E$14 -> 15890 | J14: =$E$14 -> 15890
A15: Other financial assets, non-current (deposits, etc.) | C15: 3105 | D15: 3511 | E15: 2776 | F15: =$E$15 -> 2776 | G15: =$E$15 -> 2776 | H15: =$E$15 -> 2776 | I15: =$E$15 -> 2776 | J15: =$E$15 -> 2776
A16: Total cash & investments | C16: =C11+C12+C13+C14+C15 -> 54599 | D16: =D11+D12+D13+D14+D15 -> 65347 | E16: =E11+E12+E13+E14+E15 -> 62747 | F16: =F11+F12+F13+F14+F15 -> 71287.459 | G16: =G11+G12+G13+G14+G15 -> 80641.664 | H16: =H11+H12+H13+H14+H15 -> 90897.007 | I16: =I11+I12+I13+I14+I15 -> 102157.03 | J16: =J11+J12+J13+J14+J15 -> 114422.28
A17: Net cash / (debt) = Total cash & investments − Total debt | C17: =C16-C8 -> 46240 | D17: =D16-D8 -> 57120 | E17: =E16-E8 -> 53571 | F17: =F16-F8 -> 62111.459 | G17: =G16-G8 -> 71465.664 | H17: =H16-H8 -> 81721.007 | I17: =I16-I8 -> 92981.035 | J17: =J16-J8 -> 105246.28
A19: 3. Equity Market Value & Capital Weights
A20: Equity market value (current share price × diluted shares) | D20: =Assumptions!D48 -> 481712
A21: Debt market value (lease liabilities, book value proxy) | D21: =E8 -> 9176
A22: Total capital (Debt + Equity) | D22: =D20+D21 -> 490888
A23: Weight of debt, % = Debt / Total capital | D23: =D21/D22 -> 0.018692655
A24: Weight of equity, % = Equity / Total capital | D24: =D20/D22 -> 0.98130735
A26: 4. Credit Profile Commentary
A27: Infosys has maintained a debt-free balance sheet across FY24-FY26, funding operations, capex and shareholder returns entirely from internally generated cash flow. The only liabilities resembling debt are IFRS 16 / Ind AS 116 lease liabilities relating to leased office premises. Given the absence of financial borrowings, WACC in this model is driven predominantly by the cost of equity, with a small weighting to the after-tax cost of the lease obligation. This is consistent with Infosys’ stated AAA-rated, debt-free capital allocation philosophy (Infosys Integrated Annual Report 2025-26).

Sheet DCF Valuation
A1: Infosys Limited — DCF Valuation Model
A2: Discounted Cash Flow (Unlevered FCFF) Valuation Summary | ₹ Crore, except per-share data
A4: (₹ Crore, unless stated) | C4: FY2027E | D4: FY2028E | E4: FY2029E | F4: FY2030E | G4: FY2031E
A5: 1. Unlevered Free Cash Flow to Firm (FCFF) Build-up
A6: EBIT (Operating profit) | C6: ='Income Statement'!F14 -> 40517.82 | D6: ='Income Statement'!G14 -> 44589.861 | E6: ='Income Statement'!H14 -> 49287.497 | F6: ='Income Statement'!I14 -> 54469.53 | G6: ='Income Statement'!J14 -> 59369.3
A7: (−) Tax on EBIT (at effective tax rate) | C7: =C6*Assumptions!F14 -> 10939.811 | D7: =D6*Assumptions!G14 -> 12039.262 | E7: =E6*Assumptions!H14 -> 13307.624 | F7: =F6*Assumptions!I14 -> 14706.773 | G7: =G6*Assumptions!J14 -> 16029.711
A8: NOPAT (EBIT after tax) | C8: =C6-C7 -> 29578.009 | D8: =D6-D7 -> 32550.598 | E8: =E6-E7 -> 35979.873 | F8: =F6-F7 -> 39762.757 | G8: =G6-G7 -> 43339.589
A9: (+) Depreciation & amortization | C9: ='Income Statement'!F10 -> 5209.434 | D9: ='Income Statement'!G10 -> 5652.2359 | E9: ='Income Statement'!H10 -> 6160.9371 | F9: ='Income Statement'!I10 -> 6715.4215 | G9: ='Income Statement'!J10 -> 7286.2323
A10: (−) Capital expenditure | C10: ='WC & PPE Schedule'!F15 -> 2894.13 | D10: ='WC & PPE Schedule'!G15 -> 3140.131 | E10: ='WC & PPE Schedule'!H15 -> 3422.7428 | F10: ='WC & PPE Schedule'!I15 -> 3730.7897 | G10: ='WC & PPE Schedule'!J15 -> 4047.9068
A11: (+/−) Change in net working capital | C11: ='WC & PPE Schedule'!F11 -> -1756.8855 | D11: ='WC & PPE Schedule'!G11 -> -1779.2953 | E11: ='WC & PPE Schedule'!H11 -> -2044.0963 | F11: ='WC & PPE Schedule'!I11 -> -2228.0649 | G11: ='WC & PPE Schedule'!J11 -> -2293.6691
A12: Unlevered Free Cash Flow to Firm (FCFF) | C12: =C8+C9-C10+C11 -> 30136.427 | D12: =D8+D9-D10+D11 -> 33283.408 | E12: =E8+E9-E10+E11 -> 36673.971 | F12: =F8+F9-F10+F11 -> 40519.323 | G12: =G8+G9-G10+G11 -> 44284.245
A14: 2. Discounting
A15: Discount period (years from valuation date) | C15: 1 | D15: 2 | E15: 3 | F15: 4 | G15: 5
A16: Discount factor = 1 / (1+WACC)^n | C16: =1/(1+Assumptions!$D$39)^C15 -> 0.88471252 | D16: =1/(1+Assumptions!$D$39)^D15 -> 0.78271625 | E16: =1/(1+Assumptions!$D$39)^E15 -> 0.69247887 | F16: =1/(1+Assumptions!$D$39)^F15 -> 0.61264472 | G16: =1/(1+Assumptions!$D$39)^G15 -> 0.54201446
A17: Present value of FCFF | C17: =C12*C16 -> 26662.074 | D17: =D12*D16 -> 26051.464 | E17: =E12*E16 -> 25395.95 | F17: =F12*F16 -> 24823.95 | G17: =G12*G16 -> 24002.701
A19: 3. Terminal Value
A20: Terminal-year FCFF (FY2031E) | D20: =G12 -> 44284.245
A21: Terminal Value (undiscounted) = FCFF×(1+g) / (WACC−g) | D21: =D20*(1+Assumptions!$D$42)/(Assumptions!$D$39-Assumptions!$D$42) -> 578982.35
A22: Terminal discount factor (Year 5) | D22: =G16 -> 0.54201446
A23: Present value of Terminal Value | D23: =D21*D22 -> 313816.8
A25: 4. Enterprise Value to Equity Value Bridge
A26: Sum of PV of explicit-period FCFF (FY27E-FY31E) | D26: =SUM(C17:G17) -> 126936.14
A27: (+) PV of Terminal Value | D27: =D23 -> 313816.8
A28: Enterprise Value | D28: =D26+D27 -> 440752.94
A29: Terminal Value as % of Enterprise Value | D29: =D27/D28 -> 0.71200161
A31: (+) Cash & investments (non-operating, as at Mar 31, 2026) | D31: ='Capital Structure'!$E$16 -> 62747
A32: (−) Total debt (lease liabilities, as at Mar 31, 2026) | D32: ='Capital Structure'!$E$8 -> 9176
A33: (−) Non-controlling interests (as at Mar 31, 2026) | D33: ='Balance Sheet'!$E$29 -> 445
A34: Equity Value attributable to owners | D34: =D28+D31-D32-D33 -> 493878.94
A36: ÷ Diluted shares outstanding (crore) | D36: =Assumptions!$D$47 -> 404.8
A37: Intrinsic Value per Share (₹) | D37: =D34/D36 -> 1220.0567
A39: 5. Valuation Football Field vs. Market Price
A40: Current market price (Aug 10, 2026) | D40: =Assumptions!$D$46 -> 1190
A41: Upside / (Downside) to intrinsic value, % | D41: =D37/D40-1 -> 0.025257713
A42: Verdict | D42: =IF(D41>0.15,"UNDERVALUED",IF(D41<-0.15,"OVERVALUED","FAIRLY VALUED")) -> FAIRLY VALUED
A44: 6. Sensitivity — Intrinsic Value per Share (₹)
A45: Intrinsic Value per Share (₹) — WACC (rows) × Terminal Growth Rate (columns)
B46: WACC / g | C46: =Assumptions!$D$42+(-0.01) -> 0.04 | D46: =Assumptions!$D$42+(-0.005) -> 0.045 | E46: =Assumptions!$D$42+(0) -> 0.05 | F46: =Assumptions!$D$42+(0.005) -> 0.055 | G46: =Assumptions!$D$42+(0.01) -> 0.06
B47: =Assumptions!$D$39+(-0.01) -> 0.12031067 | C47: =((C12/(1+$B47)^1+D12/(1+$B47)^2+E12/(1+$B47)^3+F12/(1+$B47)^4+G12/(1+$B47)^5+(G12*(1+C$46)/($B47-C$46))/(1+$B47)^5)+'Capital Structure'!$E$16-'Capital Structure'!$E$8-'Balance Sheet'!$E$29)/Assumptions!$D$47 -> 1255.9105 | D47: =((C12/(1+$B47)^1+D12/(1+$B47)^2+E12/(1+$B47)^3+F12/(1+$B47)^4+G12/(1+$B47)^5+(G12*(1+D$46)/($B47-D$46))/(1+$B47)^5)+'Capital Structure'!$E$16-'Capital Structure'!$E$8-'Balance Sheet'!$E$29)/Assumptions!$D$47 -> 1313.3215 | E47: =((C12/(1+$B47)^1+D12/(1+$B47)^2+E12/(1+$B47)^3+F12/(1+$B47)^4+G12/(1+$B47)^5+(G12*(1+E$46)/($B47-E$46))/(1+$B47)^5)+'Capital Structure'!$E$16-'Capital Structure'!$E$8-'Balance Sheet'!$E$29)/Assumptions!$D$47 -> 1378.8979 | F47: =((C12/(1+$B47)^1+D12/(1+$B47)^2+E12/(1+$B47)^3+F12/(1+$B47)^4+G12/(1+$B47)^5+(G12*(1+F$46)/($B47-F$46))/(1+$B47)^5)+'Capital Structure'!$E$16-'Capital Structure'!$E$8-'Balance Sheet'!$E$29)/Assumptions!$D$47 -> 1454.5149 | G47: =((C12/(1+$B47)^1+D12/(1+$B47)^2+E12/(1+$B47)^3+F12/(1+$B47)^4+G12/(1+$B47)^5+(G12*(1+G$46)/($B47-G$46))/(1+$B47)^5)+'Capital Structure'!$E$16-'Capital Structure'!$E$8-'Balance Sheet'!$E$29)/Assumptions!$D$47 -> 1542.6698
B48: =Assumptions!$D$39+(-0.005) -> 0.12531067 | C48: =((C12/(1+$B48)^1+D12/(1+$B48)^2+E12/(1+$B48)^3+F12/(1+$B48)^4+G12/(1+$B48)^5+(G12*(1+C$46)/($B48-C$46))/(1+$B48)^5)+'Capital Structure'!$E$16-'Capital Structure'!$E$8-'Balance Sheet'!$E$29)/Assumptions!$D$47 -> 1188.0043 | D48: =((C12/(1+$B48)^1+D12/(1+$B48)^2+E12/(1+$B48)^3+F12/(1+$B48)^4+G12/(1+$B48)^5+(G12*(1+D$46)/($B48-D$46))/(1+$B48)^5)+'Capital Structure'!$E$16-'Capital Structure'!$E$8-'Balance Sheet'!$E$29)/Assumptions!$D$47 -> 1237.7909 | E48: =((C12/(1+$B48)^1+D12/(1+$B48)^2+E12/(1+$B48)^3+F12/(1+$B48)^4+G12/(1+$B48)^5+(G12*(1+E$46)/($B48-E$46))/(1+$B48)^5)+'Capital Structure'!$E$16-'Capital Structure'!$E$8-'Balance Sheet'!$E$29)/Assumptions!$D$47 -> 1294.1883 | F48: =((C12/(1+$B48)^1+D12/(1+$B48)^2+E12/(1+$B48)^3+F12/(1+$B48)^4+G12/(1+$B48)^5+(G12*(1+F$46)/($B48-F$46))/(1+$B48)^5)+'Capital Structure'!$E$16-'Capital Structure'!$E$8-'Balance Sheet'!$E$29)/Assumptions!$D$47 -> 1358.6069 | G48: =((C12/(1+$B48)^1+D12/(1+$B48)^2+E12/(1+$B48)^3+F12/(1+$B48)^4+G12/(1+$B48)^5+(G12*(1+G$46)/($B48-G$46))/(1+$B48)^5)+'Capital Structure'!$E$16-'Capital Structure'!$E$8-'Balance Sheet'!$E$29)/Assumptions!$D$47 -> 1432.8889
B49: =Assumptions!$D$39+(0) -> 0.13031067 | C49: =((C12/(1+$B49)^1+D12/(1+$B49)^2+E12/(1+$B49)^3+F12/(1+$B49)^4+G12/(1+$B49)^5+(G12*(1+C$46)/($B49-C$46))/(1+$B49)^5)+'Capital Structure'!$E$16-'Capital Structure'!$E$8-'Balance Sheet'!$E$29)/Assumptions!$D$47 -> 1127.6496 | D49: =((C12/(1+$B49)^1+D12/(1+$B49)^2+E12/(1+$B49)^3+F12/(1+$B49)^4+G12/(1+$B49)^5+(G12*(1+D$46)/($B49-D$46))/(1+$B49)^5)+'Capital Structure'!$E$16-'Capital Structure'!$E$8-'Balance Sheet'!$E$29)/Assumptions!$D$47 -> 1171.1452 | E49: =((C12/(1+$B49)^1+D12/(1+$B49)^2+E12/(1+$B49)^3+F12/(1+$B49)^4+G12/(1+$B49)^5+(G12*(1+E$46)/($B49-E$46))/(1+$B49)^5)+'Capital Structure'!$E$16-'Capital Structure'!$E$8-'Balance Sheet'!$E$29)/Assumptions!$D$47 -> 1220.0567 | F49: =((C12/(1+$B49)^1+D12/(1+$B49)^2+E12/(1+$B49)^3+F12/(1+$B49)^4+G12/(1+$B49)^5+(G12*(1+F$46)/($B49-F$46))/(1+$B49)^5)+'Capital Structure'!$E$16-'Capital Structure'!$E$8-'Balance Sheet'!$E$29)/Assumptions!$D$47 -> 1275.4628 | G49: =((C12/(1+$B49)^1+D12/(1+$B49)^2+E12/(1+$B49)^3+F12/(1+$B49)^4+G12/(1+$B49)^5+(G12*(1+G$46)/($B49-G$46))/(1+$B49)^5)+'Capital Structure'!$E$16-'Capital Structure'!$E$8-'Balance Sheet'!$E$29)/Assumptions!$D$47 -> 1338.7491
B50: =Assumptions!$D$39+(0.005) -> 0.13531067 | C50: =((C12/(1+$B50)^1+D12/(1+$B50)^2+E12/(1+$B50)^3+F12/(1+$B50)^4+G12/(1+$B50)^5+(G12*(1+C$46)/($B50-C$46))/(1+$B50)^5)+'Capital Structure'!$E$16-'Capital Structure'!$E$8-'Balance Sheet'!$E$29)/Assumptions!$D$47 -> 1073.6574 | D50: =((C12/(1+$B50)^1+D12/(1+$B50)^2+E12/(1+$B50)^3+F12/(1+$B50)^4+G12/(1+$B50)^5+(G12*(1+D$46)/($B50-D$46))/(1+$B50)^5)+'Capital Structure'!$E$16-'Capital Structure'!$E$8-'Balance Sheet'!$E$29)/Assumptions!$D$47 -> 1111.908 | E50: =((C12/(1+$B50)^1+D12/(1+$B50)^2+E12/(1+$B50)^3+F12/(1+$B50)^4+G12/(1+$B50)^5+(G12*(1+E$46)/($B50-E$46))/(1+$B50)^5)+'Capital Structure'!$E$16-'Capital Structure'!$E$8-'Balance Sheet'!$E$29)/Assumptions!$D$47 -> 1154.6424 | F50: =((C12/(1+$B50)^1+D12/(1+$B50)^2+E12/(1+$B50)^3+F12/(1+$B50)^4+G12/(1+$B50)^5+(G12*(1+F$46)/($B50-F$46))/(1+$B50)^5)+'Capital Structure'!$E$16-'Capital Structure'!$E$8-'Balance Sheet'!$E$29)/Assumptions!$D$47 -> 1202.698 | G50: =((C12/(1+$B50)^1+D12/(1+$B50)^2+E12/(1+$B50)^3+F12/(1+$B50)^4+G12/(1+$B50)^5+(G12*(1+G$46)/($B50-G$46))/(1+$B50)^5)+'Capital Structure'!$E$16-'Capital Structure'!$E$8-'Balance Sheet'!$E$29)/Assumptions!$D$47 -> 1257.1345
B51: =Assumptions!$D$39+(0.01) -> 0.14031067 | C51: =((C12/(1+$B51)^1+D12/(1+$B51)^2+E12/(1+$B51)^3+F12/(1+$B51)^4+G12/(1+$B51)^5+(G12*(1+C$46)/($B51-C$46))/(1+$B51)^5)+'Capital Structure'!$E$16-'Capital Structure'!$E$8-'Balance Sheet'!$E$29)/Assumptions!$D$47 -> 1025.0755 | D51: =((C12/(1+$B51)^1+D12/(1+$B51)^2+E12/(1+$B51)^3+F12/(1+$B51)^4+G12/(1+$B51)^5+(G12*(1+D$46)/($B51-D$46))/(1+$B51)^5)+'Capital Structure'!$E$16-'Capital Structure'!$E$8-'Balance Sheet'!$E$29)/Assumptions!$D$47 -> 1058.9129 | E51: =((C12/(1+$B51)^1+D12/(1+$B51)^2+E12/(1+$B51)^3+F12/(1+$B51)^4+G12/(1+$B51)^5+(G12*(1+E$46)/($B51-E$46))/(1+$B51)^5)+'Capital Structure'!$E$16-'Capital Structure'!$E$8-'Balance Sheet'!$E$29)/Assumptions!$D$47 -> 1096.4971 | F51: =((C12/(1+$B51)^1+D12/(1+$B51)^2+E12/(1+$B51)^3+F12/(1+$B51)^4+G12/(1+$B51)^5+(G12*(1+F$46)/($B51-F$46))/(1+$B51)^5)+'Capital Structure'!$E$16-'Capital Structure'!$E$8-'Balance Sheet'!$E$29)/Assumptions!$D$47 -> 1138.4869 | G51: =((C12/(1+$B51)^1+D12/(1+$B51)^2+E12/(1+$B51)^3+F12/(1+$B51)^4+G12/(1+$B51)^5+(G12*(1+G$46)/($B51-G$46))/(1+$B51)^5)+'Capital Structure'!$E$16-'Capital Structure'!$E$8-'Balance Sheet'!$E$29)/Assumptions!$D$47 -> 1185.7051
A53: Sensitivity table recomputes Enterprise Value and Equity Value at each WACC/terminal-growth-rate combination, holding the explicit-period FCFF forecast (FY27E-FY31E) constant, then divides by diluted shares outstanding. Base case (highlighted) matches Section 4 above.

Sheet Charts & Outputs
A1: Infosys Limited — DCF Valuation Model
A2: Charts & Key Outputs Summary
A5: Intrinsic Value / Share | C5: Current Market Price | E5: Upside / (Downside) | G5: WACC | I5: Terminal Growth Rate | K5: Enterprise Value (₹ cr)
A6: ='DCF Valuation'!D37 -> 1220.0567 | C6: ='DCF Valuation'!D40 -> 1190 | E6: ='DCF Valuation'!D41 -> 0.025257713 | G6: =Assumptions!D39 -> 0.13031067 | I6: =Assumptions!D42 -> 0.05 | K6: ='DCF Valuation'!D28 -> 440752.94
A9: Chart Data Tables (feed the charts below — do not delete)
A10: (₹ Crore, unless stated) | C10: FY2024A | D10: FY2025A | E10: FY2026A | F10: FY2027E | G10: FY2028E | H10: FY2029E | I10: FY2030E | J10: FY2031E
A11: Revenue (₹ cr) | C11: ='Income Statement'!C5 -> 153670 | D11: ='Income Statement'!D5 -> 162990 | E11: ='Income Statement'!E5 -> 178650 | F11: ='Income Statement'!F5 -> 192942 | G11: ='Income Statement'!G5 -> 209342.07 | H11: ='Income Statement'!H5 -> 228182.86 | I11: ='Income Statement'!I5 -> 248719.31 | J11: ='Income Statement'!J5 -> 269860.46
A12: EBIT margin (%) | C12: ='Income Statement'!C15 -> 0.20659205 | D12: ='Income Statement'!D15 -> 0.21120314 | E12: ='Income Statement'!E15 -> 0.20922474 | F12: ='Income Statement'!F15 -> 0.21 | G12: ='Income Statement'!G15 -> 0.213 | H12: ='Income Statement'!H15 -> 0.216 | I12: ='Income Statement'!I15 -> 0.219 | J12: ='Income Statement'!J15 -> 0.22
A13: PAT attributable to owners (₹ cr) | C13: ='Income Statement'!C28 -> 26233 | D13: ='Income Statement'!D28 -> 26713 | E13: ='Income Statement'!E28 -> 29440 | F13: ='Income Statement'!F28 -> 32282.516 | G13: ='Income Statement'!G28 -> 35484.393 | H13: ='Income Statement'!H28 -> 39177.059 | I13: ='Income Statement'!I28 -> 43246.982 | J13: ='Income Statement'!J28 -> 47119.717
A14: Free Cash Flow (₹ cr) | C14: ='Cash Flow'!C31 -> 23009 | D14: ='Cash Flow'!D31 -> 33457 | E14: ='Cash Flow'!E31 -> 31259 | F14: ='Cash Flow'!F31 -> 28638.232 | G14: ='Cash Flow'!G31 -> 31657.867 | H14: ='Cash Flow'!H31 -> 34902.131 | I14: ='Cash Flow'!I31 -> 38588.018 | J14: ='Cash Flow'!J31 -> 42188.779
A15: Cash & investments, closing (₹ cr) | C15: ='Cash Flow'!C28 -> 14786 | D15: ='Cash Flow'!D28 -> 24455 | E15: ='Cash Flow'!E28 -> 22201 | F15: ='Cash Flow'!F28 -> 30741.459 | G15: ='Cash Flow'!G28 -> 40095.664 | H15: ='Cash Flow'!H28 -> 50351.007 | I15: ='Cash Flow'!I28 -> 61611.035 | J15: ='Cash Flow'!J28 -> 73876.281
A17: Valuation Bridge Data
A18: PV of Explicit FCFF (FY27-31) | B18: ='DCF Valuation'!D26 -> 126936.14
A19: PV of Terminal Value | B19: ='DCF Valuation'!D27 -> 313816.8
A20: Enterprise Value | B20: ='DCF Valuation'!D28 -> 440752.94
A21: (+) Cash & Investments | B21: ='DCF Valuation'!D31 -> 62747
A22: (-) Total Debt | B22: =-'DCF Valuation'!D32 -> -9176
A23: (-) NCI | B23: =-'DCF Valuation'!D33 -> -445
A24: Equity Value | B24: ='DCF Valuation'!D34 -> 493878.94
A27: WACC Sensitivity Data (at base terminal growth)
A28: ='DCF Valuation'!B47 -> 0.12031067 | B28: ='DCF Valuation'!E47 -> 1378.8979
A29: ='DCF Valuation'!B48 -> 0.12531067 | B29: ='DCF Valuation'!E48 -> 1294.1883
A30: ='DCF Valuation'!B49 -> 0.13031067 | B30: ='DCF Valuation'!E49 -> 1220.0567
A31: ='DCF Valuation'!B50 -> 0.13531067 | B31: ='DCF Valuation'!E50 -> 1154.6424
A32: ='DCF Valuation'!B51 -> 0.14031067 | B32: ='DCF Valuation'!E51 -> 1096.4971
